Workbook

Sheet Plan stratégique  likewatt
A2: Plan stratégique
A5: Résumé stratégie
A6: Le plan stratégique est articulé autour de 3 axes : - la structuration et le renforcement de l'action commerciale et du marketing, avec un focus particulier sur Optiwize Leads - l'amélioration du produit (amélioration continue, extension fonctionnelle métier pour les installateurs et les developpeurs, batiment neufs et pilotage en production) - l'internationalisation vers l'Europe (adaption des produits aux spécificités nationales, filiales commerciales ES/CH/BE/DE)
A12: Milestones clés
A13: - Financement amélioration produit et développements spécifiques nationaux (500 k€) - Série A en 2027 entre 2,5 et 3M€ permettant de lancer l'internationalisation et l'accélération commerciale en France
A19: Scénario d'investissement
A20: Le scénario d'investissement privilégié est : Phase 1 : investissement produit et commercial suite à l'obtention d'un financement de 500 k€ sous forme de prêt. Phase 2 : Série A permettant de financer l'internationalisation et le renforcement commercial/marketing En l'absence de série A, le développement commercial se concentrera sur la France autour de Leads et des nouveaux produits.
A27: Scénario financier
A28: Selon le scénario standard privilégié d'une série A en juin 2027, la société générerait 43 M€ de revenus récurrents en 2032 (EBITDA à 49%). Le scénario conservateur prévoir 23M€ d'ARR et 23% d'EBITDA. Un décalge d'un des investissements en CH/BE/DE sera nécessaire ou un financemnt complémentaire de 500 k€. Dans le scénario standard alternatif d'une absence de série A, la société générerait 4,6 M€ de revenus en 2032 (EBITDA à 46%). Le scénario conservateur prévoir 2,4M€ d'ARR et 15% d'EBITDA avec un enjeu de trésorerie en S2 2027 en raison notamment du remboursement FTS. Un décalage des investissement R&D et marketing et le gel des recrutements sur une période de 18 mois ou un refinancemement seront nécessaire
B37: Scénarisation | F37: Stratégie investissement
B38: Acquisition Optiwize Pro | C38: Standard | F38: Début WP 3 R&D | G38: ='Annexe E Financement'!$B$20 -> 46082
B39: Modèle Leads | C39: Simulation | F39: Début ES | G39: =G43 -> 47515
B40: Adoption Leads | C40: Standard | F40: Début CH | G40: =G39+366 -> 47881
B41: Churn | C41: Standard | F41: Début BE | G41: =G40+366 -> 48247
B42: Montant levée | C42: 0 | F42: Début DE | G42: =G41+366 -> 48613
B43: Date levée | C43: 47515 | D43: 0 | F43: Début phase 2 FR | G43: =C43 -> 47515
B44: Point bas | C44: ='Prévisionnel annuel'!O10 -> 201756.47
B45: Date Point bas | C45: =Trésorerie!D32 -> 46722
B47: Date trésorerie négative | C47: =_xlfn.IFNA(Trésorerie!C33,"Pas avant 2032") -> Pas avant 2032

Sheet KPI
C3: Vente Optiwize Pro | D3: Adoption Leads | E3: Churn | G3: Modèle Leads | H3: Montant levée
B4: Scénario : | C4: ='Prévisionnel annuel'!O3 -> Standard | D4: ='Prévisionnel annuel'!O5 -> Standard | E4: ='Prévisionnel annuel'!O6 -> Standard | G4: ='Prévisionnel annuel'!O4 -> Simulation | H4: ='Prévisionnel annuel'!O7 -> 0
C8: 2025 | D8: 2026 | E8: 2027 | F8: 2028 | G8: 2029 | H8: 2030 | I8: 2031
B9: ARR (EoY) | C9: =C10+C11 -> 660000 | D9: =D10+D11 -> 836912.94 | E9: =E10+E11 -> 1213042.5 | F9: =F10+F11 -> 1704444.6 | G9: =G10+G11 -> 2329801.8 | H9: =H10+H11 -> 4016646.1 | I9: =I10+I11 -> 10524398
B10: ARR Optiwize Pro | C10: ='Prévisionnel annuel'!D6 -> 650000 | D10: =SUM(Ventes!J4:U4) -> 810992.44 | E10: =SUM(OFFSET(Ventes!$J4:$U4,0,12)) -> 1120863.3 | F10: =SUM(OFFSET(Ventes!$J4:$U4,0,24)) -> 1435720.1 | G10: =SUM(OFFSET(Ventes!$J4:$U4,0,36)) -> 1771593.8 | H10: =SUM(OFFSET(Ventes!$J4:$U4,0,48)) -> 2782173.8 | I10: =SUM(OFFSET(Ventes!$J4:$U4,0,60)) -> 6775579
B11: ARR Leads | C11: ='Prévisionnel annuel'!D7 -> 10000 | D11: =SUM(Ventes!J8:U8) -> 25920.503 | E11: =SUM(OFFSET(Ventes!$J8:$U8,0,12)) -> 92179.136 | F11: =SUM(OFFSET(Ventes!$J8:$U8,0,24)) -> 268724.54 | G11: =SUM(OFFSET(Ventes!$J8:$U8,0,36)) -> 558208.08 | H11: =SUM(OFFSET(Ventes!$J8:$U8,0,48)) -> 1234472.3 | I11: =SUM(OFFSET(Ventes!$J8:$U8,0,60)) -> 3748819.1
B12: # Clients (EoY) | C12: =C13 -> 177.65663 | D12: =D13 -> 224.53008 | E12: =E13 -> 284.65376 | F12: =F13 -> 348.07281 | G12: =G13 -> 416.73121 | H12: =H13 -> 826.35106 | I12: =I13 -> 2128.5565
B13: # Clients Optiwize Pro (EoY) | C13: =Ventes!I19 -> 177.65663 | D13: =Ventes!U19 -> 224.53008 | E13: =OFFSET(Ventes!$U$19,0,12) -> 284.65376 | F13: =OFFSET(Ventes!$U$19,0,24) -> 348.07281 | G13: =OFFSET(Ventes!$U$19,0,36) -> 416.73121 | H13: =OFFSET(Ventes!$U$19,0,48) -> 826.35106 | I13: =OFFSET(Ventes!$U$19,0,60) -> 2128.5565
B14: % Upsell Leads | C14: =Hypothèses!B71 -> 0.05 | D14: =Hypothèses!C71 -> 0.1 | E14: =Hypothèses!D71 -> 0.25 | F14: =Hypothèses!E71 -> 0.45 | G14: =Hypothèses!F71 -> 0.6 | H14: =Hypothèses!G71 -> 0.65 | I14: =Hypothèses!H71 -> 0.65
B15: % Projets simulés | C15: =Hypothèses!B72 -> 0.08 | D15: =Hypothèses!C72 -> 0.09 | E15: =Hypothèses!D72 -> 0.12 | F15: =Hypothèses!E72 -> 0.18 | G15: =Hypothèses!F72 -> 0.25 | H15: =Hypothèses!G72 -> 0.35 | I15: =Hypothèses!H72 -> 0.45
B16: EBITDA | C16: ='Prévisionnel annuel'!D14/'Prévisionnel annuel'!D5 -> -0.0628 | D16: ='Prévisionnel annuel'!E14/'Prévisionnel annuel'!E5 -> -0.32722408 | E16: ='Prévisionnel annuel'!F14/'Prévisionnel annuel'!F5 -> -0.15925648 | F16: ='Prévisionnel annuel'!G14/'Prévisionnel annuel'!G5 -> 0.090617986 | G16: ='Prévisionnel annuel'!H14/'Prévisionnel annuel'!H5 -> 0.22071401 | H16: ='Prévisionnel annuel'!I14/'Prévisionnel annuel'!I5 -> 0.037005179 | I16: ='Prévisionnel annuel'!J14/'Prévisionnel annuel'!J5 -> 0.25646799
B17: Trésorerie (EoY) | C17: =Trésorerie!I15 -> 471063.09 | D17: =OFFSET(Trésorerie!$I15,0,12) -> 494393.5 | E17: =OFFSET(Trésorerie!$I15,0,24) -> 201756.47 | F17: =OFFSET(Trésorerie!$I15,0,36) -> 460489.32 | G17: =OFFSET(Trésorerie!$I15,0,48) -> 1044551 | H17: =OFFSET(Trésorerie!$I15,0,60) -> 1284612.5 | I17: =OFFSET(Trésorerie!$I15,0,72) -> 3945708.3
B18: Equipe (EoY) | C18: ='Annexe A Plan RH'!$W92 -> 11 | D18: =OFFSET('Annexe A Plan RH'!$W92,0,12) -> 15 | E18: =OFFSET('Annexe A Plan RH'!$W92,0,24) -> 15 | F18: =OFFSET('Annexe A Plan RH'!$W92,0,36) -> 15 | G18: =OFFSET('Annexe A Plan RH'!$W92,0,48) -> 18 | H18: =OFFSET('Annexe A Plan RH'!$W92,0,60) -> 42 | I18: =OFFSET('Annexe A Plan RH'!$W92,0,72) -> 55

Sheet Prévisionnel annuel
N2: Scénarisation (Ne pas modifier ici) | R2: Stratégie investissement (Ne pas modifier ici)
C3: Année -1 | D3: Année 0 | E3: Année 1 | F3: Année 2 | G3: Année 3 | H3: Année 4 | I3: Année 5 | J3: Année 6 | K3: Année 7 | N3: Acquisition Optiwize Pro | O3: ='Plan stratégique likewatt'!C38 -> Standard | R3: ='Plan stratégique likewatt'!F38 -> Début WP 3 R&D | S3: ='Plan stratégique likewatt'!G38 -> 46082
C4: 2024 | D4: 2025 | E4: 2026 | F4: 2027 | G4: 2028 | H4: 2029 | I4: 2030 | J4: 2031 | K4: 2032 | N4: Modèle Leads | O4: ='Plan stratégique likewatt'!C39 -> Simulation | R4: ='Plan stratégique likewatt'!F39 -> Début ES | S4: ='Plan stratégique likewatt'!G39 -> 47515
B5: CA TOTAL | C5: =SUM(C6:C8) -> 643214 | D5: =SUM(D6:D8) -> 670000 | E5: =SUM(Ventes!J3:U3) -> 850072.77 | F5: =SUM(Ventes!V3:AG3) -> 1237725.3 | G5: =SUM(Ventes!AH3:AS3) -> 1732141.7 | H5: =SUM(Ventes!AT3:BE3) -> 2351078.7 | I5: =SUM(Ventes!BF3:BQ3) -> 4096388.5 | J5: =SUM(Ventes!BR3:CC3) -> 10768417 | K5: =SUM(Ventes!BH3:BS3) -> 4793848.7 | N5: Adoption Leads | O5: ='Plan stratégique likewatt'!C40 -> Standard | R5: ='Plan stratégique likewatt'!F40 -> Début CH | S5: ='Plan stratégique likewatt'!G40 -> 47881
B6: Optiwize Pro - Abonnement | C6: =549325+7118 -> 556443 | D6: 650000 | E6: =SUM(Ventes!J4:U4) -> 810992.44 | F6: =SUM(Ventes!V4:AG4) -> 1120863.3 | G6: =SUM(Ventes!AH4:AS4) -> 1435720.1 | H6: =SUM(Ventes!AT4:BE4) -> 1771593.8 | I6: =SUM(Ventes!BF4:BQ4) -> 2782173.8 | J6: =SUM(Ventes!BR4:CC4) -> 6775579 | K6: =SUM(Ventes!BH4:BS4) -> 3187995.2 | N6: Churn | O6: ='Plan stratégique likewatt'!C41 -> Standard | R6: ='Plan stratégique likewatt'!F41 -> Début BE | S6: ='Plan stratégique likewatt'!G41 -> 48247
B7: Leads - Pay as you go | C7: 0 | D7: 10000 | E7: =SUM(Ventes!J8:U8) -> 25920.503 | F7: =SUM(Ventes!V8:AG8) -> 92179.136 | G7: =SUM(Ventes!AH8:AS8) -> 268724.54 | H7: =SUM(Ventes!AT8:BE8) -> 558208.08 | I7: =SUM(Ventes!BF8:BQ8) -> 1234472.3 | J7: =SUM(Ventes!BR8:CC8) -> 3748819.1 | K7: =SUM(Ventes!BH8:BS8) -> 1506773.3 | N7: Montant levée | O7: ='Plan stratégique likewatt'!C42 -> 0 | R7: ='Plan stratégique likewatt'!F42 -> Début DE | S7: ='Plan stratégique likewatt'!G42 -> 48613
B8: Prestations de services (installations) | C8: =73040+3923+1710+8098 -> 86771 | D8: 10000 | E8: =SUM(Ventes!J12:U12) -> 13159.832 | F8: =SUM(Ventes!V12:AG12) -> 24682.854 | G8: =SUM(Ventes!AH12:AS12) -> 27697.077 | H8: =SUM(Ventes!AT12:BE12) -> 21276.838 | I8: =SUM(Ventes!BF12:BQ12) -> 79742.337 | J8: =SUM(Ventes!BR12:CC12) -> 244019.41 | K8: =SUM(Ventes!BH12:BS12) -> 99080.144 | N8: Date levée | O8: =EOMONTH('Plan stratégique likewatt'!C43,-1)+1 -> 47515 | R8: ='Plan stratégique likewatt'!F43 -> Début phase 2 FR | S8: ='Plan stratégique likewatt'!G43 -> 47515
B9: Productions immobilisées & stockées | C9: 0 | D9: 0 | E9: 0 | F9: 0 | G9: 0 | H9: 0 | I9: 0 | J9: 0 | K9: 0 | N9: Low point | O9: =Trésorerie!C33 -> #N/A
B10: MARGE BRUTE | C10: =C5+C11 -> 580814 | D10: =D5+D11 -> 667000 | E10: =E5+E11 -> 703478.5 | F10: =F5+F11 -> 946974.52 | G10: =G5+G11 -> 1281943.5 | H10: =H5+H11 -> 1772549.6 | I10: =I5+I11 -> 3035994.1 | J10: =J5+J11 -> 8125643 | K10: =K5+K11 -> 3568566.7 | N10: Low point | O10: =Trésorerie!C32 -> 201756.47 | P10: =Trésorerie!D32 -> 46722
B11: Couts variables, Sous-traitance | C11: -62400 | D11: -3000 | E11: =SUM('Couts variables'!J3:U3) -> -146594.28 | F11: =SUM('Couts variables'!V3:AG3) -> -290750.8 | G11: =SUM('Couts variables'!AH3:AS3) -> -450198.19 | H11: =SUM('Couts variables'!AT3:BE3) -> -578529.1 | I11: =SUM('Couts variables'!BF3:BQ3) -> -1060394.4 | J11: =SUM('Couts variables'!BR3:CC3) -> -2642774.5 | K11: =SUM('Couts variables'!BH3:BS3) -> -1225282
B12: VALEUR AJOUTEE | C12: =C10+C13 -> 493635 | D12: =D10+D13 -> 577000 | E12: =E10+E13 -> 494572.34 | F12: =F10+F13 -> 762534.6 | G12: =G10+G13 -> 1097058.8 | H12: =H10+H13 -> 1553971.7 | I12: =I10+I13 -> 2469425.9 | J12: =J10+J13 -> 6845274.9 | K12: =K10+K13 -> 2879470.2
B13: Couts fixes | C13: -87179 | D13: -90000 | E13: =SUM('Couts fixes'!J2:U2) -> -208906.16 | F13: =SUM('Couts fixes'!V2:AG2) -> -184439.92 | G13: =SUM('Couts fixes'!AH2:AS2) -> -184884.71 | H13: =SUM('Couts fixes'!AT2:BE2) -> -218577.93 | I13: =SUM('Couts fixes'!BF2:BQ2) -> -566568.2 | J13: =SUM('Couts fixes'!BR2:CC2) -> -1280368 | K13: =SUM('Couts fixes'!BH2:BS2) -> -689096.54
B14: EBE (EBITDA) | C14: =C12+C15+C16 -> 94334 | D14: =D12+D15+D16 -> -42076 | E14: =E12+E15+E16 -> -278164.28 | F14: =F12+F15+F16 -> -197115.78 | G14: =G12+G15+G16 -> 156963.19 | H14: =H12+H15+H16 -> 518915.99 | I14: =I12+I15+I16 -> 151587.59 | J14: =J12+J15+J16 -> 2761754.4 | K14: =K12+K15 -> 151328.17
B15: Salaires | C15: =-(343148+51982) -> -395130 | D15: =-53146*6-49200*6 -> -614076 | E15: =SUM('Couts RH'!J4:U4) -> -767965.62 | F15: =SUM('Couts RH'!V4:AG4) -> -954730.88 | G15: =SUM('Couts RH'!AH4:AS4) -> -935031.3 | H15: =SUM('Couts RH'!AT4:BE4) -> -1029839.7 | I15: =SUM('Couts RH'!BF4:BQ4) -> -2312465.9 | J15: =SUM('Couts RH'!BR4:CC4) -> -4077987 | K15: =SUM('Couts RH'!BH4:BS4) -> -2728142
B16: Impots, taxes (CFE, ...) | C16: -4171 | D16: -5000 | E16: =SUM('Couts fixes'!$J14:$U14) -> -4771 | F16: =SUM(OFFSET('Couts fixes'!$J14:$U14,0,12)) -> -4919.5108 | G16: =SUM(OFFSET('Couts fixes'!$J14:$U14,0,24)) -> -5064.3 | H16: =SUM(OFFSET('Couts fixes'!$J14:$U14,0,36)) -> -5215.92 | I16: =SUM(OFFSET('Couts fixes'!$J14:$U14,0,48)) -> -5372.3976 | J16: =SUM(OFFSET('Couts fixes'!$J14:$U14,0,60)) -> -5533.5695
B17: REX | C17: =C14+C18+C19 -> 101127 | D17: =D14+D18+D19 -> -48591 | E17: =E14+E18+E19 -> -287351.45 | F17: =F14+F18+F19 -> -207936.95 | G17: =G14+G18+G19 -> 144508.02 | H17: =H14+H18+H19 -> 499226.83 | I17: =I14+I18+I19 -> 116264.42 | J17: =J14+J18+J19 -> 2713397.2
B18: Amortissement | C18: -6515 | D18: -6515 | E18: =SUM(CAPEX!$C3:U3)/5 -> -9187.1667 | F18: =SUM(CAPEX!$C3:AG3)/5 -> -10821.167 | G18: =SUM(CAPEX!$C3:AS3)/5 -> -12455.167 | H18: =SUM(CAPEX!$C3:BE3)/5 -> -19689.167 | I18: =SUM(CAPEX!$C3:BQ3)/5 -> -35323.167 | J18: =SUM(CAPEX!$C3:CC3)/5 -> -48357.167
B19: Dépréciations, reprises comptable | C19: =12980+367-39 -> 13308 | D19: 0 | E19: 0 | F19: 0 | G19: 0 | H19: 0 | I19: 0 | J19: 0
B20: Resultat courant avant impots | C20: =C17+C21 -> 95410 | D20: =D17+D21 -> -54091 | E20: =E17+E21 -> -289526.45 | F20: =F17+F21 -> -209194.95 | G20: =G17+G21 -> 144166.02 | H20: =H17+H21 -> 499226.83 | I20: =I17+I21 -> 116264.42 | J20: =J17+J21 -> 2713397.2
B21: Résultat financier | C21: =-8717+3000 -> -5717 | D21: -5500 | E21: =SUM(OFFSET('Annexe E Financement'!$J11:$U11,0,0)) -> -2175 | F21: =SUM(OFFSET('Annexe E Financement'!$J11:$U11,0,12)) -> -1258 | G21: =SUM(OFFSET('Annexe E Financement'!$J11:$U11,0,24)) -> -342 | H21: =SUM(OFFSET('Annexe E Financement'!$J11:$U11,0,36)) -> 0 | I21: =SUM(OFFSET('Annexe E Financement'!$J11:$U11,0,49)) -> 0 | J21: =SUM(OFFSET('Annexe E Financement'!$J11:$U11,0,60)) -> 0
B22: Résultat de l'exercice | C22: =C20+C23+C24 -> 232614 | D22: =D20+D23+D24 -> 65909 | E22: =E20+E23+E24 -> -196765.51 | F22: =F20+F23+F24 -> -95105.886 | G22: =G20+G23+G24 -> 258255.09 | H22: =H20+H23+H24 -> 590615.48 | I22: =I20+I23+I24 -> 187256.67 | J22: =J20+J23+J24 -> 2988081.3
B23: Impots (IS, CIR,...) | C23: =137233 -> 137233 | D23: 120000 | E23: ='Annexe E Financement'!L39-IF(D20>0,D20*33%,0) -> 92760.938 | F23: ='Annexe E Financement'!X39-IF(E20>0,E20*33%,0) -> 114089.06 | G23: ='Annexe E Financement'!AJ39-IF(F20>0,F20*33%,0) -> 114089.06 | H23: ='Annexe E Financement'!AV39-IF(G20>0,G20*33%,0) -> 91388.649 | I23: ='Annexe E Financement'!BH39-IF(H20>0,H20*33%,0) -> 70992.245 | J23: ='Annexe E Financement'!BT39-IF(I20>0,I20*33%,0) -> 274684.11
B24: Produits et charges exceptionnels | C24: -29 | D24: 0 | E24: 0 | F24: 0 | G24: 0 | H24: 0 | I24: 0 | J24: 0
B25: CAF | C25: =C22-C18-C19 -> 225821 | D25: =D22-D18-D19 -> 72424 | E25: =E22-E18-E19 -> -187578.35 | F25: =F22-F18-F19 -> -84284.719 | G25: =G22-G18-G19 -> 270710.25 | H25: =H22-H18-H19 -> 610304.64 | I25: =I22-I18-I19 -> 222579.84 | J25: =J22-J18-J19 -> 3036438.5

Sheet Hypothèses
A2: Hypothèses marché
A3: Croissance organique marché FR | B3: 0.12
A4: Croissance organique marché ES | B4: 0.12
A5: Croissance organique marché CH | B5: 0.12
A6: Croissance organique marché BE | B6: 0.12
A7: Croissance organique marché DE | B7: 0.12
B9: 2025 | C9: 2026 | D9: 2027 | E9: 2028 | F9: 2029 | G9: 2030 | H9: 2031
A10: Hypothèses clients
A11: Nombre de projets/installateur
A12: FR | B12: 300 | C12: =B12*(1+$B3/2) -> 318 | D12: =C12*(1+$B3/2) -> 337.08 | E12: =D12*(1+$B3/2) -> 357.3048 | F12: =E12*(1+$B3/2) -> 378.74309 | G12: =F12*(1+$B3/2) -> 401.46767 | H12: =G12*(1+$B3/2) -> 425.55573
A13: ES | B13: 300 | C13: =B13*(1+$B4/2) -> 318 | D13: =C13*(1+$B4/2) -> 337.08 | E13: =D13*(1+$B4/2) -> 357.3048 | F13: =E13*(1+$B4/2) -> 378.74309 | G13: =F13*(1+$B4/2) -> 401.46767 | H13: =G13*(1+$B4/2) -> 425.55573
A14: CH | B14: 300 | C14: =B14*(1+$B5/2) -> 318 | D14: =C14*(1+$B5/2) -> 337.08 | E14: =D14*(1+$B5/2) -> 357.3048 | F14: =E14*(1+$B5/2) -> 378.74309 | G14: =F14*(1+$B5/2) -> 401.46767 | H14: =G14*(1+$B5/2) -> 425.55573
A15: BE | B15: 300 | C15: =B15*(1+$B6/2) -> 318 | D15: =C15*(1+$B6/2) -> 337.08 | E15: =D15*(1+$B6/2) -> 357.3048 | F15: =E15*(1+$B6/2) -> 378.74309 | G15: =F15*(1+$B6/2) -> 401.46767 | H15: =G15*(1+$B6/2) -> 425.55573
A16: DE | B16: 300 | C16: =B16*(1+$B7/2) -> 318 | D16: =C16*(1+$B7/2) -> 337.08 | E16: =D16*(1+$B7/2) -> 357.3048 | F16: =E16*(1+$B7/2) -> 378.74309 | G16: =F16*(1+$B7/2) -> 401.46767 | H16: =G16*(1+$B7/2) -> 425.55573
A19: Hypothèses commerciales
A20: Panier moyen mensuel Optiwize Pro | B20: ='Annexe G Evolution Portefeuill'!C$81/12 -> 329.71081 | C20: ='Annexe G Evolution Portefeuill'!D$81/12 -> 336.79557 | D20: ='Annexe G Evolution Portefeuill'!E$81/12 -> 363.71813 | E20: ='Annexe G Evolution Portefeuill'!F$81/12 -> 374.4191 | F20: ='Annexe G Evolution Portefeuill'!G$81/12 -> 385.19247 | G20: ='Annexe G Evolution Portefeuill'!H$81/12 -> 410.53172 | H20: ='Annexe G Evolution Portefeuill'!I$81/12 -> 412.85085
A21: FR | B21: =B20 -> 329.71081 | C21: =C20 -> 336.79557 | D21: =D20 -> 363.71813 | E21: =E20 -> 374.4191 | F21: =F20 -> 385.19247 | G21: =G20 -> 410.53172 | H21: =H20 -> 412.85085
A22: ES | B22: =B21 -> 329.71081 | C22: =C21 -> 336.79557 | D22: =D21 -> 363.71813 | E22: =E21 -> 374.4191 | F22: =F21 -> 385.19247 | G22: =G21 -> 410.53172 | H22: =H21 -> 412.85085
A23: CH | B23: =B22 -> 329.71081 | C23: =C22 -> 336.79557 | D23: =D22 -> 363.71813 | E23: =E22 -> 374.4191 | F23: =F22 -> 385.19247 | G23: =G22 -> 410.53172 | H23: =H22 -> 412.85085
A24: BE | B24: =B23 -> 329.71081 | C24: =C23 -> 336.79557 | D24: =D23 -> 363.71813 | E24: =E23 -> 374.4191 | F24: =F23 -> 385.19247 | G24: =G23 -> 410.53172 | H24: =H23 -> 412.85085
A25: DE | B25: =B24 -> 329.71081 | C25: =C24 -> 336.79557 | D25: =D24 -> 363.71813 | E25: =E24 -> 374.4191 | F25: =F24 -> 385.19247 | G25: =G24 -> 410.53172 | H25: =H24 -> 412.85085
A27: Panier moyen mensuel Leads
A28: FR | B28: {=_xlfn.IFS('Prévisionnel annuel'!$O$4="Simulation",B35,'Prévisionnel annuel'!$O$4="Succes",B42*$B$48*$B$47)} -> 35 | C28: {=_xlfn.IFS('Prévisionnel annuel'!$O$4="Simulation",C35,'Prévisionnel annuel'!$O$4="Succes",C42*$B$48*$B$47)} -> 35 | D28: {=_xlfn.IFS('Prévisionnel annuel'!$O$4="Simulation",D35,'Prévisionnel annuel'!$O$4="Succes",D42*$B$48*$B$47)} -> 35 | E28: {=_xlfn.IFS('Prévisionnel annuel'!$O$4="Simulation",E35,'Prévisionnel annuel'!$O$4="Succes",E42*$B$48*$B$47)} -> 35 | F28: {=_xlfn.IFS('Prévisionnel annuel'!$O$4="Simulation",F35,'Prévisionnel annuel'!$O$4="Succes",F42*$B$48*$B$47)} -> 35 | G28: {=_xlfn.IFS('Prévisionnel annuel'!$O$4="Simulation",G35,'Prévisionnel annuel'!$O$4="Succes",G42*$B$48*$B$47)} -> 35 | H28: {=_xlfn.IFS('Prévisionnel annuel'!$O$4="Simulation",H35,'Prévisionnel annuel'!$O$4="Succes",H42*$B$48*$B$47)} -> 35
A29: ES | B29: {=_xlfn.IFS('Prévisionnel annuel'!$O$4="Simulation",B36,'Prévisionnel annuel'!$O$4="Succes",B43*$B$48*$B$47)} -> 35 | C29: {=_xlfn.IFS('Prévisionnel annuel'!$O$4="Simulation",C36,'Prévisionnel annuel'!$O$4="Succes",C43*$B$48*$B$47)} -> 35 | D29: {=_xlfn.IFS('Prévisionnel annuel'!$O$4="Simulation",D36,'Prévisionnel annuel'!$O$4="Succes",D43*$B$48*$B$47)} -> 35 | E29: {=_xlfn.IFS('Prévisionnel annuel'!$O$4="Simulation",E36,'Prévisionnel annuel'!$O$4="Succes",E43*$B$48*$B$47)} -> 35 | F29: {=_xlfn.IFS('Prévisionnel annuel'!$O$4="Simulation",F36,'Prévisionnel annuel'!$O$4="Succes",F43*$B$48*$B$47)} -> 35 | G29: {=_xlfn.IFS('Prévisionnel annuel'!$O$4="Simulation",G36,'Prévisionnel annuel'!$O$4="Succes",G43*$B$48*$B$47)} -> 35 | H29: {=_xlfn.IFS('Prévisionnel annuel'!$O$4="Simulation",H36,'Prévisionnel annuel'!$O$4="Succes",H43*$B$48*$B$47)} -> 35
A30: CH | B30: {=_xlfn.IFS('Prévisionnel annuel'!$O$4="Simulation",B37,'Prévisionnel annuel'!$O$4="Succes",B44*$B$48*$B$47)} -> 35 | C30: {=_xlfn.IFS('Prévisionnel annuel'!$O$4="Simulation",C37,'Prévisionnel annuel'!$O$4="Succes",C44*$B$48*$B$47)} -> 35 | D30: {=_xlfn.IFS('Prévisionnel annuel'!$O$4="Simulation",D37,'Prévisionnel annuel'!$O$4="Succes",D44*$B$48*$B$47)} -> 35 | E30: {=_xlfn.IFS('Prévisionnel annuel'!$O$4="Simulation",E37,'Prévisionnel annuel'!$O$4="Succes",E44*$B$48*$B$47)} -> 35 | F30: {=_xlfn.IFS('Prévisionnel annuel'!$O$4="Simulation",F37,'Prévisionnel annuel'!$O$4="Succes",F44*$B$48*$B$47)} -> 35 | G30: {=_xlfn.IFS('Prévisionnel annuel'!$O$4="Simulation",G37,'Prévisionnel annuel'!$O$4="Succes",G44*$B$48*$B$47)} -> 35 | H30: {=_xlfn.IFS('Prévisionnel annuel'!$O$4="Simulation",H37,'Prévisionnel annuel'!$O$4="Succes",H44*$B$48*$B$47)} -> 35
A31: BE | B31: {=_xlfn.IFS('Prévisionnel annuel'!$O$4="Simulation",B38,'Prévisionnel annuel'!$O$4="Succes",B45*$B$48*$B$47)} -> 35 | C31: {=_xlfn.IFS('Prévisionnel annuel'!$O$4="Simulation",C38,'Prévisionnel annuel'!$O$4="Succes",C45*$B$48*$B$47)} -> 35 | D31: {=_xlfn.IFS('Prévisionnel annuel'!$O$4="Simulation",D38,'Prévisionnel annuel'!$O$4="Succes",D45*$B$48*$B$47)} -> 35 | E31: {=_xlfn.IFS('Prévisionnel annuel'!$O$4="Simulation",E38,'Prévisionnel annuel'!$O$4="Succes",E45*$B$48*$B$47)} -> 35 | F31: {=_xlfn.IFS('Prévisionnel annuel'!$O$4="Simulation",F38,'Prévisionnel annuel'!$O$4="Succes",F45*$B$48*$B$47)} -> 35 | G31: {=_xlfn.IFS('Prévisionnel annuel'!$O$4="Simulation",G38,'Prévisionnel annuel'!$O$4="Succes",G45*$B$48*$B$47)} -> 35 | H31: {=_xlfn.IFS('Prévisionnel annuel'!$O$4="Simulation",H38,'Prévisionnel annuel'!$O$4="Succes",H45*$B$48*$B$47)} -> 35
A32: DE | B32: {=_xlfn.IFS('Prévisionnel annuel'!$O$4="Simulation",B39,'Prévisionnel annuel'!$O$4="Succes",B46*$B$48*$B$47)} -> 35 | C32: {=_xlfn.IFS('Prévisionnel annuel'!$O$4="Simulation",C39,'Prévisionnel annuel'!$O$4="Succes",C46*$B$48*$B$47)} -> 35 | D32: {=_xlfn.IFS('Prévisionnel annuel'!$O$4="Simulation",D39,'Prévisionnel annuel'!$O$4="Succes",D46*$B$48*$B$47)} -> 35 | E32: {=_xlfn.IFS('Prévisionnel annuel'!$O$4="Simulation",E39,'Prévisionnel annuel'!$O$4="Succes",E46*$B$48*$B$47)} -> 35 | F32: {=_xlfn.IFS('Prévisionnel annuel'!$O$4="Simulation",F39,'Prévisionnel annuel'!$O$4="Succes",F46*$B$48*$B$47)} -> 35 | G32: {=_xlfn.IFS('Prévisionnel annuel'!$O$4="Simulation",G39,'Prévisionnel annuel'!$O$4="Succes",G46*$B$48*$B$47)} -> 35 | H32: {=_xlfn.IFS('Prévisionnel annuel'!$O$4="Simulation",H39,'Prévisionnel annuel'!$O$4="Succes",H46*$B$48*$B$47)} -> 35
A34: Prix moyen simu - modèle simu Leads
A35: FR | B35: 35 | C35: 35 | D35: 35 | E35: 35 | F35: 35 | G35: 35 | H35: 35
A36: ES | B36: 35 | C36: 35 | D36: 35 | E36: 35 | F36: 35 | G36: 35 | H36: 35
A37: CH | B37: 35 | C37: 35 | D37: 35 | E37: 35 | F37: 35 | G37: 35 | H37: 35
A38: BE | B38: 35 | C38: 35 | D38: 35 | E38: 35 | F38: 35 | G38: 35 | H38: 35
A39: DE | B39: 35 | C39: 35 | D39: 35 | E39: 35 | F39: 35 | G39: 35 | H39: 35
A41: Prix moyen projet - modèle succes Leads
A42: FR | B42: 6000 | C42: =B42*102% -> 6120 | D42: =C42*102% -> 6242.4 | E42: =D42*102% -> 6367.248 | F42: =E42*102% -> 6494.593 | G42: =F42*102% -> 6624.4848 | H42: =G42*102% -> 6756.9745
A43: ES | B43: 5000 | C43: =B43*102% -> 5100 | D43: =C43*102% -> 5202 | E43: =D43*102% -> 5306.04 | F43: =E43*102% -> 5412.1608 | G43: =F43*102% -> 5520.404 | H43: =G43*102% -> 5630.8121
A44: CH | B44: 15000 | C44: =B44*102% -> 15300 | D44: =C44*102% -> 15606 | E44: =D44*102% -> 15918.12 | F44: =E44*102% -> 16236.482 | G44: =F44*102% -> 16561.212 | H44: =G44*102% -> 16892.436
A45: BE | B45: 6000 | C45: =B45*102% -> 6120 | D45: =C45*102% -> 6242.4 | E45: =D45*102% -> 6367.248 | F45: =E45*102% -> 6494.593 | G45: =F45*102% -> 6624.4848 | H45: =G45*102% -> 6756.9745
A46: DE | B46: 6000 | C46: =B46*102% -> 6120 | D46: =C46*102% -> 6242.4 | E46: =D46*102% -> 6367.248 | F46: =E46*102% -> 6494.593 | G46: =F46*102% -> 6624.4848 | H46: =G46*102% -> 6756.9745
A47: Success fees | B47: 0.05
A48: Conversion simu Leads en vente | B48: 0.33
A50: # rdv/mois/commercial prospection directe (installateur) | B50: 12 | C50: =B50 -> 12 | D50: =C50 -> 12 | E50: =D50 -> 12 | F50: =E50 -> 12 | G50: =F50 -> 12 | H50: =G50 -> 12
A51: # rdv max/mois/commerciaux | B51: 40 | C51: =B51 -> 40 | D51: =C51 -> 40 | E51: =D51 -> 40 | F51: =E51 -> 40 | G51: =F51 -> 40 | H51: =G51 -> 40
A53: Tx de conversion rdv/signature Optiwize
A54: FR | B54: 0.25 | C54: {=_xlfn.IFS('Prévisionnel annuel'!$O$3="Standard",25%,'Prévisionnel annuel'!$O$3="Optimiste",30%,'Prévisionnel annuel'!$O$3="Conservateur",20%)} -> 0.25 | D54: {=_xlfn.IFS('Prévisionnel annuel'!$O$3="Standard",25%,'Prévisionnel annuel'!$O$3="Optimiste",30%,'Prévisionnel annuel'!$O$3="Conservateur",20%)} -> 0.25 | E54: {=_xlfn.IFS('Prévisionnel annuel'!$O$3="Standard",25%,'Prévisionnel annuel'!$O$3="Optimiste",30%,'Prévisionnel annuel'!$O$3="Conservateur",20%)} -> 0.25 | F54: {=_xlfn.IFS('Prévisionnel annuel'!$O$3="Standard",25%,'Prévisionnel annuel'!$O$3="Optimiste",30%,'Prévisionnel annuel'!$O$3="Conservateur",20%)} -> 0.25 | G54: {=_xlfn.IFS('Prévisionnel annuel'!$O$3="Standard",25%,'Prévisionnel annuel'!$O$3="Optimiste",30%,'Prévisionnel annuel'!$O$3="Conservateur",20%)} -> 0.25 | H54: {=_xlfn.IFS('Prévisionnel annuel'!$O$3="Standard",25%,'Prévisionnel annuel'!$O$3="Optimiste",30%,'Prévisionnel annuel'!$O$3="Conservateur",20%)} -> 0.25
A55: ES | B55: 0 | C55: 0 | D55: {=_xlfn.IFS('Prévisionnel annuel'!$O$3="Standard",25%,'Prévisionnel annuel'!$O$3="Optimiste",30%,'Prévisionnel annuel'!$O$3="Conservateur",20%)} -> 0.25 | E55: {=_xlfn.IFS('Prévisionnel annuel'!$O$3="Standard",25%,'Prévisionnel annuel'!$O$3="Optimiste",30%,'Prévisionnel annuel'!$O$3="Conservateur",20%)} -> 0.25 | F55: {=_xlfn.IFS('Prévisionnel annuel'!$O$3="Standard",25%,'Prévisionnel annuel'!$O$3="Optimiste",30%,'Prévisionnel annuel'!$O$3="Conservateur",20%)} -> 0.25 | G55: {=_xlfn.IFS('Prévisionnel annuel'!$O$3="Standard",25%,'Prévisionnel annuel'!$O$3="Optimiste",30%,'Prévisionnel annuel'!$O$3="Conservateur",20%)} -> 0.25 | H55: {=_xlfn.IFS('Prévisionnel annuel'!$O$3="Standard",25%,'Prévisionnel annuel'!$O$3="Optimiste",30%,'Prévisionnel annuel'!$O$3="Conservateur",20%)} -> 0.25
A56: CH | B56: 0 | C56: 0 | D56: 0 | E56: {=_xlfn.IFS('Prévisionnel annuel'!$O$3="Standard",25%,'Prévisionnel annuel'!$O$3="Optimiste",30%,'Prévisionnel annuel'!$O$3="Conservateur",20%)} -> 0.25 | F56: {=_xlfn.IFS('Prévisionnel annuel'!$O$3="Standard",25%,'Prévisionnel annuel'!$O$3="Optimiste",30%,'Prévisionnel annuel'!$O$3="Conservateur",20%)} -> 0.25 | G56: {=_xlfn.IFS('Prévisionnel annuel'!$O$3="Standard",25%,'Prévisionnel annuel'!$O$3="Optimiste",30%,'Prévisionnel annuel'!$O$3="Conservateur",20%)} -> 0.25 | H56: {=_xlfn.IFS('Prévisionnel annuel'!$O$3="Standard",25%,'Prévisionnel annuel'!$O$3="Optimiste",30%,'Prévisionnel annuel'!$O$3="Conservateur",20%)} -> 0.25
A57: BE | B57: 0 | C57: 0 | D57: 0 | E57: {=_xlfn.IFS('Prévisionnel annuel'!$O$3="Standard",25%,'Prévisionnel annuel'!$O$3="Optimiste",30%,'Prévisionnel annuel'!$O$3="Conservateur",20%)} -> 0.25 | F57: {=_xlfn.IFS('Prévisionnel annuel'!$O$3="Standard",25%,'Prévisionnel annuel'!$O$3="Optimiste",30%,'Prévisionnel annuel'!$O$3="Conservateur",20%)} -> 0.25 | G57: {=_xlfn.IFS('Prévisionnel annuel'!$O$3="Standard",25%,'Prévisionnel annuel'!$O$3="Optimiste",30%,'Prévisionnel annuel'!$O$3="Conservateur",20%)} -> 0.25 | H57: {=_xlfn.IFS('Prévisionnel annuel'!$O$3="Standard",25%,'Prévisionnel annuel'!$O$3="Optimiste",30%,'Prévisionnel annuel'!$O$3="Conservateur",20%)} -> 0.25
A58: DE | B58: 0 | C58: 0 | D58: 0 | E58: {=_xlfn.IFS('Prévisionnel annuel'!$O$3="Standard",25%,'Prévisionnel annuel'!$O$3="Optimiste",30%,'Prévisionnel annuel'!$O$3="Conservateur",20%)} -> 0.25 | F58: {=_xlfn.IFS('Prévisionnel annuel'!$O$3="Standard",25%,'Prévisionnel annuel'!$O$3="Optimiste",30%,'Prévisionnel annuel'!$O$3="Conservateur",20%)} -> 0.25 | G58: {=_xlfn.IFS('Prévisionnel annuel'!$O$3="Standard",25%,'Prévisionnel annuel'!$O$3="Optimiste",30%,'Prévisionnel annuel'!$O$3="Conservateur",20%)} -> 0.25 | H58: {=_xlfn.IFS('Prévisionnel annuel'!$O$3="Standard",25%,'Prévisionnel annuel'!$O$3="Optimiste",30%,'Prévisionnel annuel'!$O$3="Conservateur",20%)} -> 0.25
A60: Budget marketing Suite Optiwize et Corporate (frais externe) | B60: =SUM(B61:B63) -> 20000 | C60: =SUM(C61:C63) -> 40000 | D60: =SUM(D61:D63) -> 50000 | E60: =SUM(E61:E63) -> 50000 | F60: =SUM(F61:F63) -> 75000 | G60: =SUM(G61:G63) -> 277500 | H60: =SUM(H61:H63) -> 1261111.1
A61: FR | B61: 20000 | C61: 40000 | D61: =IF(YEAR('Plan stratégique likewatt'!$G43)<D$9,'Annexe I Scénario investisseme'!E$39,IF(YEAR('Plan stratégique likewatt'!$G39)>D$9,50000,DATEDIF('Plan stratégique likewatt'!$G39,"31/12/2027","D")/360*'Annexe I Scénario investisseme'!E$39)) -> 50000 | E61: =IF(YEAR('Plan stratégique likewatt'!$G43)<E$9,'Annexe I Scénario investisseme'!F$39,IF(YEAR('Plan stratégique likewatt'!$G39)>E$9,50000,DATEDIF('Plan stratégique likewatt'!$G39,"31/12/2028","D")/360*'Annexe I Scénario investisseme'!EF$39)) -> 50000 | F61: =IF(YEAR('Plan stratégique likewatt'!$G43)<F$9,'Annexe I Scénario investisseme'!G$39,IF(YEAR('Plan stratégique likewatt'!$G39)>F$9,75000,DATEDIF('Plan stratégique likewatt'!$G39,"31/12/2029","D")/360*'Annexe I Scénario investisseme'!EG$39)) -> 75000 | G61: =IF(YEAR('Plan stratégique likewatt'!$G43)<G$9,'Annexe I Scénario investisseme'!H$39,IF(YEAR('Plan stratégique likewatt'!$G39)>G$9,'Annexe I Scénario investisseme'!H$39*0.5,DATEDIF('Plan stratégique likewatt'!$G39,"31/12/2030","D")/360*'Annexe I Scénario investisseme'!EH$39)) -> 0 | H61: =IF(YEAR('Plan stratégique likewatt'!$G43)<H$9,'Annexe I Scénario investisseme'!I$39,IF(YEAR('Plan stratégique likewatt'!$G39)>H$9,'Annexe I Scénario investisseme'!I$39*0.5,DATEDIF('Plan stratégique likewatt'!$G39,"31/12/2031","D")/360*'Annexe I Scénario investisseme'!EI$39)) -> 400000
A62: ES | D62: =IF(YEAR('Plan stratégique likewatt'!$G39)<D$9,'Annexe I Scénario investisseme'!E$39,IF(YEAR('Plan stratégique likewatt'!$G39)>D$9,0,DATEDIF('Plan stratégique likewatt'!$G39,"31/12/2027","D")/360*'Annexe I Scénario investisseme'!E$39)) -> 0 | E62: =IF(YEAR('Plan stratégique likewatt'!$G39)<E$9,'Annexe I Scénario investisseme'!F$39,IF(YEAR('Plan stratégique likewatt'!$G39)>E$9,0,DATEDIF('Plan stratégique likewatt'!$G39,"31/12/2028","D")/360*'Annexe I Scénario investisseme'!F$39)) -> 0 | F62: =IF(YEAR('Plan stratégique likewatt'!$G39)<F$9,'Annexe I Scénario investisseme'!G$39,IF(YEAR('Plan stratégique likewatt'!$G39)>F$9,0,DATEDIF('Plan stratégique likewatt'!$G39,"31/12/2029","D")/360*'Annexe I Scénario investisseme'!G$39)) -> 0 | G62: =IF(YEAR('Plan stratégique likewatt'!$G39)<G$9,'Annexe I Scénario investisseme'!H$39,IF(YEAR('Plan stratégique likewatt'!$G39)>G$9,0,DATEDIF('Plan stratégique likewatt'!$G39,"31/12/2030","D")/360*'Annexe I Scénario investisseme'!H$39)) -> 277500 | H62: =IF(YEAR('Plan stratégique likewatt'!$G39)<H$9,'Annexe I Scénario investisseme'!I$39,IF(YEAR('Plan stratégique likewatt'!$G39)>H$9,0,DATEDIF('Plan stratégique likewatt'!$G39,"31/12/2031","D")/360*'Annexe I Scénario investisseme'!I$39)) -> 400000
A63: CH | D63: =IF(YEAR('Plan stratégique likewatt'!$G40)<D$9,'Annexe I Scénario investisseme'!E$66,IF(YEAR('Plan stratégique likewatt'!$G40)>D$9,0,DATEDIF('Plan stratégique likewatt'!$G40,"31/12/2027","D")/360*'Annexe I Scénario investisseme'!E$66)) -> 0 | E63: =IF(YEAR('Plan stratégique likewatt'!$G40)<E$9,'Annexe I Scénario investisseme'!F$66,IF(YEAR('Plan stratégique likewatt'!$G40)>E$9,0,DATEDIF('Plan stratégique likewatt'!$G40,"31/12/2028","D")/360*'Annexe I Scénario investisseme'!F$66)) -> 0 | F63: =IF(YEAR('Plan stratégique likewatt'!$G40)<F$9,'Annexe I Scénario investisseme'!G$66,IF(YEAR('Plan stratégique likewatt'!$G40)>F$9,0,DATEDIF('Plan stratégique likewatt'!$G40,"31/12/2029","D")/360*'Annexe I Scénario investisseme'!G$66)) -> 0 | G63: =IF(YEAR('Plan stratégique likewatt'!$G40)<G$9,'Annexe I Scénario investisseme'!H$66,IF(YEAR('Plan stratégique likewatt'!$G40)>G$9,0,DATEDIF('Plan stratégique likewatt'!$G40,"31/12/2030","D")/360*'Annexe I Scénario investisseme'!H$66)) -> 0 | H63: =IF(YEAR('Plan stratégique likewatt'!$G40)<H$9,'Annexe I Scénario investisseme'!I$66,IF(YEAR('Plan stratégique likewatt'!$G40)>H$9,0,DATEDIF('Plan stratégique likewatt'!$G40,"31/12/2031","D")/360*'Annexe I Scénario investisseme'!I$66)) -> 461111.11
A64: BE | D64: =IF(YEAR('Plan stratégique likewatt'!$G41)<D$9,'Annexe I Scénario investisseme'!E$90,IF(YEAR('Plan stratégique likewatt'!$G41)>D$9,0,DATEDIF('Plan stratégique likewatt'!$G41,"31/12/2027","D")/360*'Annexe I Scénario investisseme'!E$90)) -> 0 | E64: =IF(YEAR('Plan stratégique likewatt'!$G41)<E$9,'Annexe I Scénario investisseme'!F$90,IF(YEAR('Plan stratégique likewatt'!$G41)>E$9,0,DATEDIF('Plan stratégique likewatt'!$G41,"31/12/2028","D")/360*'Annexe I Scénario investisseme'!F$90)) -> 0 | F64: =IF(YEAR('Plan stratégique likewatt'!$G41)<F$9,'Annexe I Scénario investisseme'!G$90,IF(YEAR('Plan stratégique likewatt'!$G41)>F$9,0,DATEDIF('Plan stratégique likewatt'!$G41,"31/12/2029","D")/360*'Annexe I Scénario investisseme'!G$90)) -> 0 | G64: =IF(YEAR('Plan stratégique likewatt'!$G41)<G$9,'Annexe I Scénario investisseme'!H$90,IF(YEAR('Plan stratégique likewatt'!$G41)>G$9,0,DATEDIF('Plan stratégique likewatt'!$G41,"31/12/2030","D")/360*'Annexe I Scénario investisseme'!H$90)) -> 0 | H64: =IF(YEAR('Plan stratégique likewatt'!$G41)<H$9,'Annexe I Scénario investisseme'!I$90,IF(YEAR('Plan stratégique likewatt'!$G41)>H$9,0,DATEDIF('Plan stratégique likewatt'!$G41,"31/12/2031","D")/360*'Annexe I Scénario investisseme'!I$90)) -> 0
A65: DE | D65: =IF(YEAR('Plan stratégique likewatt'!$G42)<D$9,'Annexe I Scénario investisseme'!E$114,IF(YEAR('Plan stratégique likewatt'!$G42)>D$9,0,DATEDIF('Plan stratégique likewatt'!$G42,"31/12/2027","D")/360*'Annexe I Scénario investisseme'!E$114)) -> 0 | E65: =IF(YEAR('Plan stratégique likewatt'!$G42)<E$9,'Annexe I Scénario investisseme'!F$114,IF(YEAR('Plan stratégique likewatt'!$G42)>E$9,0,DATEDIF('Plan stratégique likewatt'!$G42,"31/12/2028","D")/360*'Annexe I Scénario investisseme'!F$114)) -> 0 | F65: =IF(YEAR('Plan stratégique likewatt'!$G42)<F$9,'Annexe I Scénario investisseme'!G$114,IF(YEAR('Plan stratégique likewatt'!$G42)>F$9,0,DATEDIF('Plan stratégique likewatt'!$G42,"31/12/2029","D")/360*'Annexe I Scénario investisseme'!G$114)) -> 0 | G65: =IF(YEAR('Plan stratégique likewatt'!$G42)<G$9,'Annexe I Scénario investisseme'!H$114,IF(YEAR('Plan stratégique likewatt'!$G42)>G$9,0,DATEDIF('Plan stratégique likewatt'!$G42,"31/12/2030","D")/360*'Annexe I Scénario investisseme'!H$114)) -> 0 | H65: =IF(YEAR('Plan stratégique likewatt'!$G42)<H$9,'Annexe I Scénario investisseme'!I$114,IF(YEAR('Plan stratégique likewatt'!$G42)>H$9,0,DATEDIF('Plan stratégique likewatt'!$G42,"31/12/2031","D")/360*'Annexe I Scénario investisseme'!I$114)) -> 0
A67: CPL (démo) Inbound marketing | B67: =250*794/637 -> 311.61695 | C67: =B67 -> 311.61695 | D67: =C67 -> 311.61695 | E67: =D67 -> 311.61695 | F67: =E67 -> 311.61695 | G67: =F67 -> 311.61695 | H67: =G67 -> 311.61695 | J67: https://btob-leaders.com/inbound-marketing-outbound-marketing/
A68: Délai invest to lead marketing (mois) | B68: 6
A69: Budget annuel /ETP marketing | B69: 50000
A71: Conversion optiwize installateur vers leads v1 | B71: 0.05 | C71: {=_xlfn.IFS('Prévisionnel annuel'!$O$5="Standard",10%,'Prévisionnel annuel'!$O$5="Optimiste",13%,'Prévisionnel annuel'!$O$5="Conservateur",7%)} -> 0.1 | D71: {=_xlfn.IFS('Prévisionnel annuel'!$O$5="Standard",25%,'Prévisionnel annuel'!$O$5="Optimiste",30%,'Prévisionnel annuel'!$O$5="Conservateur",20%)} -> 0.25 | E71: {=_xlfn.IFS('Prévisionnel annuel'!$O$5="Standard",45%,'Prévisionnel annuel'!$O$5="Optimiste",50%,'Prévisionnel annuel'!$O$5="Conservateur",40%)} -> 0.45 | F71: =_xlfn.IFS('Prévisionnel annuel'!$O$5="Standard",60%,'Prévisionnel annuel'!$O$5="Optimiste",70%,'Prévisionnel annuel'!$O$5="Conservateur",50%) -> 0.6 | G71: {=_xlfn.IFS('Prévisionnel annuel'!$O$5="Standard",65%,'Prévisionnel annuel'!$O$5="Optimiste",75%,'Prévisionnel annuel'!$O$5="Conservateur",50%)} -> 0.65 | H71: {=_xlfn.IFS('Prévisionnel annuel'!$O$5="Standard",65%,'Prévisionnel annuel'!$O$5="Optimiste",80%,'Prévisionnel annuel'!$O$5="Conservateur",50%)} -> 0.65
A72: Taux d'utilisation leads (en % de projets annuel) | B72: 0.08 | C72: {=_xlfn.IFS('Prévisionnel annuel'!$O$5="Standard",9%,'Prévisionnel annuel'!$O$5="Optimiste",10%,'Prévisionnel annuel'!$O$5="Conservateur",8%)} -> 0.09 | D72: {=_xlfn.IFS('Prévisionnel annuel'!$O$5="Standard",12%,'Prévisionnel annuel'!$O$5="Optimiste",15%,'Prévisionnel annuel'!$O$5="Conservateur",9%)} -> 0.12 | E72: {=_xlfn.IFS('Prévisionnel annuel'!$O$5="Standard",18%,'Prévisionnel annuel'!$O$5="Optimiste",25%,'Prévisionnel annuel'!$O$5="Conservateur",11%)} -> 0.18 | F72: {=_xlfn.IFS('Prévisionnel annuel'!$O$5="Standard",25%,'Prévisionnel annuel'!$O$5="Optimiste",35%,'Prévisionnel annuel'!$O$5="Conservateur",15%)} -> 0.25 | G72: {=_xlfn.IFS('Prévisionnel annuel'!$O$5="Standard",35%,'Prévisionnel annuel'!$O$5="Optimiste",45%,'Prévisionnel annuel'!$O$5="Conservateur",20%)} -> 0.35 | H72: {=_xlfn.IFS('Prévisionnel annuel'!$O$5="Standard",45%,'Prévisionnel annuel'!$O$5="Optimiste",60%,'Prévisionnel annuel'!$O$5="Conservateur",20%)} -> 0.45
A74: Prix installation Optiwize | B74: 0
A75: Prix installation Leads | B75: 490
A78: Hypothèses satisfaction clients & usages
A79: Churn annuel Optiwize Premium | B79: ='Annexe G Evolution Portefeuill'!C6 -> 0.10466175 | C79: ='Annexe G Evolution Portefeuill'!D6 -> 0.084563143 | D79: ='Annexe G Evolution Portefeuill'!E6 -> 0.064055216 | E79: ='Annexe G Evolution Portefeuill'!F6 -> 0.05364542 | F79: ='Annexe G Evolution Portefeuill'!G6 -> 0.05364542 | G79: ='Annexe G Evolution Portefeuill'!H6 -> 0.05364542 | H79: ='Annexe G Evolution Portefeuill'!I6 -> 0.05364542
A80: Churn annuel Optiwize Standard | B80: ='Annexe G Evolution Portefeuill'!C7 -> 0.23919697 | C80: ='Annexe G Evolution Portefeuill'!D7 -> 0.17651034 | D80: ='Annexe G Evolution Portefeuill'!E7 -> 0.15316551 | E80: ='Annexe G Evolution Portefeuill'!F7 -> 0.13405825 | F80: ='Annexe G Evolution Portefeuill'!G7 -> 0.12435839 | G80: ='Annexe G Evolution Portefeuill'!H7 -> 0.11455986 | H80: ='Annexe G Evolution Portefeuill'!I7 -> 0.12435839
A81: Churn annuel Optiwize Essentiel | B81: ='Annexe G Evolution Portefeuill'!C8 -> 0.4191334 | C81: ='Annexe G Evolution Portefeuill'!D8 -> 0.35910134 | D81: ='Annexe G Evolution Portefeuill'!E8 -> 0.3305048 | E81: ='Annexe G Evolution Portefeuill'!F8 -> 0.31436174 | F81: ='Annexe G Evolution Portefeuill'!G8 -> 0.41308271 | G81: ='Annexe G Evolution Portefeuill'!H8 -> 0.28911929 | H81: ='Annexe G Evolution Portefeuill'!I8 -> 0.2787992
A82: % leads v1/total projets
A83: % leads v2/total projets
A84: Tps support/client/mois existant (heures) | B84: 1
A85: Tps dev/client/mois (heures) | B85: =B84/10 -> 0.1
A86: Tps Onboarding Optiwize(heures) | B86: 4
A87: Tps Onboarding Leads v1 (heures) - Package marketing | B87: 4
A90: Hypothèses RH générales
A91: Temps de formation commerciaux (mois) | B91: 6
A92: Temps de formation support | B92: 3
A93: Turnover commerciaux | B93: 0.1
A94: Cout workspace par salarié | B94: 1000
A95: Loyer mensuel/employé FR | B95: 160
A96: Loyer mensuel/employé ES | B96: 130
A97: Loyer mensuel/employé CH | B97: 200
A98: Abonnement IT moyen /employé/ mois | B98: 100
A99: Assurances par salarié | B99: 100

Sheet Ventes
C1: 2025 | J1: 2026 | V1: 2027 | AH1: 2028 | AT1: 2029 | BF1: 2030
C2: 45809 | D2: 45839 | E2: 45870 | F2: 45901 | G2: 45931 | H2: 45962 | I2: 45992 | J2: 46023 | K2: 46054 | L2: 46082 | M2: 46113 | N2: 46143 | O2: 46174 | P2: 46204 | Q2: 46235 | R2: 46266 | S2: 46296 | T2: 46327 | U2: 46357 | V2: 46388 | W2: 46419 | X2: 46447 | Y2: 46478 | Z2: 46508 | AA2: 46539 | AB2: 46569 | AC2: 46600 | AD2: 46631 | AE2: 46661 | AF2: 46692 | AG2: 46722 | AH2: 46753 | AI2: 46784 | AJ2: 46813 | AK2: 46844 | AL2: 46874 | AM2: 46905 | AN2: 46935 | AO2: 46966 | AP2: 46997 | AQ2: 47027 | AR2: 47058 | AS2: 47088 | AT2: 47119 | AU2: 47150 | AV2: 47178 | AW2: 47209 | AX2: 47239 | AY2: 47270 | AZ2: 47300 | BA2: 47331 | BB2: 47362 | BC2: 47392 | BD2: 47423 | BE2: 47453 | BF2: 47484 | BG2: 47515 | BH2: 47543 | BI2: 47574 | BJ2: 47604 | BK2: 47635 | BL2: 47665 | BM2: 47696 | BN2: 47727 | BO2: 47757 | BP2: 47788 | BQ2: 47818 | BR2: 47849 | BS2: 47880 | BT2: 47908 | BU2: 47939 | BV2: 47969 | BW2: 48000 | BX2: 48030 | BY2: 48061 | BZ2: 48092 | CA2: 48122 | CB2: 48153 | CC2: 48183
A3: REVENUS (HT) | C3: =C4+C8+C12 -> 53008.343 | D3: =D4+D8+D12 -> 54444.887 | E3: =E4+E8+E12 -> 55553.416 | F3: =F4+F8+F12 -> 56642.458 | G3: =G4+G8+G12 -> 57712.458 | H3: =H4+H8+H12 -> 58763.855 | I3: =I4+I8+I12 -> 59797.07 | J3: =J4+J8+J12 -> 63058.019 | ... CC3: =CC4+CC8+CC12 -> 1386303.1
A4: Abonnements - Optiwize Pro | C4: =C19*Hypothèses!$B$20 -> 52424.018 | D4: =D19*Hypothèses!$B$20 -> 53499.623 | E4: =E19*Hypothèses!$B$20 -> 54554.438 | F4: =F19*Hypothèses!$B$20 -> 55588.949 | G4: =G19*Hypothèses!$B$20 -> 56603.627 | H4: =H19*Hypothèses!$B$20 -> 57598.932 | I4: =I19*Hypothèses!$B$20 -> 58575.31 | J4: =J19*Hypothèses!$C$20 -> 60975.406 | K4: =K19*Hypothèses!$C$20 -> 62280.54 | L4: =L19*Hypothèses!$C$20 -> 62555.562 | M4: =M19*Hypothèses!$C$20 -> 63841.557 | N4: =N19*Hypothèses!$C$20 -> 65108.034 | O4: =O19*Hypothèses!$C$20 -> 66355.349 | P4: =P19*Hypothèses!$C$20 -> 67583.85 | Q4: =Q19*Hypothèses!$C$20 -> 69244.211 | ... U4: =U19*Hypothèses!$C$20 -> 75620.737 | V4: =V19*Hypothèses!$D$20 -> 83500.764 | W4: =W19*Hypothèses!$D$20 -> 85314.75 | X4: =X19*Hypothèses!$D$20 -> 87107.916 | Y4: =Y19*Hypothèses!$D$20 -> 88880.555 | Z4: =Z19*Hypothèses!$D$20 -> 90632.954 | AA4: =AA19*Hypothèses!$D$20 -> 92365.396 | AB4: =AB19*Hypothèses!$D$20 -> 94078.159 | AC4: =AC19*Hypothèses!$D$20 -> 96014.683 | ... AG4: =AG19*Hypothèses!$D$20 -> 103533.73 | AH4: =AH19*Hypothèses!$E$20 -> 108653 | AI4: =AI19*Hypothèses!$E$20 -> 110708.51 | AJ4: =AJ19*Hypothèses!$E$20 -> 112746.49 | AK4: =AK19*Hypothèses!$E$20 -> 114767.09 | AL4: =AL19*Hypothèses!$E$20 -> 116770.48 | AM4: =AM19*Hypothèses!$E$20 -> 118756.8 | AN4: =AN19*Hypothèses!$E$20 -> 120726.22 | AO4: =AO19*Hypothèses!$E$20 -> 122678.89 | ... AS4: =AS19*Hypothèses!$E$20 -> 130325.11 | AT4: =AT19*Hypothèses!$F$20 -> 136083.61 | AU4: =AU19*Hypothèses!$F$20 -> 138079.98 | AV4: =AV19*Hypothèses!$F$20 -> 140064.11 | AW4: =AW19*Hypothèses!$F$20 -> 142036.02 | AX4: =AX19*Hypothèses!$F$20 -> 143995.71 | AY4: =AY19*Hypothèses!$F$20 -> 145943.19 | AZ4: =AZ19*Hypothèses!$F$20 -> 147878.47 | BA4: =BA19*Hypothèses!$F$20 -> 150445.36 | ... BE4: =BE19*Hypothèses!$F$20 -> 160521.72 | BF4: =BF19*Hypothèses!$G$20 -> 173871.03 | BG4: =BG19*Hypothèses!$G$20 -> 176640.34 | BH4: =BH19*Hypothèses!$G$20 -> 181852.66 | BI4: =BI19*Hypothèses!$G$20 -> 187020.47 | BJ4: =BJ19*Hypothèses!$G$20 -> 194607.45 | BK4: =BK19*Hypothèses!$G$20 -> 204589.96 | BL4: =BL19*Hypothèses!$G$20 -> 214481.47 | BM4: =BM19*Hypothèses!$G$20 -> 239920.55 | ... BQ4: =BQ19*Hypothèses!$G$20 -> 339243.32 | BR4: =BR19*Hypothèses!$H$20 -> 365496.86 | BS4: =BS19*Hypothèses!$H$20 -> 390835.89 | BT4: =BT19*Hypothèses!$H$20 -> 415928.57 | BU4: =BU19*Hypothèses!$H$20 -> 441979.34 | BV4: =BV19*Hypothèses!$H$20 -> 467777.96 | BW4: =BW19*Hypothèses!$H$20 -> 493327.53 | BX4: =BX19*Hypothèses!$H$20 -> 522309.6 | BY4: =BY19*Hypothèses!$H$20 -> 592996.34 | ... CC4: =CC19*Hypothèses!$H$20 -> 878776.35
A5: Installateurs
A6: Bureaux d'études
A8: Pay as you go - Leads | C8: =C9+C10 -> 584.325 | D8: =D9+D10 -> 629.44238 | E8: =E9+E10 -> 675.63438 | F8: =F9+F10 -> 722.86868 | G8: =G9+G10 -> 771.11402 | H8: =H9+H10 -> 820.34007 | I8: =I9+I10 -> 870.51748 | J8: =J9+J10 -> 1190.1325 | ... CC8: =CC9+CC10 -> 474956.64
A9: Installateurs/developpeurs | C9: =(C43*Hypothèses!$B$12/12*Hypothèses!$B$28+C44*Hypothèses!$B$13/12*Hypothèses!$B$29+C45*Hypothèses!$B$14/12*Hypothèses!$B$30+C46*Hypothèses!$B$15/12*Hypothèses!$B$31+C47*Hypothèses!$B$16/12*Hypothèses!$B$32)*Hypothèses!$B$72 -> 584.325 | D9: =(D43*Hypothèses!$B$12/12*Hypothèses!$B$28+D44*Hypothèses!$B$13/12*Hypothèses!$B$29+D45*Hypothèses!$B$14/12*Hypothèses!$B$30+D46*Hypothèses!$B$15/12*Hypothèses!$B$31+D47*Hypothèses!$B$16/12*Hypothèses!$B$32)*Hypothèses!$B$72 -> 629.44238 | E9: =(E43*Hypothèses!$B$12/12*Hypothèses!$B$28+E44*Hypothèses!$B$13/12*Hypothèses!$B$29+E45*Hypothèses!$B$14/12*Hypothèses!$B$30+E46*Hypothèses!$B$15/12*Hypothèses!$B$31+E47*Hypothèses!$B$16/12*Hypothèses!$B$32)*Hypothèses!$B$72 -> 675.63438 | F9: =(F43*Hypothèses!$B$12/12*Hypothèses!$B$28+F44*Hypothèses!$B$13/12*Hypothèses!$B$29+F45*Hypothèses!$B$14/12*Hypothèses!$B$30+F46*Hypothèses!$B$15/12*Hypothèses!$B$31+F47*Hypothèses!$B$16/12*Hypothèses!$B$32)*Hypothèses!$B$72 -> 722.86868 | G9: =(G43*Hypothèses!$B$12/12*Hypothèses!$B$28+G44*Hypothèses!$B$13/12*Hypothèses!$B$29+G45*Hypothèses!$B$14/12*Hypothèses!$B$30+G46*Hypothèses!$B$15/12*Hypothèses!$B$31+G47*Hypothèses!$B$16/12*Hypothèses!$B$32)*Hypothèses!$B$72 -> 771.11402 | H9: =(H43*Hypothèses!$B$12/12*Hypothèses!$B$28+H44*Hypothèses!$B$13/12*Hypothèses!$B$29+H45*Hypothèses!$B$14/12*Hypothèses!$B$30+H46*Hypothèses!$B$15/12*Hypothèses!$B$31+H47*Hypothèses!$B$16/12*Hypothèses!$B$32)*Hypothèses!$B$72 -> 820.34007 | I9: =(I43*Hypothèses!$B$12/12*Hypothèses!$B$28+I44*Hypothèses!$B$13/12*Hypothèses!$B$29+I45*Hypothèses!$B$14/12*Hypothèses!$B$30+I46*Hypothèses!$B$15/12*Hypothèses!$B$31+I47*Hypothèses!$B$16/12*Hypothèses!$B$32)*Hypothèses!$B$72 -> 870.51748 | J9: =(J43*Hypothèses!$C$12/12*Hypothèses!$C$28+J44*Hypothèses!$C$13/12*Hypothèses!$C$29+J45*Hypothèses!$C$14/12*Hypothèses!$C$30+J46*Hypothèses!$C$15/12*Hypothèses!$C$31+J47*Hypothèses!$C$16/12*Hypothèses!$B$32)*Hypothèses!$C$72 -> 1190.1325 | K9: =(K43*Hypothèses!$C$12/12*Hypothèses!$C$28+K44*Hypothèses!$C$13/12*Hypothèses!$C$29+K45*Hypothèses!$C$14/12*Hypothèses!$C$30+K46*Hypothèses!$C$15/12*Hypothèses!$C$31+K47*Hypothèses!$C$16/12*Hypothèses!$B$32)*Hypothèses!$C$72 -> 1350.6738 | L9: =(L43*Hypothèses!$C$12/12*Hypothèses!$C$28+L44*Hypothèses!$C$13/12*Hypothèses!$C$29+L45*Hypothèses!$C$14/12*Hypothèses!$C$30+L46*Hypothèses!$C$15/12*Hypothèses!$C$31+L47*Hypothèses!$C$16/12*Hypothèses!$B$32)*Hypothèses!$C$72 -> 1492.302 | M9: =(M43*Hypothèses!$C$12/12*Hypothèses!$C$28+M44*Hypothèses!$C$13/12*Hypothèses!$C$29+M45*Hypothèses!$C$14/12*Hypothèses!$C$30+M46*Hypothèses!$C$15/12*Hypothèses!$C$31+M47*Hypothèses!$C$16/12*Hypothèses!$B$32)*Hypothèses!$C$72 -> 1661.433 | N9: =(N43*Hypothèses!$C$12/12*Hypothèses!$C$28+N44*Hypothèses!$C$13/12*Hypothèses!$C$29+N45*Hypothèses!$C$14/12*Hypothèses!$C$30+N46*Hypothèses!$C$15/12*Hypothèses!$C$31+N47*Hypothèses!$C$16/12*Hypothèses!$B$32)*Hypothèses!$C$72 -> 1835.5915 | O9: =(O43*Hypothèses!$C$12/12*Hypothèses!$C$28+O44*Hypothèses!$C$13/12*Hypothèses!$C$29+O45*Hypothèses!$C$14/12*Hypothèses!$C$30+O46*Hypothèses!$C$15/12*Hypothèses!$C$31+O47*Hypothèses!$C$16/12*Hypothèses!$B$32)*Hypothèses!$C$72 -> 2014.6615 | P9: =(P43*Hypothèses!$C$12/12*Hypothèses!$C$28+P44*Hypothèses!$C$13/12*Hypothèses!$C$29+P45*Hypothèses!$C$14/12*Hypothèses!$C$30+P46*Hypothèses!$C$15/12*Hypothèses!$C$31+P47*Hypothèses!$C$16/12*Hypothèses!$B$32)*Hypothèses!$C$72 -> 2198.5295 | Q9: =(Q43*Hypothèses!$C$12/12*Hypothèses!$C$28+Q44*Hypothèses!$C$13/12*Hypothèses!$C$29+Q45*Hypothèses!$C$14/12*Hypothèses!$C$30+Q46*Hypothèses!$C$15/12*Hypothèses!$C$31+Q47*Hypothèses!$C$16/12*Hypothèses!$B$32)*Hypothèses!$C$72 -> 2402.7112 | ... U9: =(U43*Hypothèses!$C$12/12*Hypothèses!$C$28+U44*Hypothèses!$C$13/12*Hypothèses!$C$29+U45*Hypothèses!$C$14/12*Hypothèses!$C$30+U46*Hypothèses!$C$15/12*Hypothèses!$C$31+U47*Hypothèses!$C$16/12*Hypothèses!$B$32)*Hypothèses!$C$72 -> 3279.9635 | V9: =(V43*Hypothèses!$D$12/12*Hypothèses!$D$28+V44*Hypothèses!$D$13/12*Hypothèses!$D$29+V45*Hypothèses!$D$14/12*Hypothèses!$D$30+V46*Hypothèses!$D$15/12*Hypothèses!$D$31+V47*Hypothèses!$D$16/12*Hypothèses!$D$32)*Hypothèses!$D$72 -> 5055.8398 | W9: =(W43*Hypothèses!$D$12/12*Hypothèses!$D$28+W44*Hypothèses!$D$13/12*Hypothèses!$D$29+W45*Hypothèses!$D$14/12*Hypothèses!$D$30+W46*Hypothèses!$D$15/12*Hypothèses!$D$31+W47*Hypothèses!$D$16/12*Hypothèses!$D$32)*Hypothèses!$D$72 -> 5488.5284 | X9: =(X43*Hypothèses!$D$12/12*Hypothèses!$D$28+X44*Hypothèses!$D$13/12*Hypothèses!$D$29+X45*Hypothèses!$D$14/12*Hypothèses!$D$30+X46*Hypothèses!$D$15/12*Hypothèses!$D$31+X47*Hypothèses!$D$16/12*Hypothèses!$D$32)*Hypothèses!$D$72 -> 5933.5281 | Y9: =(Y43*Hypothèses!$D$12/12*Hypothèses!$D$28+Y44*Hypothèses!$D$13/12*Hypothèses!$D$29+Y45*Hypothèses!$D$14/12*Hypothèses!$D$30+Y46*Hypothèses!$D$15/12*Hypothèses!$D$31+Y47*Hypothèses!$D$16/12*Hypothèses!$D$32)*Hypothèses!$D$72 -> 6390.6235 | Z9: =(Z43*Hypothèses!$D$12/12*Hypothèses!$D$28+Z44*Hypothèses!$D$13/12*Hypothèses!$D$29+Z45*Hypothèses!$D$14/12*Hypothèses!$D$30+Z46*Hypothèses!$D$15/12*Hypothèses!$D$31+Z47*Hypothèses!$D$16/12*Hypothèses!$D$32)*Hypothèses!$D$72 -> 6859.6034 | AA9: =(AA43*Hypothèses!$D$12/12*Hypothèses!$D$28+AA44*Hypothèses!$D$13/12*Hypothèses!$D$29+AA45*Hypothèses!$D$14/12*Hypothèses!$D$30+AA46*Hypothèses!$D$15/12*Hypothèses!$D$31+AA47*Hypothèses!$D$16/12*Hypothèses!$D$32)*Hypothèses!$D$72 -> 7340.2604 | AB9: =(AB43*Hypothèses!$D$12/12*Hypothèses!$D$28+AB44*Hypothèses!$D$13/12*Hypothèses!$D$29+AB45*Hypothèses!$D$14/12*Hypothèses!$D$30+AB46*Hypothèses!$D$15/12*Hypothèses!$D$31+AB47*Hypothèses!$D$16/12*Hypothèses!$D$32)*Hypothèses!$D$72 -> 7832.3911 | AC9: =(AC43*Hypothèses!$D$12/12*Hypothèses!$D$28+AC44*Hypothèses!$D$13/12*Hypothèses!$D$29+AC45*Hypothèses!$D$14/12*Hypothèses!$D$30+AC46*Hypothèses!$D$15/12*Hypothèses!$D$31+AC47*Hypothèses!$D$16/12*Hypothèses!$D$32)*Hypothèses!$D$72 -> 8356.9607 | ... AG9: =(AG43*Hypothèses!$D$12/12*Hypothèses!$D$28+AG44*Hypothèses!$D$13/12*Hypothèses!$D$29+AG45*Hypothèses!$D$14/12*Hypothèses!$D$30+AG46*Hypothèses!$D$15/12*Hypothèses!$D$31+AG47*Hypothèses!$D$16/12*Hypothèses!$D$32)*Hypothèses!$D$72 -> 10578.608 | AH9: =(AH43*Hypothèses!$E$12/12*Hypothèses!$E$28+AH44*Hypothèses!$E$13/12*Hypothèses!$E$29+AH45*Hypothèses!$E$14/12*Hypothèses!$E$30+AH46*Hypothèses!$E$15/12*Hypothèses!$E$31+AH47*Hypothèses!$E$16/12*Hypothèses!$E$32)*Hypothèses!$E$72 -> 17623.48 | AI9: =(AI43*Hypothèses!$E$12/12*Hypothèses!$E$28+AI44*Hypothèses!$E$13/12*Hypothèses!$E$29+AI45*Hypothèses!$E$14/12*Hypothèses!$E$30+AI46*Hypothèses!$E$15/12*Hypothèses!$E$31+AI47*Hypothèses!$E$16/12*Hypothèses!$E$32)*Hypothèses!$E$72 -> 18442.204 | AJ9: =(AJ43*Hypothèses!$E$12/12*Hypothèses!$E$28+AJ44*Hypothèses!$E$13/12*Hypothèses!$E$29+AJ45*Hypothèses!$E$14/12*Hypothèses!$E$30+AJ46*Hypothèses!$E$15/12*Hypothèses!$E$31+AJ47*Hypothèses!$E$16/12*Hypothèses!$E$32)*Hypothèses!$E$72 -> 19275.952 | AK9: =(AK43*Hypothèses!$E$12/12*Hypothèses!$E$28+AK44*Hypothèses!$E$13/12*Hypothèses!$E$29+AK45*Hypothèses!$E$14/12*Hypothèses!$E$30+AK46*Hypothèses!$E$15/12*Hypothèses!$E$31+AK47*Hypothèses!$E$16/12*Hypothèses!$E$32)*Hypothèses!$E$72 -> 20124.522 | AL9: =(AL43*Hypothèses!$E$12/12*Hypothèses!$E$28+AL44*Hypothèses!$E$13/12*Hypothèses!$E$29+AL45*Hypothèses!$E$14/12*Hypothèses!$E$30+AL46*Hypothèses!$E$15/12*Hypothèses!$E$31+AL47*Hypothèses!$E$16/12*Hypothèses!$E$32)*Hypothèses!$E$72 -> 20987.713 | AM9: =(AM43*Hypothèses!$E$12/12*Hypothèses!$E$28+AM44*Hypothèses!$E$13/12*Hypothèses!$E$29+AM45*Hypothèses!$E$14/12*Hypothèses!$E$30+AM46*Hypothèses!$E$15/12*Hypothèses!$E$31+AM47*Hypothèses!$E$16/12*Hypothèses!$E$32)*Hypothèses!$E$72 -> 21865.328 | AN9: =(AN43*Hypothèses!$E$12/12*Hypothèses!$E$28+AN44*Hypothèses!$E$13/12*Hypothèses!$E$29+AN45*Hypothèses!$E$14/12*Hypothèses!$E$30+AN46*Hypothèses!$E$15/12*Hypothèses!$E$31+AN47*Hypothèses!$E$16/12*Hypothèses!$E$32)*Hypothèses!$E$72 -> 22757.171 | AO9: =(AO43*Hypothèses!$E$12/12*Hypothèses!$E$28+AO44*Hypothèses!$E$13/12*Hypothèses!$E$29+AO45*Hypothèses!$E$14/12*Hypothèses!$E$30+AO46*Hypothèses!$E$15/12*Hypothèses!$E$31+AO47*Hypothèses!$E$16/12*Hypothèses!$E$32)*Hypothèses!$E$72 -> 23663.051 | ... AS9: =(AS43*Hypothèses!$E$12/12*Hypothèses!$E$28+AS44*Hypothèses!$E$13/12*Hypothèses!$E$29+AS45*Hypothèses!$E$14/12*Hypothèses!$E$30+AS46*Hypothèses!$E$15/12*Hypothèses!$E$31+AS47*Hypothèses!$E$16/12*Hypothèses!$E$32)*Hypothèses!$E$72 -> 27423.163 | AT9: =(AT43*Hypothèses!$F$12/12*Hypothèses!$F$28+AT44*Hypothèses!$F$13/12*Hypothèses!$F$29+AT45*Hypothèses!$F$14/12*Hypothèses!$F$30+AT46*Hypothèses!$F$15/12*Hypothèses!$F$31+AT47*Hypothèses!$F$16/12*Hypothèses!$F$32)*Hypothèses!$F$72 -> 41262.389 | AU9: =(AU43*Hypothèses!$F$12/12*Hypothèses!$F$28+AU44*Hypothèses!$F$13/12*Hypothèses!$F$29+AU45*Hypothèses!$F$14/12*Hypothèses!$F$30+AU46*Hypothèses!$F$15/12*Hypothèses!$F$31+AU47*Hypothèses!$F$16/12*Hypothèses!$F$32)*Hypothèses!$F$72 -> 42156.456 | AV9: =(AV43*Hypothèses!$F$12/12*Hypothèses!$F$28+AV44*Hypothèses!$F$13/12*Hypothèses!$F$29+AV45*Hypothèses!$F$14/12*Hypothèses!$F$30+AV46*Hypothèses!$F$15/12*Hypothèses!$F$31+AV47*Hypothèses!$F$16/12*Hypothèses!$F$32)*Hypothèses!$F$72 -> 43055.114 | AW9: =(AW43*Hypothèses!$F$12/12*Hypothèses!$F$28+AW44*Hypothèses!$F$13/12*Hypothèses!$F$29+AW45*Hypothèses!$F$14/12*Hypothèses!$F$30+AW46*Hypothèses!$F$15/12*Hypothèses!$F$31+AW47*Hypothèses!$F$16/12*Hypothèses!$F$32)*Hypothèses!$F$72 -> 43958.286 | AX9: =(AX43*Hypothèses!$F$12/12*Hypothèses!$F$28+AX44*Hypothèses!$F$13/12*Hypothèses!$F$29+AX45*Hypothèses!$F$14/12*Hypothèses!$F$30+AX46*Hypothèses!$F$15/12*Hypothèses!$F$31+AX47*Hypothèses!$F$16/12*Hypothèses!$F$32)*Hypothèses!$F$72 -> 44865.898 | AY9: =(AY43*Hypothèses!$F$12/12*Hypothèses!$F$28+AY44*Hypothèses!$F$13/12*Hypothèses!$F$29+AY45*Hypothèses!$F$14/12*Hypothèses!$F$30+AY46*Hypothèses!$F$15/12*Hypothèses!$F$31+AY47*Hypothèses!$F$16/12*Hypothèses!$F$32)*Hypothèses!$F$72 -> 45777.875 | AZ9: =(AZ43*Hypothèses!$F$12/12*Hypothèses!$F$28+AZ44*Hypothèses!$F$13/12*Hypothèses!$F$29+AZ45*Hypothèses!$F$14/12*Hypothèses!$F$30+AZ46*Hypothèses!$F$15/12*Hypothèses!$F$31+AZ47*Hypothèses!$F$16/12*Hypothèses!$F$32)*Hypothèses!$F$72 -> 46694.144 | BA9: =(BA43*Hypothèses!$F$12/12*Hypothèses!$F$28+BA44*Hypothèses!$F$13/12*Hypothèses!$F$29+BA45*Hypothèses!$F$14/12*Hypothèses!$F$30+BA46*Hypothèses!$F$15/12*Hypothèses!$F$31+BA47*Hypothèses!$F$16/12*Hypothèses!$F$32)*Hypothèses!$F$72 -> 47819.269 | ... BE9: =(BE43*Hypothèses!$F$12/12*Hypothèses!$F$28+BE44*Hypothèses!$F$13/12*Hypothèses!$F$29+BE45*Hypothèses!$F$14/12*Hypothèses!$F$30+BE46*Hypothèses!$F$15/12*Hypothèses!$F$31+BE47*Hypothèses!$F$16/12*Hypothèses!$F$32)*Hypothèses!$F$72 -> 52364.74 | BF9: =(BF43*Hypothèses!$G$12/12*Hypothèses!$G$28+BF44*Hypothèses!$G$13/12*Hypothèses!$G$29+BF45*Hypothèses!$G$14/12*Hypothèses!$G$30+BF46*Hypothèses!$G$15/12*Hypothèses!$G$31+BF47*Hypothèses!$G$16/12*Hypothèses!$G$32)*Hypothèses!$G$72 -> 78976.399 | BG9: =(BG43*Hypothèses!$G$12/12*Hypothèses!$G$28+BG44*Hypothèses!$G$13/12*Hypothèses!$G$29+BG45*Hypothèses!$G$14/12*Hypothèses!$G$30+BG46*Hypothèses!$G$15/12*Hypothèses!$G$31+BG47*Hypothèses!$G$16/12*Hypothèses!$G$32)*Hypothèses!$G$72 -> 80234.286 | BH9: =(BH43*Hypothèses!$G$12/12*Hypothèses!$G$28+BH44*Hypothèses!$G$13/12*Hypothèses!$G$29+BH45*Hypothèses!$G$14/12*Hypothèses!$G$30+BH46*Hypothèses!$G$15/12*Hypothèses!$G$31+BH47*Hypothèses!$G$16/12*Hypothèses!$G$32)*Hypothèses!$G$72 -> 82601.85 | BI9: =(BI43*Hypothèses!$G$12/12*Hypothèses!$G$28+BI44*Hypothèses!$G$13/12*Hypothèses!$G$29+BI45*Hypothèses!$G$14/12*Hypothèses!$G$30+BI46*Hypothèses!$G$15/12*Hypothèses!$G$31+BI47*Hypothèses!$G$16/12*Hypothèses!$G$32)*Hypothèses!$G$72 -> 84949.193 | BJ9: =(BJ43*Hypothèses!$G$12/12*Hypothèses!$G$28+BJ44*Hypothèses!$G$13/12*Hypothèses!$G$29+BJ45*Hypothèses!$G$14/12*Hypothèses!$G$30+BJ46*Hypothèses!$G$15/12*Hypothèses!$G$31+BJ47*Hypothèses!$G$16/12*Hypothèses!$G$32)*Hypothèses!$G$72 -> 88395.382 | BK9: =(BK43*Hypothèses!$G$12/12*Hypothèses!$G$28+BK44*Hypothèses!$G$13/12*Hypothèses!$G$29+BK45*Hypothèses!$G$14/12*Hypothèses!$G$30+BK46*Hypothèses!$G$15/12*Hypothèses!$G$31+BK47*Hypothèses!$G$16/12*Hypothèses!$G$32)*Hypothèses!$G$72 -> 92929.676 | BL9: =(BL43*Hypothèses!$G$12/12*Hypothèses!$G$28+BL44*Hypothèses!$G$13/12*Hypothèses!$G$29+BL45*Hypothèses!$G$14/12*Hypothèses!$G$30+BL46*Hypothèses!$G$15/12*Hypothèses!$G$31+BL47*Hypothèses!$G$16/12*Hypothèses!$G$32)*Hypothèses!$G$72 -> 97422.638 | BM9: =(BM43*Hypothèses!$G$12/12*Hypothèses!$G$28+BM44*Hypothèses!$G$13/12*Hypothèses!$G$29+BM45*Hypothèses!$G$14/12*Hypothèses!$G$30+BM46*Hypothèses!$G$15/12*Hypothèses!$G$31+BM47*Hypothèses!$G$16/12*Hypothèses!$G$32)*Hypothèses!$G$72 -> 107000.8 | ... BQ9: =(BQ43*Hypothèses!$G$12/12*Hypothèses!$G$28+BQ44*Hypothèses!$G$13/12*Hypothèses!$G$29+BQ45*Hypothèses!$G$14/12*Hypothèses!$G$30+BQ46*Hypothèses!$G$15/12*Hypothèses!$G$31+BQ47*Hypothèses!$G$16/12*Hypothèses!$G$32)*Hypothèses!$G$72 -> 144405.05 | BR9: =(BR43*Hypothèses!$H$12/12*Hypothèses!$H$28+BR44*Hypothèses!$H$13/12*Hypothèses!$H$29+BR45*Hypothèses!$H$14/12*Hypothèses!$H$30+BR46*Hypothèses!$H$15/12*Hypothèses!$H$31+BR47*Hypothèses!$H$16/12*Hypothèses!$H$32)*Hypothèses!$H$72 -> 209224.2 | BS9: =(BS43*Hypothèses!$H$12/12*Hypothèses!$H$28+BS44*Hypothèses!$H$13/12*Hypothèses!$H$29+BS45*Hypothèses!$H$14/12*Hypothèses!$H$30+BS46*Hypothèses!$H$15/12*Hypothèses!$H$31+BS47*Hypothèses!$H$16/12*Hypothèses!$H$32)*Hypothèses!$H$72 -> 222287.49 | BT9: =(BT43*Hypothèses!$H$12/12*Hypothèses!$H$28+BT44*Hypothèses!$H$13/12*Hypothèses!$H$29+BT45*Hypothèses!$H$14/12*Hypothèses!$H$30+BT46*Hypothèses!$H$15/12*Hypothèses!$H$31+BT47*Hypothèses!$H$16/12*Hypothèses!$H$32)*Hypothèses!$H$72 -> 235224.58 | BU9: =(BU43*Hypothèses!$H$12/12*Hypothèses!$H$28+BU44*Hypothèses!$H$13/12*Hypothèses!$H$29+BU45*Hypothèses!$H$14/12*Hypothèses!$H$30+BU46*Hypothèses!$H$15/12*Hypothèses!$H$31+BU47*Hypothèses!$H$16/12*Hypothèses!$H$32)*Hypothèses!$H$72 -> 248799.43 | BV9: =(BV43*Hypothèses!$H$12/12*Hypothèses!$H$28+BV44*Hypothèses!$H$13/12*Hypothèses!$H$29+BV45*Hypothèses!$H$14/12*Hypothèses!$H$30+BV46*Hypothèses!$H$15/12*Hypothèses!$H$31+BV47*Hypothèses!$H$16/12*Hypothèses!$H$32)*Hypothèses!$H$72 -> 262243.39 | BW9: =(BW43*Hypothèses!$H$12/12*Hypothèses!$H$28+BW44*Hypothèses!$H$13/12*Hypothèses!$H$29+BW45*Hypothèses!$H$14/12*Hypothèses!$H$30+BW46*Hypothèses!$H$15/12*Hypothèses!$H$31+BW47*Hypothèses!$H$16/12*Hypothèses!$H$32)*Hypothèses!$H$72 -> 275558.06 | BX9: =(BX43*Hypothèses!$H$12/12*Hypothèses!$H$28+BX44*Hypothèses!$H$13/12*Hypothèses!$H$29+BX45*Hypothèses!$H$14/12*Hypothèses!$H$30+BX46*Hypothèses!$H$15/12*Hypothèses!$H$31+BX47*Hypothèses!$H$16/12*Hypothèses!$H$32)*Hypothèses!$H$72 -> 291032.24 | BY9: =(BY43*Hypothèses!$H$12/12*Hypothèses!$H$28+BY44*Hypothèses!$H$13/12*Hypothèses!$H$29+BY45*Hypothèses!$H$14/12*Hypothèses!$H$30+BY46*Hypothèses!$H$15/12*Hypothèses!$H$31+BY47*Hypothèses!$H$16/12*Hypothèses!$H$32)*Hypothèses!$H$72 -> 327318.56 | ... CC9: =(CC43*Hypothèses!$H$12/12*Hypothèses!$H$28+CC44*Hypothèses!$H$13/12*Hypothèses!$H$29+CC45*Hypothèses!$H$14/12*Hypothèses!$H$30+CC46*Hypothèses!$H$15/12*Hypothèses!$H$31+CC47*Hypothèses!$H$16/12*Hypothèses!$H$32)*Hypothèses!$H$72 -> 474956.64
A12: Prestation | C12: =SUM(C13:C14) -> 0 | D12: =SUM(D13:D14) -> 315.82164 | E12: =SUM(E13:E14) -> 323.34398 | F12: =SUM(F13:F14) -> 330.64017 | G12: =SUM(G13:G14) -> 337.71733 | H12: =SUM(H13:H14) -> 344.58235 | I12: =SUM(I13:I14) -> 351.24187 | J12: =SUM(J13:J14) -> 892.48048 | ... CC12: =SUM(CC13:CC14) -> 32570.151
A13: Installations Optiwize Pro | D13: =(D19-C19)*Hypothèses!$B$74 -> 0 | E13: =(E19-D19)*Hypothèses!$B$74 -> 0 | F13: =(F19-E19)*Hypothèses!$B$74 -> 0 | G13: =(G19-F19)*Hypothèses!$B$74 -> 0 | H13: =(H19-G19)*Hypothèses!$B$74 -> 0 | I13: =(I19-H19)*Hypothèses!$B$74 -> 0 | J13: =(J19-I19)*Hypothèses!$B$74 -> 0 | K13: =(K19-J19)*Hypothèses!$B$74 -> 0 | ... CC13: =(CC19-CB19)*Hypothèses!$B$74 -> 0
A14: Installations Leads | D14: =(D42-C42)*Hypothèses!$B$75 -> 315.82164 | E14: =(E42-D42)*Hypothèses!$B$75 -> 323.34398 | F14: =(F42-E42)*Hypothèses!$B$75 -> 330.64017 | G14: =(G42-F42)*Hypothèses!$B$75 -> 337.71733 | H14: =(H42-G42)*Hypothèses!$B$75 -> 344.58235 | I14: =(I42-H42)*Hypothèses!$B$75 -> 351.24187 | J14: =(J42-I42)*Hypothèses!$B$75 -> 892.48048 | K14: =(K42-J42)*Hypothèses!$B$75 -> 942.38076 | ... CC14: =(CC42-CB42)*Hypothèses!$B$75 -> 32570.151
A16: MILESTONES | V16: Lancement Espagne | AH16: Lancement Suisse | AM16: Leads v2
A19: # CLIENTS | C19: =C20+C51 -> 159 | D19: =D20+D51 -> 162.26227 | E19: =E20+E51 -> 165.46148 | F19: =F20+F51 -> 168.59911 | G19: =G20+G51 -> 171.67659 | H19: =H20+H51 -> 174.69531 | I19: =I20+I51 -> 177.65663 | J19: =J20+J51 -> 181.04575 | ... CC19: =CC20+CC51 -> 2128.5565
A20: Installateurs/developpeurs | C20: =C21+C28+C35 -> 111.3 | D20: =D21+D28+D35 -> 113.58359 | E20: =E21+E28+E35 -> 115.82304 | F20: =F21+F28+F35 -> 118.01938 | G20: =G21+G28+G35 -> 120.17361 | H20: =H21+H28+H35 -> 122.28672 | I20: =I21+I28+I35 -> 124.35964 | J20: =J21+J28+J35 -> 126.73202 | ... CC20: =CC21+CC28+CC35 -> 1308.2322
A21: Optiwize Pro - Premium | C21: =C22+C23+C24 -> 35 | D21: =D22+D23+D24 -> 35.697549 | E21: =E22+E23+E24 -> 36.388123 | F21: =F22+F23+F24 -> 37.071791 | G21: =G22+G23+G24 -> 37.748622 | H21: =H22+H23+H24 -> 38.418685 | I21: =I22+I23+I24 -> 39.082047 | J21: =J22+J23+J24 -> 39.959787 | ... CC21: =CC22+CC23+CC24 -> 575.83379
A22: dt FR | C22: 35 | D22: =C22*(1-'Annexe G Evolution Portefeuill'!$C20)+C$86*'Annexe B Plan commercial'!$B5*Hypothèses!$B$54 -> 35.697549 | E22: =D22*(1-'Annexe G Evolution Portefeuill'!$C20)+D$86*'Annexe B Plan commercial'!$B5*Hypothèses!$B$54 -> 36.388123 | F22: =E22*(1-'Annexe G Evolution Portefeuill'!$C20)+E$86*'Annexe B Plan commercial'!$B5*Hypothèses!$B$54 -> 37.071791 | G22: =F22*(1-'Annexe G Evolution Portefeuill'!$C20)+F$86*'Annexe B Plan commercial'!$B5*Hypothèses!$B$54 -> 37.748622 | H22: =G22*(1-'Annexe G Evolution Portefeuill'!$C20)+G$86*'Annexe B Plan commercial'!$B5*Hypothèses!$B$54 -> 38.418685 | I22: =H22*(1-'Annexe G Evolution Portefeuill'!$C20)+H$86*'Annexe B Plan commercial'!$B5*Hypothèses!$B$54 -> 39.082047 | J22: =I22*(1-'Annexe G Evolution Portefeuill'!$D20)+I$86*'Annexe B Plan commercial'!$C5*Hypothèses!$C$54 -> 39.959787 | K22: =J22*(1-'Annexe G Evolution Portefeuill'!$D20)+J$86*'Annexe B Plan commercial'!$C5*Hypothèses!$C$54 -> 40.924104 | L22: =K22*(1-'Annexe G Evolution Portefeuill'!$D20)+K$86*'Annexe B Plan commercial'!$C5*Hypothèses!$C$54 -> 41.355705 | M22: =L22*(1-'Annexe G Evolution Portefeuill'!$D20)+L$86*'Annexe B Plan commercial'!$C5*Hypothèses!$C$54 -> 42.308854 | N22: =M22*(1-'Annexe G Evolution Portefeuill'!$D20)+M$86*'Annexe B Plan commercial'!$C5*Hypothèses!$C$54 -> 43.254378 | O22: =N22*(1-'Annexe G Evolution Portefeuill'!$D20)+N$86*'Annexe B Plan commercial'!$C5*Hypothèses!$C$54 -> 44.192337 | P22: =O22*(1-'Annexe G Evolution Portefeuill'!$D20)+O$86*'Annexe B Plan commercial'!$C5*Hypothèses!$C$54 -> 45.122793 | Q22: =P22*(1-'Annexe G Evolution Portefeuill'!$D20)+P$86*'Annexe B Plan commercial'!$C5*Hypothèses!$C$54 -> 46.2798 | ... U22: =T22*(1-'Annexe G Evolution Portefeuill'!$D20)+T$86*'Annexe B Plan commercial'!$C5*Hypothèses!$C$54 -> 50.816004 | V22: =U22*(1-'Annexe G Evolution Portefeuill'!$E20)+U$86*'Annexe B Plan commercial'!$D5*Hypothèses!$D$54 -> 52.332695 | W22: =V22*(1-'Annexe G Evolution Portefeuill'!$E20)+V$86*'Annexe B Plan commercial'!$D5*Hypothèses!$D$54 -> 53.840286 | X22: =W22*(1-'Annexe G Evolution Portefeuill'!$E20)+W$86*'Annexe B Plan commercial'!$D5*Hypothèses!$D$54 -> 55.338831 | Y22: =X22*(1-'Annexe G Evolution Portefeuill'!$E20)+X$86*'Annexe B Plan commercial'!$D5*Hypothèses!$D$54 -> 56.828385 | Z22: =Y22*(1-'Annexe G Evolution Portefeuill'!$E20)+Y$86*'Annexe B Plan commercial'!$D5*Hypothèses!$D$54 -> 58.309001 | AA22: =Z22*(1-'Annexe G Evolution Portefeuill'!$E20)+Z$86*'Annexe B Plan commercial'!$D5*Hypothèses!$D$54 -> 59.780734 | AB22: =AA22*(1-'Annexe G Evolution Portefeuill'!$E20)+AA$86*'Annexe B Plan commercial'!$D5*Hypothèses!$D$54 -> 61.243637 | AC22: =AB22*(1-'Annexe G Evolution Portefeuill'!$E20)+AB$86*'Annexe B Plan commercial'!$D5*Hypothèses!$D$54 -> 62.838158 | ... AG22: =AF22*(1-'Annexe G Evolution Portefeuill'!$E20)+AF$86*'Annexe B Plan commercial'!$D5*Hypothèses!$D$54 -> 69.121147 | AH22: =AG22*(1-'Annexe G Evolution Portefeuill'!$F20)+AG$86*'Annexe B Plan commercial'!$E5*Hypothèses!$E$54 -> 71.064522 | AI22: =AH22*(1-'Annexe G Evolution Portefeuill'!$F20)+AH$86*'Annexe B Plan commercial'!$E5*Hypothèses!$E$54 -> 72.99818 | AJ22: =AI22*(1-'Annexe G Evolution Portefeuill'!$F20)+AI$86*'Annexe B Plan commercial'!$E5*Hypothèses!$E$54 -> 74.92217 | AK22: =AJ22*(1-'Annexe G Evolution Portefeuill'!$F20)+AJ$86*'Annexe B Plan commercial'!$E5*Hypothèses!$E$54 -> 76.83654 | AL22: =AK22*(1-'Annexe G Evolution Portefeuill'!$F20)+AK$86*'Annexe B Plan commercial'!$E5*Hypothèses!$E$54 -> 78.741338 | AM22: =AL22*(1-'Annexe G Evolution Portefeuill'!$F20)+AL$86*'Annexe B Plan commercial'!$E5*Hypothèses!$E$54 -> 80.636613 | AN22: =AM22*(1-'Annexe G Evolution Portefeuill'!$F20)+AM$86*'Annexe B Plan commercial'!$E5*Hypothèses!$E$54 -> 82.52241 | AO22: =AN22*(1-'Annexe G Evolution Portefeuill'!$F20)+AN$86*'Annexe B Plan commercial'!$E5*Hypothèses!$E$54 -> 84.398779 | ... AS22: =AR22*(1-'Annexe G Evolution Portefeuill'!$F20)+AR$86*'Annexe B Plan commercial'!$E5*Hypothèses!$E$54 -> 91.810904 | AT22: =AS22*(1-'Annexe G Evolution Portefeuill'!$G20)+AS$86*'Annexe B Plan commercial'!$F5*Hypothèses!$F$54 -> 93.967828 | AU22: =AT22*(1-'Annexe G Evolution Portefeuill'!$G20)+AT$86*'Annexe B Plan commercial'!$F5*Hypothèses!$F$54 -> 96.113967 | AV22: =AU22*(1-'Annexe G Evolution Portefeuill'!$G20)+AU$86*'Annexe B Plan commercial'!$F5*Hypothèses!$F$54 -> 98.249375 | AW22: =AV22*(1-'Annexe G Evolution Portefeuill'!$G20)+AV$86*'Annexe B Plan commercial'!$F5*Hypothèses!$F$54 -> 100.37411 | AX22: =AW22*(1-'Annexe G Evolution Portefeuill'!$G20)+AW$86*'Annexe B Plan commercial'!$F5*Hypothèses!$F$54 -> 102.48821 | AY22: =AX22*(1-'Annexe G Evolution Portefeuill'!$G20)+AX$86*'Annexe B Plan commercial'!$F5*Hypothèses!$F$54 -> 104.59175 | AZ22: =AY22*(1-'Annexe G Evolution Portefeuill'!$G20)+AY$86*'Annexe B Plan commercial'!$F5*Hypothèses!$F$54 -> 106.68477 | BA22: =AZ22*(1-'Annexe G Evolution Portefeuill'!$G20)+AZ$86*'Annexe B Plan commercial'!$F5*Hypothèses!$F$54 -> 109.23531 | ... BE22: =BD22*(1-'Annexe G Evolution Portefeuill'!$G20)+BD$86*'Annexe B Plan commercial'!$F5*Hypothèses!$F$54 -> 119.3106 | BF22: =BE22*(1-'Annexe G Evolution Portefeuill'!$H20)+BE$86*'Annexe B Plan commercial'!$G5*Hypothèses!$G$54 -> 122.18351 | BG22: =BF22*(1-'Annexe G Evolution Portefeuill'!$H20)+BF$86*'Annexe B Plan commercial'!$G5*Hypothèses!$G$54 -> 125.04205 | BH22: =BG22*(1-'Annexe G Evolution Portefeuill'!$H20)+BG$86*'Annexe B Plan commercial'!$G5*Hypothèses!$G$54 -> 128.83131 | BI22: =BH22*(1-'Annexe G Evolution Portefeuill'!$H20)+BH$86*'Annexe B Plan commercial'!$G5*Hypothèses!$G$54 -> 132.60161 | BJ22: =BI22*(1-'Annexe G Evolution Portefeuill'!$H20)+BI$86*'Annexe B Plan commercial'!$G5*Hypothèses!$G$54 -> 138.24307 | BK22: =BJ22*(1-'Annexe G Evolution Portefeuill'!$H20)+BJ$86*'Annexe B Plan commercial'!$G5*Hypothèses!$G$54 -> 145.74631 | BL22: =BK22*(1-'Annexe G Evolution Portefeuill'!$H20)+BK$86*'Annexe B Plan commercial'!$G5*Hypothèses!$G$54 -> 153.21205 | BM22: =BL22*(1-'Annexe G Evolution Portefeuill'!$H20)+BL$86*'Annexe B Plan commercial'!$G5*Hypothèses!$G$54 -> 160.95099 | ... BQ22: =BP22*(1-'Annexe G Evolution Portefeuill'!$H20)+BP$86*'Annexe B Plan commercial'!$G5*Hypothèses!$G$54 -> 191.52173 | BR22: =BQ22*(1-'Annexe G Evolution Portefeuill'!$I20)+BQ$86*'Annexe B Plan commercial'!$H5*Hypothèses!$H$54 -> 199.06912 | BS22: =BR22*(1-'Annexe G Evolution Portefeuill'!$I20)+BR$86*'Annexe B Plan commercial'!$H5*Hypothèses!$H$54 -> 206.57877 | BT22: =BS22*(1-'Annexe G Evolution Portefeuill'!$I20)+BS$86*'Annexe B Plan commercial'!$H5*Hypothèses!$H$54 -> 214.05088 | BU22: =BT22*(1-'Annexe G Evolution Portefeuill'!$I20)+BT$86*'Annexe B Plan commercial'!$H5*Hypothèses!$H$54 -> 221.48563 | BV22: =BU22*(1-'Annexe G Evolution Portefeuill'!$I20)+BU$86*'Annexe B Plan commercial'!$H5*Hypothèses!$H$54 -> 228.8832 | BW22: =BV22*(1-'Annexe G Evolution Portefeuill'!$I20)+BV$86*'Annexe B Plan commercial'!$H5*Hypothèses!$H$54 -> 236.24378 | BX22: =BW22*(1-'Annexe G Evolution Portefeuill'!$I20)+BW$86*'Annexe B Plan commercial'!$H5*Hypothèses!$H$54 -> 243.56756 | BY22: =BX22*(1-'Annexe G Evolution Portefeuill'!$I20)+BX$86*'Annexe B Plan commercial'!$H5*Hypothèses!$H$54 -> 259.27853 | ... CC22: =CB22*(1-'Annexe G Evolution Portefeuill'!$I20)+CB$86*'Annexe B Plan commercial'!$H5*Hypothèses!$H$54 -> 325.09251
A23: dt ES | C23: 0 | D23: =C$23*(1-'Annexe G Evolution Portefeuill'!$C20)+C$87*'Annexe B Plan commercial'!$B$11*Hypothèses!$B$55 -> 0 | E23: =D$23*(1-'Annexe G Evolution Portefeuill'!$C20)+D$87*'Annexe B Plan commercial'!$B$11*Hypothèses!$B$55 -> 0 | F23: =E$23*(1-'Annexe G Evolution Portefeuill'!$C20)+E$87*'Annexe B Plan commercial'!$B$11*Hypothèses!$B$55 -> 0 | G23: =F$23*(1-'Annexe G Evolution Portefeuill'!$C20)+F$87*'Annexe B Plan commercial'!$B$11*Hypothèses!$B$55 -> 0 | H23: =G$23*(1-'Annexe G Evolution Portefeuill'!$C20)+G$87*'Annexe B Plan commercial'!$B$11*Hypothèses!$B$55 -> 0 | I23: =H$23*(1-'Annexe G Evolution Portefeuill'!$C20)+H$87*'Annexe B Plan commercial'!$B$11*Hypothèses!$B$55 -> 0 | J23: =I$23*(1-'Annexe G Evolution Portefeuill'!$D20)+I$87*'Annexe B Plan commercial'!$C$11*Hypothèses!$C$55 -> 0 | K23: =J$23*(1-'Annexe G Evolution Portefeuill'!$D20)+J$87*'Annexe B Plan commercial'!$C$11*Hypothèses!$C$55 -> 0 | L23: =K$23*(1-'Annexe G Evolution Portefeuill'!$D20)+K$87*'Annexe B Plan commercial'!$C$11*Hypothèses!$C$55 -> 0 | M23: =L$23*(1-'Annexe G Evolution Portefeuill'!$D20)+L$87*'Annexe B Plan commercial'!$C$11*Hypothèses!$C$55 -> 0 | N23: =M$23*(1-'Annexe G Evolution Portefeuill'!$D20)+M$87*'Annexe B Plan commercial'!$C$11*Hypothèses!$C$55 -> 0 | O23: =N$23*(1-'Annexe G Evolution Portefeuill'!$D20)+N$87*'Annexe B Plan commercial'!$C$11*Hypothèses!$C$55 -> 0 | P23: =O$23*(1-'Annexe G Evolution Portefeuill'!$D20)+O$87*'Annexe B Plan commercial'!$C$11*Hypothèses!$C$55 -> 0 | Q23: =P$23*(1-'Annexe G Evolution Portefeuill'!$D20)+P$87*'Annexe B Plan commercial'!$C$11*Hypothèses!$C$55 -> 0 | ... U23: =T$23*(1-'Annexe G Evolution Portefeuill'!$D20)+T$87*'Annexe B Plan commercial'!$C$11*Hypothèses!$C$55 -> 0 | V23: =U$23*(1-'Annexe G Evolution Portefeuill'!$E$20)+U$87*'Annexe B Plan commercial'!$D$11*Hypothèses!$D$55 -> 0 | W23: =V$23*(1-'Annexe G Evolution Portefeuill'!$E$20)+V$87*'Annexe B Plan commercial'!$D$11*Hypothèses!$D$55 -> 0 | X23: =W$23*(1-'Annexe G Evolution Portefeuill'!$E$20)+W$87*'Annexe B Plan commercial'!$D$11*Hypothèses!$D$55 -> 0 | Y23: =X$23*(1-'Annexe G Evolution Portefeuill'!$E$20)+X$87*'Annexe B Plan commercial'!$D$11*Hypothèses!$D$55 -> 0 | Z23: =Y$23*(1-'Annexe G Evolution Portefeuill'!$E$20)+Y$87*'Annexe B Plan commercial'!$D$11*Hypothèses!$D$55 -> 0 | AA23: =Z$23*(1-'Annexe G Evolution Portefeuill'!$E$20)+Z$87*'Annexe B Plan commercial'!$D$11*Hypothèses!$D$55 -> 0 | AB23: =AA$23*(1-'Annexe G Evolution Portefeuill'!$E$20)+AA$87*'Annexe B Plan commercial'!$D$11*Hypothèses!$D$55 -> 0 | AC23: =AB$23*(1-'Annexe G Evolution Portefeuill'!$E$20)+AB$87*'Annexe B Plan commercial'!$D$11*Hypothèses!$D$55 -> 0 | ... AG23: =AF$23*(1-'Annexe G Evolution Portefeuill'!$E$20)+AF$87*'Annexe B Plan commercial'!$D$11*Hypothèses!$D$55 -> 0 | AH23: =AG$23*(1-'Annexe G Evolution Portefeuill'!$F$20)+AG$87*'Annexe B Plan commercial'!$E$11*Hypothèses!$E$55 -> 0 | AI23: =AH$23*(1-'Annexe G Evolution Portefeuill'!$F$20)+AH$87*'Annexe B Plan commercial'!$E$11*Hypothèses!$E$55 -> 0 | AJ23: =AI$23*(1-'Annexe G Evolution Portefeuill'!$F$20)+AI$87*'Annexe B Plan commercial'!$E$11*Hypothèses!$E$55 -> 0 | AK23: =AJ$23*(1-'Annexe G Evolution Portefeuill'!$F$20)+AJ$87*'Annexe B Plan commercial'!$E$11*Hypothèses!$E$55 -> 0 | AL23: =AK$23*(1-'Annexe G Evolution Portefeuill'!$F$20)+AK$87*'Annexe B Plan commercial'!$E$11*Hypothèses!$E$55 -> 0 | AM23: =AL$23*(1-'Annexe G Evolution Portefeuill'!$F$20)+AL$87*'Annexe B Plan commercial'!$E$11*Hypothèses!$E$55 -> 0 | AN23: =AM$23*(1-'Annexe G Evolution Portefeuill'!$F$20)+AM$87*'Annexe B Plan commercial'!$E$11*Hypothèses!$E$55 -> 0 | AO23: =AN$23*(1-'Annexe G Evolution Portefeuill'!$F$20)+AN$87*'Annexe B Plan commercial'!$E$11*Hypothèses!$E$55 -> 0 | ... AS23: =AR$23*(1-'Annexe G Evolution Portefeuill'!$F$20)+AR$87*'Annexe B Plan commercial'!$E$11*Hypothèses!$E$55 -> 0 | AT23: =AS$23*(1-'Annexe G Evolution Portefeuill'!$G$20)+AS$87*'Annexe B Plan commercial'!$F$11*Hypothèses!$F$55 -> 0 | AU23: =AT$23*(1-'Annexe G Evolution Portefeuill'!$G$20)+AT$87*'Annexe B Plan commercial'!$F$11*Hypothèses!$F$55 -> 0 | AV23: =AU$23*(1-'Annexe G Evolution Portefeuill'!$G$20)+AU$87*'Annexe B Plan commercial'!$F$11*Hypothèses!$F$55 -> 0 | AW23: =AV$23*(1-'Annexe G Evolution Portefeuill'!$G$20)+AV$87*'Annexe B Plan commercial'!$F$11*Hypothèses!$F$55 -> 0 | AX23: =AW$23*(1-'Annexe G Evolution Portefeuill'!$G$20)+AW$87*'Annexe B Plan commercial'!$F$11*Hypothèses!$F$55 -> 0 | AY23: =AX$23*(1-'Annexe G Evolution Portefeuill'!$G$20)+AX$87*'Annexe B Plan commercial'!$F$11*Hypothèses!$F$55 -> 0 | AZ23: =AY$23*(1-'Annexe G Evolution Portefeuill'!$G$20)+AY$87*'Annexe B Plan commercial'!$F$11*Hypothèses!$F$55 -> 0 | BA23: =AZ$23*(1-'Annexe G Evolution Portefeuill'!$G$20)+AZ$87*'Annexe B Plan commercial'!$F$11*Hypothèses!$F$55 -> 0 | ... BE23: =BD$23*(1-'Annexe G Evolution Portefeuill'!$G$20)+BD$87*'Annexe B Plan commercial'!$F$11*Hypothèses!$F$55 -> 0 | BF23: =BE$23*(1-'Annexe G Evolution Portefeuill'!$H$20)+BE$87*'Annexe B Plan commercial'!$G$11*Hypothèses!$G$55 -> 0 | BG23: =BF$23*(1-'Annexe G Evolution Portefeuill'!$H$20)+BF$87*'Annexe B Plan commercial'!$G$11*Hypothèses!$G$55 -> 0 | BH23: =BG$23*(1-'Annexe G Evolution Portefeuill'!$H$20)+BG$87*'Annexe B Plan commercial'!$G$11*Hypothèses!$G$55 -> 0.84 | BI23: =BH$23*(1-'Annexe G Evolution Portefeuill'!$H$20)+BH$87*'Annexe B Plan commercial'!$G$11*Hypothèses!$G$55 -> 1.6758 | BJ23: =BI$23*(1-'Annexe G Evolution Portefeuill'!$H$20)+BI$87*'Annexe B Plan commercial'!$G$11*Hypothèses!$G$55 -> 2.507421 | BK23: =BJ$23*(1-'Annexe G Evolution Portefeuill'!$H$20)+BJ$87*'Annexe B Plan commercial'!$G$11*Hypothèses!$G$55 -> 3.3348839 | BL23: =BK$23*(1-'Annexe G Evolution Portefeuill'!$H$20)+BK$87*'Annexe B Plan commercial'!$G$11*Hypothèses!$G$55 -> 4.1582095 | BM23: =BL$23*(1-'Annexe G Evolution Portefeuill'!$H$20)+BL$87*'Annexe B Plan commercial'!$G$11*Hypothèses!$G$55 -> 12.398388 | ... BQ23: =BP$23*(1-'Annexe G Evolution Portefeuill'!$H$20)+BP$87*'Annexe B Plan commercial'!$G$11*Hypothèses!$G$55 -> 44.949149 | BR23: =BQ$23*(1-'Annexe G Evolution Portefeuill'!$I$20)+BQ$87*'Annexe B Plan commercial'!$G$11*Hypothèses!$G$55 -> 52.985373 | BS23: =BR$23*(1-'Annexe G Evolution Portefeuill'!$I$20)+BR$87*'Annexe B Plan commercial'!$G$11*Hypothèses!$G$55 -> 61.821416 | BT23: =BS$23*(1-'Annexe G Evolution Portefeuill'!$I$20)+BS$87*'Annexe B Plan commercial'!$G$11*Hypothèses!$G$55 -> 70.613279 | BU23: =BT$23*(1-'Annexe G Evolution Portefeuill'!$I$20)+BT$87*'Annexe B Plan commercial'!$G$11*Hypothèses!$G$55 -> 79.361182 | BV23: =BU$23*(1-'Annexe G Evolution Portefeuill'!$I$20)+BU$87*'Annexe B Plan commercial'!$G$11*Hypothèses!$G$55 -> 88.065346 | BW23: =BV$23*(1-'Annexe G Evolution Portefeuill'!$I$20)+BV$87*'Annexe B Plan commercial'!$G$11*Hypothèses!$G$55 -> 96.725989 | BX23: =BW$23*(1-'Annexe G Evolution Portefeuill'!$I$20)+BW$87*'Annexe B Plan commercial'!$G$11*Hypothèses!$G$55 -> 107.02333 | BY23: =BX$23*(1-'Annexe G Evolution Portefeuill'!$I$20)+BX$87*'Annexe B Plan commercial'!$G$11*Hypothèses!$G$55 -> 120.54511 | ... CC23: =CB$23*(1-'Annexe G Evolution Portefeuill'!$I$20)+CB$87*'Annexe B Plan commercial'!$G$11*Hypothèses!$G$55 -> 177.3111
A24: dt CH | C24: 0 | D24: =C$24*(1-'Annexe G Evolution Portefeuill'!$C20)+C$88*'Annexe B Plan commercial'!$B$17*Hypothèses!$B$56 -> 0 | E24: =D$24*(1-'Annexe G Evolution Portefeuill'!$C20)+D$88*'Annexe B Plan commercial'!$B$17*Hypothèses!$B$56 -> 0 | F24: =E$24*(1-'Annexe G Evolution Portefeuill'!$C20)+E$88*'Annexe B Plan commercial'!$B$17*Hypothèses!$B$56 -> 0 | G24: =F$24*(1-'Annexe G Evolution Portefeuill'!$C20)+F$88*'Annexe B Plan commercial'!$B$17*Hypothèses!$B$56 -> 0 | H24: =G$24*(1-'Annexe G Evolution Portefeuill'!$C20)+G$88*'Annexe B Plan commercial'!$B$17*Hypothèses!$B$56 -> 0 | I24: =H$24*(1-'Annexe G Evolution Portefeuill'!$C20)+H$88*'Annexe B Plan commercial'!$B$17*Hypothèses!$B$56 -> 0 | J24: =I$24*(1-'Annexe G Evolution Portefeuill'!$D20)+I$88*'Annexe B Plan commercial'!$C$17*Hypothèses!$C$56 -> 0 | K24: =J$24*(1-'Annexe G Evolution Portefeuill'!$D20)+J$88*'Annexe B Plan commercial'!$C$17*Hypothèses!$C$56 -> 0 | L24: =K$24*(1-'Annexe G Evolution Portefeuill'!$D20)+K$88*'Annexe B Plan commercial'!$C$17*Hypothèses!$C$56 -> 0 | M24: =L$24*(1-'Annexe G Evolution Portefeuill'!$D20)+L$88*'Annexe B Plan commercial'!$C$17*Hypothèses!$C$56 -> 0 | N24: =M$24*(1-'Annexe G Evolution Portefeuill'!$D20)+M$88*'Annexe B Plan commercial'!$C$17*Hypothèses!$C$56 -> 0 | O24: =N$24*(1-'Annexe G Evolution Portefeuill'!$D20)+N$88*'Annexe B Plan commercial'!$C$17*Hypothèses!$C$56 -> 0 | P24: =O$24*(1-'Annexe G Evolution Portefeuill'!$D20)+O$88*'Annexe B Plan commercial'!$C$17*Hypothèses!$C$56 -> 0 | Q24: =P$24*(1-'Annexe G Evolution Portefeuill'!$D20)+P$88*'Annexe B Plan commercial'!$C$17*Hypothèses!$C$56 -> 0 | ... U24: =T$24*(1-'Annexe G Evolution Portefeuill'!$D20)+T$88*'Annexe B Plan commercial'!$C$17*Hypothèses!$C$56 -> 0 | V24: =U$24*(1-'Annexe G Evolution Portefeuill'!$E20)+U$88*'Annexe B Plan commercial'!$D$17*Hypothèses!$D$56 -> 0 | W24: =V$24*(1-'Annexe G Evolution Portefeuill'!$E20)+V$88*'Annexe B Plan commercial'!$D$17*Hypothèses!$D$56 -> 0 | X24: =W$24*(1-'Annexe G Evolution Portefeuill'!$E20)+W$88*'Annexe B Plan commercial'!$D$17*Hypothèses!$D$56 -> 0 | Y24: =X$24*(1-'Annexe G Evolution Portefeuill'!$E20)+X$88*'Annexe B Plan commercial'!$D$17*Hypothèses!$D$56 -> 0 | Z24: =Y$24*(1-'Annexe G Evolution Portefeuill'!$E20)+Y$88*'Annexe B Plan commercial'!$D$17*Hypothèses!$D$56 -> 0 | AA24: =Z$24*(1-'Annexe G Evolution Portefeuill'!$E20)+Z$88*'Annexe B Plan commercial'!$D$17*Hypothèses!$D$56 -> 0 | AB24: =AA$24*(1-'Annexe G Evolution Portefeuill'!$E20)+AA$88*'Annexe B Plan commercial'!$D$17*Hypothèses!$D$56 -> 0 | AC24: =AB$24*(1-'Annexe G Evolution Portefeuill'!$E20)+AB$88*'Annexe B Plan commercial'!$D$17*Hypothèses!$D$56 -> 0 | ... AG24: =AF$24*(1-'Annexe G Evolution Portefeuill'!$E20)+AF$88*'Annexe B Plan commercial'!$D$17*Hypothèses!$D$56 -> 0 | AH24: =AG$24*(1-'Annexe G Evolution Portefeuill'!$F20)+AG$88*'Annexe B Plan commercial'!$E$17*Hypothèses!$E$56 -> 0 | AI24: =AH$24*(1-'Annexe G Evolution Portefeuill'!$F20)+AH$88*'Annexe B Plan commercial'!$E$17*Hypothèses!$E$56 -> 0 | AJ24: =AI$24*(1-'Annexe G Evolution Portefeuill'!$F20)+AI$88*'Annexe B Plan commercial'!$E$17*Hypothèses!$E$56 -> 0 | AK24: =AJ$24*(1-'Annexe G Evolution Portefeuill'!$F20)+AJ$88*'Annexe B Plan commercial'!$E$17*Hypothèses!$E$56 -> 0 | AL24: =AK$24*(1-'Annexe G Evolution Portefeuill'!$F20)+AK$88*'Annexe B Plan commercial'!$E$17*Hypothèses!$E$56 -> 0 | AM24: =AL$24*(1-'Annexe G Evolution Portefeuill'!$F20)+AL$88*'Annexe B Plan commercial'!$E$17*Hypothèses!$E$56 -> 0 | AN24: =AM$24*(1-'Annexe G Evolution Portefeuill'!$F20)+AM$88*'Annexe B Plan commercial'!$E$17*Hypothèses!$E$56 -> 0 | AO24: =AN$24*(1-'Annexe G Evolution Portefeuill'!$F20)+AN$88*'Annexe B Plan commercial'!$E$17*Hypothèses!$E$56 -> 0 | ... AS24: =AR$24*(1-'Annexe G Evolution Portefeuill'!$F20)+AR$88*'Annexe B Plan commercial'!$E$17*Hypothèses!$E$56 -> 0 | AT24: =AS$24*(1-'Annexe G Evolution Portefeuill'!$G20)+AS$88*'Annexe B Plan commercial'!$F$17*Hypothèses!$F$56 -> 0 | AU24: =AT$24*(1-'Annexe G Evolution Portefeuill'!$G20)+AT$88*'Annexe B Plan commercial'!$F$17*Hypothèses!$F$56 -> 0 | AV24: =AU$24*(1-'Annexe G Evolution Portefeuill'!$G20)+AU$88*'Annexe B Plan commercial'!$F$17*Hypothèses!$F$56 -> 0 | AW24: =AV$24*(1-'Annexe G Evolution Portefeuill'!$G20)+AV$88*'Annexe B Plan commercial'!$F$17*Hypothèses!$F$56 -> 0 | AX24: =AW$24*(1-'Annexe G Evolution Portefeuill'!$G20)+AW$88*'Annexe B Plan commercial'!$F$17*Hypothèses!$F$56 -> 0 | AY24: =AX$24*(1-'Annexe G Evolution Portefeuill'!$G20)+AX$88*'Annexe B Plan commercial'!$F$17*Hypothèses!$F$56 -> 0 | AZ24: =AY$24*(1-'Annexe G Evolution Portefeuill'!$G20)+AY$88*'Annexe B Plan commercial'!$F$17*Hypothèses!$F$56 -> 0 | BA24: =AZ$24*(1-'Annexe G Evolution Portefeuill'!$G20)+AZ$88*'Annexe B Plan commercial'!$F$17*Hypothèses!$F$56 -> 0 | ... BE24: =BD$24*(1-'Annexe G Evolution Portefeuill'!$G20)+BD$88*'Annexe B Plan commercial'!$F$17*Hypothèses!$F$56 -> 0 | BF24: =BE$24*(1-'Annexe G Evolution Portefeuill'!$H20)+BE$88*'Annexe B Plan commercial'!$G$17*Hypothèses!$G$56 -> 0 | BG24: =BF$24*(1-'Annexe G Evolution Portefeuill'!$H20)+BF$88*'Annexe B Plan commercial'!$G$17*Hypothèses!$G$56 -> 0 | BH24: =BG$24*(1-'Annexe G Evolution Portefeuill'!$H20)+BG$88*'Annexe B Plan commercial'!$G$17*Hypothèses!$G$56 -> 0 | BI24: =BH$24*(1-'Annexe G Evolution Portefeuill'!$H20)+BH$88*'Annexe B Plan commercial'!$G$17*Hypothèses!$G$56 -> 0 | BJ24: =BI$24*(1-'Annexe G Evolution Portefeuill'!$H20)+BI$88*'Annexe B Plan commercial'!$G$17*Hypothèses!$G$56 -> 0 | BK24: =BJ$24*(1-'Annexe G Evolution Portefeuill'!$H20)+BJ$88*'Annexe B Plan commercial'!$G$17*Hypothèses!$G$56 -> 0 | BL24: =BK$24*(1-'Annexe G Evolution Portefeuill'!$H20)+BK$88*'Annexe B Plan commercial'!$G$17*Hypothèses!$G$56 -> 0 | BM24: =BL$24*(1-'Annexe G Evolution Portefeuill'!$H20)+BL$88*'Annexe B Plan commercial'!$G$17*Hypothèses!$G$56 -> 0 | ... BQ24: =BP$24*(1-'Annexe G Evolution Portefeuill'!$H20)+BP$88*'Annexe B Plan commercial'!$G$17*Hypothèses!$G$56 -> 0 | BR24: =BQ$24*(1-'Annexe G Evolution Portefeuill'!$I20)+BQ$88*'Annexe B Plan commercial'!$G$17*Hypothèses!$G$56 -> 0 | BS24: =BR$24*(1-'Annexe G Evolution Portefeuill'!$I20)+BR$88*'Annexe B Plan commercial'!$G$17*Hypothèses!$G$56 -> 0 | BT24: =BS$24*(1-'Annexe G Evolution Portefeuill'!$I20)+BS$88*'Annexe B Plan commercial'!$G$17*Hypothèses!$G$56 -> 0 | BU24: =BT$24*(1-'Annexe G Evolution Portefeuill'!$I20)+BT$88*'Annexe B Plan commercial'!$G$17*Hypothèses!$G$56 -> 0.84 | BV24: =BU$24*(1-'Annexe G Evolution Portefeuill'!$I20)+BU$88*'Annexe B Plan commercial'!$G$17*Hypothèses!$G$56 -> 1.6758 | BW24: =BV$24*(1-'Annexe G Evolution Portefeuill'!$I20)+BV$88*'Annexe B Plan commercial'!$G$17*Hypothèses!$G$56 -> 2.507421 | BX24: =BW$24*(1-'Annexe G Evolution Portefeuill'!$I20)+BW$88*'Annexe B Plan commercial'!$G$17*Hypothèses!$G$56 -> 4.1748839 | BY24: =BX$24*(1-'Annexe G Evolution Portefeuill'!$I20)+BX$88*'Annexe B Plan commercial'!$G$17*Hypothèses!$G$56 -> 18.16515 | ... CC24: =CB$24*(1-'Annexe G Evolution Portefeuill'!$I20)+CB$88*'Annexe B Plan commercial'!$G$17*Hypothèses!$G$56 -> 73.430192
A25: dt BE | C25: 0 | D25: =C$25*(1-'Annexe G Evolution Portefeuill'!$C20)+C$89*'Annexe B Plan commercial'!$B$23*Hypothèses!$B$57 -> 0 | E25: =D$25*(1-'Annexe G Evolution Portefeuill'!$C20)+D$89*'Annexe B Plan commercial'!$B$23*Hypothèses!$B$57 -> 0 | F25: =E$25*(1-'Annexe G Evolution Portefeuill'!$C20)+E$89*'Annexe B Plan commercial'!$B$23*Hypothèses!$B$57 -> 0 | G25: =F$25*(1-'Annexe G Evolution Portefeuill'!$C20)+F$89*'Annexe B Plan commercial'!$B$23*Hypothèses!$B$57 -> 0 | H25: =G$25*(1-'Annexe G Evolution Portefeuill'!$C20)+G$89*'Annexe B Plan commercial'!$B$23*Hypothèses!$B$57 -> 0 | I25: =H$25*(1-'Annexe G Evolution Portefeuill'!$C20)+H$89*'Annexe B Plan commercial'!$B$23*Hypothèses!$B$57 -> 0 | J25: =I$25*(1-'Annexe G Evolution Portefeuill'!$D20)+I$89*'Annexe B Plan commercial'!$C$23*Hypothèses!$C$57 -> 0 | K25: =J$25*(1-'Annexe G Evolution Portefeuill'!$D20)+J$89*'Annexe B Plan commercial'!$C$23*Hypothèses!$C$57 -> 0 | L25: =K$25*(1-'Annexe G Evolution Portefeuill'!$D20)+K$89*'Annexe B Plan commercial'!$C$23*Hypothèses!$C$57 -> 0 | M25: =L$25*(1-'Annexe G Evolution Portefeuill'!$D20)+L$89*'Annexe B Plan commercial'!$C$23*Hypothèses!$C$57 -> 0 | N25: =M$25*(1-'Annexe G Evolution Portefeuill'!$D20)+M$89*'Annexe B Plan commercial'!$C$23*Hypothèses!$C$57 -> 0 | O25: =N$25*(1-'Annexe G Evolution Portefeuill'!$D20)+N$89*'Annexe B Plan commercial'!$C$23*Hypothèses!$C$57 -> 0 | P25: =O$25*(1-'Annexe G Evolution Portefeuill'!$D20)+O$89*'Annexe B Plan commercial'!$C$23*Hypothèses!$C$57 -> 0 | Q25: =P$25*(1-'Annexe G Evolution Portefeuill'!$D20)+P$89*'Annexe B Plan commercial'!$C$23*Hypothèses!$C$57 -> 0 | ... U25: =T$25*(1-'Annexe G Evolution Portefeuill'!$D20)+T$89*'Annexe B Plan commercial'!$C$23*Hypothèses!$C$57 -> 0 | V25: =U$25*(1-'Annexe G Evolution Portefeuill'!$E20)+U$89*'Annexe B Plan commercial'!$D$23*Hypothèses!$D$57 -> 0 | W25: =V$25*(1-'Annexe G Evolution Portefeuill'!$E20)+V$89*'Annexe B Plan commercial'!$D$23*Hypothèses!$D$57 -> 0 | X25: =W$25*(1-'Annexe G Evolution Portefeuill'!$E20)+W$89*'Annexe B Plan commercial'!$D$23*Hypothèses!$D$57 -> 0 | Y25: =X$25*(1-'Annexe G Evolution Portefeuill'!$E20)+X$89*'Annexe B Plan commercial'!$D$23*Hypothèses!$D$57 -> 0 | Z25: =Y$25*(1-'Annexe G Evolution Portefeuill'!$E20)+Y$89*'Annexe B Plan commercial'!$D$23*Hypothèses!$D$57 -> 0 | AA25: =Z$25*(1-'Annexe G Evolution Portefeuill'!$E20)+Z$89*'Annexe B Plan commercial'!$D$23*Hypothèses!$D$57 -> 0 | AB25: =AA$25*(1-'Annexe G Evolution Portefeuill'!$E20)+AA$89*'Annexe B Plan commercial'!$D$23*Hypothèses!$D$57 -> 0 | AC25: =AB$25*(1-'Annexe G Evolution Portefeuill'!$E20)+AB$89*'Annexe B Plan commercial'!$D$23*Hypothèses!$D$57 -> 0 | ... AG25: =AF$25*(1-'Annexe G Evolution Portefeuill'!$E20)+AF$89*'Annexe B Plan commercial'!$D$23*Hypothèses!$D$57 -> 0 | AH25: =AG$25*(1-'Annexe G Evolution Portefeuill'!$F20)+AG$89*'Annexe B Plan commercial'!$E$23*Hypothèses!$E$57 -> 0 | AI25: =AH$25*(1-'Annexe G Evolution Portefeuill'!$F20)+AH$89*'Annexe B Plan commercial'!$E$23*Hypothèses!$E$57 -> 0 | AJ25: =AI$25*(1-'Annexe G Evolution Portefeuill'!$F20)+AI$89*'Annexe B Plan commercial'!$E$23*Hypothèses!$E$57 -> 0 | AK25: =AJ$25*(1-'Annexe G Evolution Portefeuill'!$F20)+AJ$89*'Annexe B Plan commercial'!$E$23*Hypothèses!$E$57 -> 0 | AL25: =AK$25*(1-'Annexe G Evolution Portefeuill'!$F20)+AK$89*'Annexe B Plan commercial'!$E$23*Hypothèses!$E$57 -> 0 | AM25: =AL$25*(1-'Annexe G Evolution Portefeuill'!$F20)+AL$89*'Annexe B Plan commercial'!$E$23*Hypothèses!$E$57 -> 0 | AN25: =AM$25*(1-'Annexe G Evolution Portefeuill'!$F20)+AM$89*'Annexe B Plan commercial'!$E$23*Hypothèses!$E$57 -> 0 | AO25: =AN$25*(1-'Annexe G Evolution Portefeuill'!$F20)+AN$89*'Annexe B Plan commercial'!$E$23*Hypothèses!$E$57 -> 0 | ... AS25: =AR$25*(1-'Annexe G Evolution Portefeuill'!$F20)+AR$89*'Annexe B Plan commercial'!$E$23*Hypothèses!$E$57 -> 0 | AT25: =AS$25*(1-'Annexe G Evolution Portefeuill'!$G21)+AS$89*'Annexe B Plan commercial'!$F$23*Hypothèses!$F$57 -> 0 | AU25: =AT$25*(1-'Annexe G Evolution Portefeuill'!$G21)+AT$89*'Annexe B Plan commercial'!$F$23*Hypothèses!$F$57 -> 0 | AV25: =AU$25*(1-'Annexe G Evolution Portefeuill'!$G21)+AU$89*'Annexe B Plan commercial'!$F$23*Hypothèses!$F$57 -> 0 | AW25: =AV$25*(1-'Annexe G Evolution Portefeuill'!$G21)+AV$89*'Annexe B Plan commercial'!$F$23*Hypothèses!$F$57 -> 0 | AX25: =AW$25*(1-'Annexe G Evolution Portefeuill'!$G21)+AW$89*'Annexe B Plan commercial'!$F$23*Hypothèses!$F$57 -> 0 | AY25: =AX$25*(1-'Annexe G Evolution Portefeuill'!$G21)+AX$89*'Annexe B Plan commercial'!$F$23*Hypothèses!$F$57 -> 0 | AZ25: =AY$25*(1-'Annexe G Evolution Portefeuill'!$G21)+AY$89*'Annexe B Plan commercial'!$F$23*Hypothèses!$F$57 -> 0 | BA25: =AZ$25*(1-'Annexe G Evolution Portefeuill'!$G21)+AZ$89*'Annexe B Plan commercial'!$F$23*Hypothèses!$F$57 -> 0 | ... BE25: =BD$25*(1-'Annexe G Evolution Portefeuill'!$G21)+BD$89*'Annexe B Plan commercial'!$F$23*Hypothèses!$F$57 -> 0 | BF25: =BE$25*(1-'Annexe G Evolution Portefeuill'!$H21)+BE$89*'Annexe B Plan commercial'!$G$23*Hypothèses!$G$57 -> 0 | BG25: =BF$25*(1-'Annexe G Evolution Portefeuill'!$H21)+BF$89*'Annexe B Plan commercial'!$G$23*Hypothèses!$G$57 -> 0 | BH25: =BG$25*(1-'Annexe G Evolution Portefeuill'!$H21)+BG$89*'Annexe B Plan commercial'!$G$23*Hypothèses!$G$57 -> 0 | BI25: =BH$25*(1-'Annexe G Evolution Portefeuill'!$H21)+BH$89*'Annexe B Plan commercial'!$G$23*Hypothèses!$G$57 -> 0 | BJ25: =BI$25*(1-'Annexe G Evolution Portefeuill'!$H21)+BI$89*'Annexe B Plan commercial'!$G$23*Hypothèses!$G$57 -> 0 | BK25: =BJ$25*(1-'Annexe G Evolution Portefeuill'!$H21)+BJ$89*'Annexe B Plan commercial'!$G$23*Hypothèses!$G$57 -> 0 | BL25: =BK$25*(1-'Annexe G Evolution Portefeuill'!$H21)+BK$89*'Annexe B Plan commercial'!$G$23*Hypothèses!$G$57 -> 0 | BM25: =BL$25*(1-'Annexe G Evolution Portefeuill'!$H21)+BL$89*'Annexe B Plan commercial'!$G$23*Hypothèses!$G$57 -> 0 | ... BQ25: =BP$25*(1-'Annexe G Evolution Portefeuill'!$H21)+BP$89*'Annexe B Plan commercial'!$G$23*Hypothèses!$G$57 -> 0 | BR25: =BQ$25*(1-'Annexe G Evolution Portefeuill'!$I21)+BQ$89*'Annexe B Plan commercial'!$G$23*Hypothèses!$G$57 -> 0 | BS25: =BR$25*(1-'Annexe G Evolution Portefeuill'!$I21)+BR$89*'Annexe B Plan commercial'!$G$23*Hypothèses!$G$57 -> 0 | BT25: =BS$25*(1-'Annexe G Evolution Portefeuill'!$I21)+BS$89*'Annexe B Plan commercial'!$G$23*Hypothèses!$G$57 -> 0 | BU25: =BT$25*(1-'Annexe G Evolution Portefeuill'!$I21)+BT$89*'Annexe B Plan commercial'!$G$23*Hypothèses!$G$57 -> 0 | BV25: =BU$25*(1-'Annexe G Evolution Portefeuill'!$I21)+BU$89*'Annexe B Plan commercial'!$G$23*Hypothèses!$G$57 -> 0 | BW25: =BV$25*(1-'Annexe G Evolution Portefeuill'!$I21)+BV$89*'Annexe B Plan commercial'!$G$23*Hypothèses!$G$57 -> 0 | BX25: =BW$25*(1-'Annexe G Evolution Portefeuill'!$I21)+BW$89*'Annexe B Plan commercial'!$G$23*Hypothèses!$G$57 -> 0 | BY25: =BX$25*(1-'Annexe G Evolution Portefeuill'!$I21)+BX$89*'Annexe B Plan commercial'!$G$23*Hypothèses!$G$57 -> 0 | ... CC25: =CB$25*(1-'Annexe G Evolution Portefeuill'!$I21)+CB$89*'Annexe B Plan commercial'!$G$23*Hypothèses!$G$57 -> 0
A26: dt DE | C26: 0 | D26: =C$26*(1-'Annexe G Evolution Portefeuill'!$C20)+C$90*'Annexe B Plan commercial'!$B$29*Hypothèses!$B$58 -> 0 | E26: =D$26*(1-'Annexe G Evolution Portefeuill'!$C20)+D$90*'Annexe B Plan commercial'!$B$29*Hypothèses!$B$58 -> 0 | F26: =E$26*(1-'Annexe G Evolution Portefeuill'!$C20)+E$90*'Annexe B Plan commercial'!$B$29*Hypothèses!$B$58 -> 0 | G26: =F$26*(1-'Annexe G Evolution Portefeuill'!$C20)+F$90*'Annexe B Plan commercial'!$B$29*Hypothèses!$B$58 -> 0 | H26: =G$26*(1-'Annexe G Evolution Portefeuill'!$C20)+G$90*'Annexe B Plan commercial'!$B$29*Hypothèses!$B$58 -> 0 | I26: =H$26*(1-'Annexe G Evolution Portefeuill'!$C20)+H$90*'Annexe B Plan commercial'!$B$29*Hypothèses!$B$58 -> 0 | J26: =I$26*(1-'Annexe G Evolution Portefeuill'!$D20)+I$90*'Annexe B Plan commercial'!$C$29*Hypothèses!$C$58 -> 0 | K26: =J$26*(1-'Annexe G Evolution Portefeuill'!$D20)+J$90*'Annexe B Plan commercial'!$C$29*Hypothèses!$C$58 -> 0 | L26: =K$26*(1-'Annexe G Evolution Portefeuill'!$D20)+K$90*'Annexe B Plan commercial'!$C$29*Hypothèses!$C$58 -> 0 | M26: =L$26*(1-'Annexe G Evolution Portefeuill'!$D20)+L$90*'Annexe B Plan commercial'!$C$29*Hypothèses!$C$58 -> 0 | N26: =M$26*(1-'Annexe G Evolution Portefeuill'!$D20)+M$90*'Annexe B Plan commercial'!$C$29*Hypothèses!$C$58 -> 0 | O26: =N$26*(1-'Annexe G Evolution Portefeuill'!$D20)+N$90*'Annexe B Plan commercial'!$C$29*Hypothèses!$C$58 -> 0 | P26: =O$26*(1-'Annexe G Evolution Portefeuill'!$D20)+O$90*'Annexe B Plan commercial'!$C$29*Hypothèses!$C$58 -> 0 | Q26: =P$26*(1-'Annexe G Evolution Portefeuill'!$D20)+P$90*'Annexe B Plan commercial'!$C$29*Hypothèses!$C$58 -> 0 | ... U26: =T$26*(1-'Annexe G Evolution Portefeuill'!$D20)+T$90*'Annexe B Plan commercial'!$C$29*Hypothèses!$C$58 -> 0 | V26: =U$26*(1-'Annexe G Evolution Portefeuill'!$E20)+U$90*'Annexe B Plan commercial'!$D$29*Hypothèses!$D$58 -> 0 | W26: =V$26*(1-'Annexe G Evolution Portefeuill'!$E20)+V$90*'Annexe B Plan commercial'!$D$29*Hypothèses!$D$58 -> 0 | X26: =W$26*(1-'Annexe G Evolution Portefeuill'!$E20)+W$90*'Annexe B Plan commercial'!$D$29*Hypothèses!$D$58 -> 0 | Y26: =X$26*(1-'Annexe G Evolution Portefeuill'!$E20)+X$90*'Annexe B Plan commercial'!$D$29*Hypothèses!$D$58 -> 0 | Z26: =Y$26*(1-'Annexe G Evolution Portefeuill'!$E20)+Y$90*'Annexe B Plan commercial'!$D$29*Hypothèses!$D$58 -> 0 | AA26: =Z$26*(1-'Annexe G Evolution Portefeuill'!$E20)+Z$90*'Annexe B Plan commercial'!$D$29*Hypothèses!$D$58 -> 0 | AB26: =AA$26*(1-'Annexe G Evolution Portefeuill'!$E20)+AA$90*'Annexe B Plan commercial'!$D$29*Hypothèses!$D$58 -> 0 | AC26: =AB$26*(1-'Annexe G Evolution Portefeuill'!$E20)+AB$90*'Annexe B Plan commercial'!$D$29*Hypothèses!$D$58 -> 0 | ... AG26: =AF$26*(1-'Annexe G Evolution Portefeuill'!$E20)+AF$90*'Annexe B Plan commercial'!$D$29*Hypothèses!$D$58 -> 0 | AH26: =AG$26*(1-'Annexe G Evolution Portefeuill'!$F20)+AG$90*'Annexe B Plan commercial'!$E$29*Hypothèses!$E$58 -> 0 | AI26: =AH$26*(1-'Annexe G Evolution Portefeuill'!$F20)+AH$90*'Annexe B Plan commercial'!$E$29*Hypothèses!$E$58 -> 0 | AJ26: =AI$26*(1-'Annexe G Evolution Portefeuill'!$F20)+AI$90*'Annexe B Plan commercial'!$E$29*Hypothèses!$E$58 -> 0 | AK26: =AJ$26*(1-'Annexe G Evolution Portefeuill'!$F20)+AJ$90*'Annexe B Plan commercial'!$E$29*Hypothèses!$E$58 -> 0 | AL26: =AK$26*(1-'Annexe G Evolution Portefeuill'!$F20)+AK$90*'Annexe B Plan commercial'!$E$29*Hypothèses!$E$58 -> 0 | AM26: =AL$26*(1-'Annexe G Evolution Portefeuill'!$F20)+AL$90*'Annexe B Plan commercial'!$E$29*Hypothèses!$E$58 -> 0 | AN26: =AM$26*(1-'Annexe G Evolution Portefeuill'!$F20)+AM$90*'Annexe B Plan commercial'!$E$29*Hypothèses!$E$58 -> 0 | AO26: =AN$26*(1-'Annexe G Evolution Portefeuill'!$F20)+AN$90*'Annexe B Plan commercial'!$E$29*Hypothèses!$E$58 -> 0 | ... AS26: =AR$26*(1-'Annexe G Evolution Portefeuill'!$F20)+AR$90*'Annexe B Plan commercial'!$E$29*Hypothèses!$E$58 -> 0 | AT26: =AS$26*(1-'Annexe G Evolution Portefeuill'!$G22)+AS$90*'Annexe B Plan commercial'!$F$29*Hypothèses!$F$58 -> 0 | AU26: =AT$26*(1-'Annexe G Evolution Portefeuill'!$G22)+AT$90*'Annexe B Plan commercial'!$F$29*Hypothèses!$F$58 -> 0 | AV26: =AU$26*(1-'Annexe G Evolution Portefeuill'!$G22)+AU$90*'Annexe B Plan commercial'!$F$29*Hypothèses!$F$58 -> 0 | AW26: =AV$26*(1-'Annexe G Evolution Portefeuill'!$G22)+AV$90*'Annexe B Plan commercial'!$F$29*Hypothèses!$F$58 -> 0 | AX26: =AW$26*(1-'Annexe G Evolution Portefeuill'!$G22)+AW$90*'Annexe B Plan commercial'!$F$29*Hypothèses!$F$58 -> 0 | AY26: =AX$26*(1-'Annexe G Evolution Portefeuill'!$G22)+AX$90*'Annexe B Plan commercial'!$F$29*Hypothèses!$F$58 -> 0 | AZ26: =AY$26*(1-'Annexe G Evolution Portefeuill'!$G22)+AY$90*'Annexe B Plan commercial'!$F$29*Hypothèses!$F$58 -> 0 | BA26: =AZ$26*(1-'Annexe G Evolution Portefeuill'!$G22)+AZ$90*'Annexe B Plan commercial'!$F$29*Hypothèses!$F$58 -> 0 | ... BE26: =BD$26*(1-'Annexe G Evolution Portefeuill'!$G22)+BD$90*'Annexe B Plan commercial'!$F$29*Hypothèses!$F$58 -> 0 | BF26: =BE$26*(1-'Annexe G Evolution Portefeuill'!$H22)+BE$90*'Annexe B Plan commercial'!$G$29*Hypothèses!$G$58 -> 0 | BG26: =BF$26*(1-'Annexe G Evolution Portefeuill'!$H22)+BF$90*'Annexe B Plan commercial'!$G$29*Hypothèses!$G$58 -> 0 | BH26: =BG$26*(1-'Annexe G Evolution Portefeuill'!$H22)+BG$90*'Annexe B Plan commercial'!$G$29*Hypothèses!$G$58 -> 0 | BI26: =BH$26*(1-'Annexe G Evolution Portefeuill'!$H22)+BH$90*'Annexe B Plan commercial'!$G$29*Hypothèses!$G$58 -> 0 | BJ26: =BI$26*(1-'Annexe G Evolution Portefeuill'!$H22)+BI$90*'Annexe B Plan commercial'!$G$29*Hypothèses!$G$58 -> 0 | BK26: =BJ$26*(1-'Annexe G Evolution Portefeuill'!$H22)+BJ$90*'Annexe B Plan commercial'!$G$29*Hypothèses!$G$58 -> 0 | BL26: =BK$26*(1-'Annexe G Evolution Portefeuill'!$H22)+BK$90*'Annexe B Plan commercial'!$G$29*Hypothèses!$G$58 -> 0 | BM26: =BL$26*(1-'Annexe G Evolution Portefeuill'!$H22)+BL$90*'Annexe B Plan commercial'!$G$29*Hypothèses!$G$58 -> 0 | ... BQ26: =BP$26*(1-'Annexe G Evolution Portefeuill'!$H22)+BP$90*'Annexe B Plan commercial'!$G$29*Hypothèses!$G$58 -> 0 | BR26: =BQ$26*(1-'Annexe G Evolution Portefeuill'!$I22)+BQ$90*'Annexe B Plan commercial'!$G$29*Hypothèses!$G$58 -> 0 | BS26: =BR$26*(1-'Annexe G Evolution Portefeuill'!$I22)+BR$90*'Annexe B Plan commercial'!$G$29*Hypothèses!$G$58 -> 0 | BT26: =BS$26*(1-'Annexe G Evolution Portefeuill'!$I22)+BS$90*'Annexe B Plan commercial'!$G$29*Hypothèses!$G$58 -> 0 | BU26: =BT$26*(1-'Annexe G Evolution Portefeuill'!$I22)+BT$90*'Annexe B Plan commercial'!$G$29*Hypothèses!$G$58 -> 0 | BV26: =BU$26*(1-'Annexe G Evolution Portefeuill'!$I22)+BU$90*'Annexe B Plan commercial'!$G$29*Hypothèses!$G$58 -> 0 | BW26: =BV$26*(1-'Annexe G Evolution Portefeuill'!$I22)+BV$90*'Annexe B Plan commercial'!$G$29*Hypothèses!$G$58 -> 0 | BX26: =BW$26*(1-'Annexe G Evolution Portefeuill'!$I22)+BW$90*'Annexe B Plan commercial'!$G$29*Hypothèses!$G$58 -> 0 | BY26: =BX$26*(1-'Annexe G Evolution Portefeuill'!$I22)+BX$90*'Annexe B Plan commercial'!$G$29*Hypothèses!$G$58 -> 0 | ... CC26: =CB$26*(1-'Annexe G Evolution Portefeuill'!$I22)+CB$90*'Annexe B Plan commercial'!$G$29*Hypothèses!$G$58 -> 0
A28: Optiwize Pro - Standard | C28: =C29+C30+C31 -> 46.2 | D28: =D29+D30+D31 -> 47.513946 | E28: =E29+E30+E31 -> 48.801613 | F28: =F29+F30+F31 -> 50.063526 | G28: =G29+G30+G31 -> 51.300202 | H28: =H29+H30+H31 -> 52.512143 | I28: =I29+I30+I31 -> 53.699846 | J28: =J29+J30+J31 -> 55.140893 | ... CC28: =CC29+CC30+CC31 -> 616.05111
A29: dt FR | C29: =66*0.7 -> 46.2 | D29: =C29*(1-'Annexe G Evolution Portefeuill'!$C$21)+C$86*'Annexe B Plan commercial'!$B6*Hypothèses!$B$54 -> 47.513946 | E29: =D29*(1-'Annexe G Evolution Portefeuill'!$C$21)+D$86*'Annexe B Plan commercial'!$B6*Hypothèses!$B$54 -> 48.801613 | F29: =E29*(1-'Annexe G Evolution Portefeuill'!$C$21)+E$86*'Annexe B Plan commercial'!$B6*Hypothèses!$B$54 -> 50.063526 | G29: =F29*(1-'Annexe G Evolution Portefeuill'!$C$21)+F$86*'Annexe B Plan commercial'!$B6*Hypothèses!$B$54 -> 51.300202 | H29: =G29*(1-'Annexe G Evolution Portefeuill'!$C$21)+G$86*'Annexe B Plan commercial'!$B6*Hypothèses!$B$54 -> 52.512143 | I29: =H29*(1-'Annexe G Evolution Portefeuill'!$C$21)+H$86*'Annexe B Plan commercial'!$B6*Hypothèses!$B$54 -> 53.699846 | J29: =I29*(1-'Annexe G Evolution Portefeuill'!$D$21)+I$86*'Annexe B Plan commercial'!$C6*Hypothèses!$C$54 -> 55.140893 | K29: =J29*(1-'Annexe G Evolution Portefeuill'!$D$21)+J$86*'Annexe B Plan commercial'!$C6*Hypothèses!$C$54 -> 56.743916 | L29: =K29*(1-'Annexe G Evolution Portefeuill'!$D$21)+K$86*'Annexe B Plan commercial'!$C6*Hypothèses!$C$54 -> 57.268887 | M29: =L29*(1-'Annexe G Evolution Portefeuill'!$D$21)+L$86*'Annexe B Plan commercial'!$C6*Hypothèses!$C$54 -> 58.83467 | N29: =M29*(1-'Annexe G Evolution Portefeuill'!$D$21)+M$86*'Annexe B Plan commercial'!$C6*Hypothèses!$C$54 -> 60.373053 | O29: =N29*(1-'Annexe G Evolution Portefeuill'!$D$21)+N$86*'Annexe B Plan commercial'!$C6*Hypothèses!$C$54 -> 61.884513 | P29: =O29*(1-'Annexe G Evolution Portefeuill'!$D$21)+O$86*'Annexe B Plan commercial'!$C6*Hypothèses!$C$54 -> 63.369523 | Q29: =P29*(1-'Annexe G Evolution Portefeuill'!$D$21)+P$86*'Annexe B Plan commercial'!$C6*Hypothèses!$C$54 -> 65.296535 | ... U29: =T29*(1-'Annexe G Evolution Portefeuill'!$D$21)+T$86*'Annexe B Plan commercial'!$C6*Hypothèses!$C$54 -> 72.673204 | V29: =U29*(1-'Annexe G Evolution Portefeuill'!$E$21)+U$86*'Annexe B Plan commercial'!$D6*Hypothèses!$D$54 -> 74.619084 | W29: =V29*(1-'Annexe G Evolution Portefeuill'!$E$21)+V$86*'Annexe B Plan commercial'!$D6*Hypothèses!$D$54 -> 76.535776 | X29: =W29*(1-'Annexe G Evolution Portefeuill'!$E$21)+W$86*'Annexe B Plan commercial'!$D6*Hypothèses!$D$54 -> 78.423717 | Y29: =X29*(1-'Annexe G Evolution Portefeuill'!$E$21)+X$86*'Annexe B Plan commercial'!$D6*Hypothèses!$D$54 -> 80.28334 | Z29: =Y29*(1-'Annexe G Evolution Portefeuill'!$E$21)+Y$86*'Annexe B Plan commercial'!$D6*Hypothèses!$D$54 -> 82.115068 | AA29: =Z29*(1-'Annexe G Evolution Portefeuill'!$E$21)+Z$86*'Annexe B Plan commercial'!$D6*Hypothèses!$D$54 -> 83.91932 | AB29: =AA29*(1-'Annexe G Evolution Portefeuill'!$E$21)+AA$86*'Annexe B Plan commercial'!$D6*Hypothèses!$D$54 -> 85.696508 | AC29: =AB29*(1-'Annexe G Evolution Portefeuill'!$E$21)+AB$86*'Annexe B Plan commercial'!$D6*Hypothèses!$D$54 -> 87.681034 | ... AG29: =AF29*(1-'Annexe G Evolution Portefeuill'!$E$21)+AF$86*'Annexe B Plan commercial'!$D6*Hypothèses!$D$54 -> 95.325887 | AH29: =AG29*(1-'Annexe G Evolution Portefeuill'!$F$21)+AG$86*'Annexe B Plan commercial'!$E6*Hypothèses!$E$54 -> 97.356623 | AI29: =AH29*(1-'Annexe G Evolution Portefeuill'!$F$21)+AH$86*'Annexe B Plan commercial'!$E6*Hypothèses!$E$54 -> 99.36096 | AJ29: =AI29*(1-'Annexe G Evolution Portefeuill'!$F$21)+AI$86*'Annexe B Plan commercial'!$E6*Hypothèses!$E$54 -> 101.33924 | AK29: =AJ29*(1-'Annexe G Evolution Portefeuill'!$F$21)+AJ$86*'Annexe B Plan commercial'!$E6*Hypothèses!$E$54 -> 103.2918 | AL29: =AK29*(1-'Annexe G Evolution Portefeuill'!$F$21)+AK$86*'Annexe B Plan commercial'!$E6*Hypothèses!$E$54 -> 105.21898 | AM29: =AL29*(1-'Annexe G Evolution Portefeuill'!$F$21)+AL$86*'Annexe B Plan commercial'!$E6*Hypothèses!$E$54 -> 107.12111 | AN29: =AM29*(1-'Annexe G Evolution Portefeuill'!$F$21)+AM$86*'Annexe B Plan commercial'!$E6*Hypothèses!$E$54 -> 108.99851 | AO29: =AN29*(1-'Annexe G Evolution Portefeuill'!$F$21)+AN$86*'Annexe B Plan commercial'!$E6*Hypothèses!$E$54 -> 110.8515 | ... AS29: =AR29*(1-'Annexe G Evolution Portefeuill'!$F$21)+AR$86*'Annexe B Plan commercial'!$E6*Hypothèses!$E$54 -> 118.02569 | AT29: =AS29*(1-'Annexe G Evolution Portefeuill'!$G$21)+AS$86*'Annexe B Plan commercial'!$F6*Hypothèses!$F$54 -> 119.87935 | AU29: =AT29*(1-'Annexe G Evolution Portefeuill'!$G$21)+AT$86*'Annexe B Plan commercial'!$F6*Hypothèses!$F$54 -> 121.71077 | AV29: =AU29*(1-'Annexe G Evolution Portefeuill'!$G$21)+AU$86*'Annexe B Plan commercial'!$F6*Hypothèses!$F$54 -> 123.52022 | AW29: =AV29*(1-'Annexe G Evolution Portefeuill'!$G$21)+AV$86*'Annexe B Plan commercial'!$F6*Hypothèses!$F$54 -> 125.30795 | AX29: =AW29*(1-'Annexe G Evolution Portefeuill'!$G$21)+AW$86*'Annexe B Plan commercial'!$F6*Hypothèses!$F$54 -> 127.07422 | AY29: =AX29*(1-'Annexe G Evolution Portefeuill'!$G$21)+AX$86*'Annexe B Plan commercial'!$F6*Hypothèses!$F$54 -> 128.81931 | AZ29: =AY29*(1-'Annexe G Evolution Portefeuill'!$G$21)+AY$86*'Annexe B Plan commercial'!$F6*Hypothèses!$F$54 -> 130.54345 | BA29: =AZ29*(1-'Annexe G Evolution Portefeuill'!$G$21)+AZ$86*'Annexe B Plan commercial'!$F6*Hypothèses!$F$54 -> 132.83189 | ... BE29: =BD29*(1-'Annexe G Evolution Portefeuill'!$G$21)+BD$86*'Annexe B Plan commercial'!$F6*Hypothèses!$F$54 -> 141.7143 | BF29: =BE29*(1-'Annexe G Evolution Portefeuill'!$H$21)+BE$86*'Annexe B Plan commercial'!$G6*Hypothèses!$G$54 -> 143.62491 | BG29: =BF29*(1-'Annexe G Evolution Portefeuill'!$H$21)+BF$86*'Annexe B Plan commercial'!$G6*Hypothèses!$G$54 -> 145.51449 | BH29: =BG29*(1-'Annexe G Evolution Portefeuill'!$H$21)+BG$86*'Annexe B Plan commercial'!$G6*Hypothèses!$G$54 -> 148.3283 | BI29: =BH29*(1-'Annexe G Evolution Portefeuill'!$H$21)+BH$86*'Annexe B Plan commercial'!$G6*Hypothèses!$G$54 -> 151.11115 | BJ29: =BI29*(1-'Annexe G Evolution Portefeuill'!$H$21)+BI$86*'Annexe B Plan commercial'!$G6*Hypothèses!$G$54 -> 155.75339 | BK29: =BJ29*(1-'Annexe G Evolution Portefeuill'!$H$21)+BJ$86*'Annexe B Plan commercial'!$G6*Hypothèses!$G$54 -> 162.23457 | BL29: =BK29*(1-'Annexe G Evolution Portefeuill'!$H$21)+BK$86*'Annexe B Plan commercial'!$G6*Hypothèses!$G$54 -> 168.64445 | BM29: =BL29*(1-'Annexe G Evolution Portefeuill'!$H$21)+BL$86*'Annexe B Plan commercial'!$G6*Hypothèses!$G$54 -> 175.29436 | ... BQ29: =BP29*(1-'Annexe G Evolution Portefeuill'!$H$21)+BP$86*'Annexe B Plan commercial'!$G6*Hypothèses!$G$54 -> 201.17052 | BR29: =BQ29*(1-'Annexe G Evolution Portefeuill'!$I$21)+BQ$86*'Annexe B Plan commercial'!$H6*Hypothèses!$H$54 -> 207.26147 | BS29: =BR29*(1-'Annexe G Evolution Portefeuill'!$I$21)+BR$86*'Annexe B Plan commercial'!$H6*Hypothèses!$H$54 -> 213.27933 | BT29: =BS29*(1-'Annexe G Evolution Portefeuill'!$I$21)+BS$86*'Annexe B Plan commercial'!$H6*Hypothèses!$H$54 -> 219.22498 | BU29: =BT29*(1-'Annexe G Evolution Portefeuill'!$I$21)+BT$86*'Annexe B Plan commercial'!$H6*Hypothèses!$H$54 -> 225.09928 | BV29: =BU29*(1-'Annexe G Evolution Portefeuill'!$I$21)+BU$86*'Annexe B Plan commercial'!$H6*Hypothèses!$H$54 -> 230.90309 | BW29: =BV29*(1-'Annexe G Evolution Portefeuill'!$I$21)+BV$86*'Annexe B Plan commercial'!$H6*Hypothèses!$H$54 -> 236.63725 | BX29: =BW29*(1-'Annexe G Evolution Portefeuill'!$I$21)+BW$86*'Annexe B Plan commercial'!$H6*Hypothèses!$H$54 -> 242.30261 | BY29: =BX29*(1-'Annexe G Evolution Portefeuill'!$I$21)+BX$86*'Annexe B Plan commercial'!$H6*Hypothèses!$H$54 -> 256.32378 | ... CC29: =CB29*(1-'Annexe G Evolution Portefeuill'!$I$21)+CB$86*'Annexe B Plan commercial'!$H6*Hypothèses!$H$54 -> 314.4585
A30: dt ES | C30: 0 | D30: =C$30*(1-'Annexe G Evolution Portefeuill'!$C21)+C$87*'Annexe B Plan commercial'!$B12*Hypothèses!$B$55 -> 0 | E30: =D$30*(1-'Annexe G Evolution Portefeuill'!$C21)+D$87*'Annexe B Plan commercial'!$B12*Hypothèses!$B$55 -> 0 | F30: =E$30*(1-'Annexe G Evolution Portefeuill'!$C21)+E$87*'Annexe B Plan commercial'!$B12*Hypothèses!$B$55 -> 0 | G30: =F$30*(1-'Annexe G Evolution Portefeuill'!$C21)+F$87*'Annexe B Plan commercial'!$B12*Hypothèses!$B$55 -> 0 | H30: =G$30*(1-'Annexe G Evolution Portefeuill'!$C21)+G$87*'Annexe B Plan commercial'!$B12*Hypothèses!$B$55 -> 0 | I30: =H$30*(1-'Annexe G Evolution Portefeuill'!$C21)+H$87*'Annexe B Plan commercial'!$B12*Hypothèses!$B$55 -> 0 | J30: =I$30*(1-'Annexe G Evolution Portefeuill'!$D21)+I$87*'Annexe B Plan commercial'!$C12*Hypothèses!$C$55 -> 0 | K30: =J$30*(1-'Annexe G Evolution Portefeuill'!$D21)+J$87*'Annexe B Plan commercial'!$C12*Hypothèses!$C$55 -> 0 | L30: =K$30*(1-'Annexe G Evolution Portefeuill'!$D21)+K$87*'Annexe B Plan commercial'!$C12*Hypothèses!$C$55 -> 0 | M30: =L$30*(1-'Annexe G Evolution Portefeuill'!$D21)+L$87*'Annexe B Plan commercial'!$C12*Hypothèses!$C$55 -> 0 | N30: =M$30*(1-'Annexe G Evolution Portefeuill'!$D21)+M$87*'Annexe B Plan commercial'!$C12*Hypothèses!$C$55 -> 0 | O30: =N$30*(1-'Annexe G Evolution Portefeuill'!$D21)+N$87*'Annexe B Plan commercial'!$C12*Hypothèses!$C$55 -> 0 | P30: =O$30*(1-'Annexe G Evolution Portefeuill'!$D21)+O$87*'Annexe B Plan commercial'!$C12*Hypothèses!$C$55 -> 0 | Q30: =P$30*(1-'Annexe G Evolution Portefeuill'!$D21)+P$87*'Annexe B Plan commercial'!$C12*Hypothèses!$C$55 -> 0 | ... U30: =T$30*(1-'Annexe G Evolution Portefeuill'!$D21)+T$87*'Annexe B Plan commercial'!$C12*Hypothèses!$C$55 -> 0 | V30: =U$30*(1-'Annexe G Evolution Portefeuill'!$E21)+U$87*'Annexe B Plan commercial'!$D12*Hypothèses!$D$55 -> 0 | W30: =V$30*(1-'Annexe G Evolution Portefeuill'!$E21)+V$87*'Annexe B Plan commercial'!$D12*Hypothèses!$D$55 -> 0 | X30: =W$30*(1-'Annexe G Evolution Portefeuill'!$E21)+W$87*'Annexe B Plan commercial'!$D12*Hypothèses!$D$55 -> 0 | Y30: =X$30*(1-'Annexe G Evolution Portefeuill'!$E21)+X$87*'Annexe B Plan commercial'!$D12*Hypothèses!$D$55 -> 0 | Z30: =Y$30*(1-'Annexe G Evolution Portefeuill'!$E21)+Y$87*'Annexe B Plan commercial'!$D12*Hypothèses!$D$55 -> 0 | AA30: =Z$30*(1-'Annexe G Evolution Portefeuill'!$E21)+Z$87*'Annexe B Plan commercial'!$D12*Hypothèses!$D$55 -> 0 | AB30: =AA$30*(1-'Annexe G Evolution Portefeuill'!$E21)+AA$87*'Annexe B Plan commercial'!$D12*Hypothèses!$D$55 -> 0 | AC30: =AB$30*(1-'Annexe G Evolution Portefeuill'!$E21)+AB$87*'Annexe B Plan commercial'!$D12*Hypothèses!$D$55 -> 0 | ... AG30: =AF$30*(1-'Annexe G Evolution Portefeuill'!$E21)+AF$87*'Annexe B Plan commercial'!$D12*Hypothèses!$D$55 -> 0 | AH30: =AG$30*(1-'Annexe G Evolution Portefeuill'!$F21)+AG$87*'Annexe B Plan commercial'!$E12*Hypothèses!$E$55 -> 0 | AI30: =AH$30*(1-'Annexe G Evolution Portefeuill'!$F21)+AH$87*'Annexe B Plan commercial'!$E12*Hypothèses!$E$55 -> 0 | AJ30: =AI$30*(1-'Annexe G Evolution Portefeuill'!$F21)+AI$87*'Annexe B Plan commercial'!$E12*Hypothèses!$E$55 -> 0 | AK30: =AJ$30*(1-'Annexe G Evolution Portefeuill'!$F21)+AJ$87*'Annexe B Plan commercial'!$E12*Hypothèses!$E$55 -> 0 | AL30: =AK$30*(1-'Annexe G Evolution Portefeuill'!$F21)+AK$87*'Annexe B Plan commercial'!$E12*Hypothèses!$E$55 -> 0 | AM30: =AL$30*(1-'Annexe G Evolution Portefeuill'!$F21)+AL$87*'Annexe B Plan commercial'!$E12*Hypothèses!$E$55 -> 0 | AN30: =AM$30*(1-'Annexe G Evolution Portefeuill'!$F21)+AM$87*'Annexe B Plan commercial'!$E12*Hypothèses!$E$55 -> 0 | AO30: =AN$30*(1-'Annexe G Evolution Portefeuill'!$F21)+AN$87*'Annexe B Plan commercial'!$E12*Hypothèses!$E$55 -> 0 | ... AS30: =AR$30*(1-'Annexe G Evolution Portefeuill'!$F21)+AR$87*'Annexe B Plan commercial'!$E12*Hypothèses!$E$55 -> 0 | AT30: =AS$30*(1-'Annexe G Evolution Portefeuill'!$G21)+AS$87*'Annexe B Plan commercial'!$F12*Hypothèses!$F$55 -> 0 | AU30: =AT$30*(1-'Annexe G Evolution Portefeuill'!$G21)+AT$87*'Annexe B Plan commercial'!$F12*Hypothèses!$F$55 -> 0 | AV30: =AU$30*(1-'Annexe G Evolution Portefeuill'!$G21)+AU$87*'Annexe B Plan commercial'!$F12*Hypothèses!$F$55 -> 0 | AW30: =AV$30*(1-'Annexe G Evolution Portefeuill'!$G21)+AV$87*'Annexe B Plan commercial'!$F12*Hypothèses!$F$55 -> 0 | AX30: =AW$30*(1-'Annexe G Evolution Portefeuill'!$G21)+AW$87*'Annexe B Plan commercial'!$F12*Hypothèses!$F$55 -> 0 | AY30: =AX$30*(1-'Annexe G Evolution Portefeuill'!$G21)+AX$87*'Annexe B Plan commercial'!$F12*Hypothèses!$F$55 -> 0 | AZ30: =AY$30*(1-'Annexe G Evolution Portefeuill'!$G21)+AY$87*'Annexe B Plan commercial'!$F12*Hypothèses!$F$55 -> 0 | BA30: =AZ$30*(1-'Annexe G Evolution Portefeuill'!$G21)+AZ$87*'Annexe B Plan commercial'!$F12*Hypothèses!$F$55 -> 0 | ... BE30: =BD$30*(1-'Annexe G Evolution Portefeuill'!$G21)+BD$87*'Annexe B Plan commercial'!$F12*Hypothèses!$F$55 -> 0 | BF30: =BE$30*(1-'Annexe G Evolution Portefeuill'!$H21)+BE$87*'Annexe B Plan commercial'!$G12*Hypothèses!$G$55 -> 0 | BG30: =BF$30*(1-'Annexe G Evolution Portefeuill'!$H21)+BF$87*'Annexe B Plan commercial'!$G12*Hypothèses!$G$55 -> 0 | BH30: =BG$30*(1-'Annexe G Evolution Portefeuill'!$H21)+BG$87*'Annexe B Plan commercial'!$G12*Hypothèses!$G$55 -> 1.05 | BI30: =BH$30*(1-'Annexe G Evolution Portefeuill'!$H21)+BH$87*'Annexe B Plan commercial'!$G12*Hypothèses!$G$55 -> 2.08845 | BJ30: =BI$30*(1-'Annexe G Evolution Portefeuill'!$H21)+BI$87*'Annexe B Plan commercial'!$G12*Hypothèses!$G$55 -> 3.115477 | BK30: =BJ$30*(1-'Annexe G Evolution Portefeuill'!$H21)+BJ$87*'Annexe B Plan commercial'!$G12*Hypothèses!$G$55 -> 4.1312068 | BL30: =BK$30*(1-'Annexe G Evolution Portefeuill'!$H21)+BK$87*'Annexe B Plan commercial'!$G12*Hypothèses!$G$55 -> 5.1357635 | BM30: =BL$30*(1-'Annexe G Evolution Portefeuill'!$H21)+BL$87*'Annexe B Plan commercial'!$G12*Hypothèses!$G$55 -> 15.405482 | ... BQ30: =BP$30*(1-'Annexe G Evolution Portefeuill'!$H21)+BP$87*'Annexe B Plan commercial'!$G12*Hypothèses!$G$55 -> 55.367047 | BR30: =BQ$30*(1-'Annexe G Evolution Portefeuill'!$I21)+BQ$87*'Annexe B Plan commercial'!$H12*Hypothèses!$H$55 -> 65.028854 | BS30: =BR$30*(1-'Annexe G Evolution Portefeuill'!$I21)+BR$87*'Annexe B Plan commercial'!$H12*Hypothèses!$H$55 -> 75.62472 | BT30: =BS$30*(1-'Annexe G Evolution Portefeuill'!$I21)+BS$87*'Annexe B Plan commercial'!$H12*Hypothèses!$H$55 -> 86.093436 | BU30: =BT$30*(1-'Annexe G Evolution Portefeuill'!$I21)+BT$87*'Annexe B Plan commercial'!$H12*Hypothèses!$H$55 -> 96.436527 | BV30: =BU$30*(1-'Annexe G Evolution Portefeuill'!$I21)+BU$87*'Annexe B Plan commercial'!$H12*Hypothèses!$H$55 -> 106.6555 | BW30: =BV$30*(1-'Annexe G Evolution Portefeuill'!$I21)+BV$87*'Annexe B Plan commercial'!$H12*Hypothèses!$H$55 -> 116.75185 | BX30: =BW$30*(1-'Annexe G Evolution Portefeuill'!$I21)+BW$87*'Annexe B Plan commercial'!$H12*Hypothèses!$H$55 -> 128.82704 | BY30: =BX$30*(1-'Annexe G Evolution Portefeuill'!$I21)+BX$87*'Annexe B Plan commercial'!$H12*Hypothèses!$H$55 -> 144.85223 | ... CC30: =CB$30*(1-'Annexe G Evolution Portefeuill'!$I21)+CB$87*'Annexe B Plan commercial'!$H12*Hypothèses!$H$55 -> 211.22771
A31: dt CH | C31: 0 | D31: =C$31*(1-'Annexe G Evolution Portefeuill'!$C21)+C$88*'Annexe B Plan commercial'!$B18*Hypothèses!$B$56 -> 0 | E31: =D$31*(1-'Annexe G Evolution Portefeuill'!$C21)+D$88*'Annexe B Plan commercial'!$B18*Hypothèses!$B$56 -> 0 | F31: =E$31*(1-'Annexe G Evolution Portefeuill'!$C21)+E$88*'Annexe B Plan commercial'!$B18*Hypothèses!$B$56 -> 0 | G31: =F$31*(1-'Annexe G Evolution Portefeuill'!$C21)+F$88*'Annexe B Plan commercial'!$B18*Hypothèses!$B$56 -> 0 | H31: =G$31*(1-'Annexe G Evolution Portefeuill'!$C21)+G$88*'Annexe B Plan commercial'!$B18*Hypothèses!$B$56 -> 0 | I31: =H$31*(1-'Annexe G Evolution Portefeuill'!$C21)+H$88*'Annexe B Plan commercial'!$B18*Hypothèses!$B$56 -> 0 | J31: =I$31*(1-'Annexe G Evolution Portefeuill'!$D21)+I$88*'Annexe B Plan commercial'!$C18*Hypothèses!$C$56 -> 0 | K31: =J$31*(1-'Annexe G Evolution Portefeuill'!$D21)+J$88*'Annexe B Plan commercial'!$C18*Hypothèses!$C$56 -> 0 | L31: =K$31*(1-'Annexe G Evolution Portefeuill'!$D21)+K$88*'Annexe B Plan commercial'!$C18*Hypothèses!$C$56 -> 0 | M31: =L$31*(1-'Annexe G Evolution Portefeuill'!$D21)+L$88*'Annexe B Plan commercial'!$C18*Hypothèses!$C$56 -> 0 | N31: =M$31*(1-'Annexe G Evolution Portefeuill'!$D21)+M$88*'Annexe B Plan commercial'!$C18*Hypothèses!$C$56 -> 0 | O31: =N$31*(1-'Annexe G Evolution Portefeuill'!$D21)+N$88*'Annexe B Plan commercial'!$C18*Hypothèses!$C$56 -> 0 | P31: =O$31*(1-'Annexe G Evolution Portefeuill'!$D21)+O$88*'Annexe B Plan commercial'!$C18*Hypothèses!$C$56 -> 0 | Q31: =P$31*(1-'Annexe G Evolution Portefeuill'!$D21)+P$88*'Annexe B Plan commercial'!$C18*Hypothèses!$C$56 -> 0 | ... U31: =T$31*(1-'Annexe G Evolution Portefeuill'!$D21)+T$88*'Annexe B Plan commercial'!$C18*Hypothèses!$C$56 -> 0 | V31: =U$31*(1-'Annexe G Evolution Portefeuill'!$E21)+U$88*'Annexe B Plan commercial'!$D18*Hypothèses!$D$56 -> 0 | W31: =V$31*(1-'Annexe G Evolution Portefeuill'!$E21)+V$88*'Annexe B Plan commercial'!$D18*Hypothèses!$D$56 -> 0 | X31: =W$31*(1-'Annexe G Evolution Portefeuill'!$E21)+W$88*'Annexe B Plan commercial'!$D18*Hypothèses!$D$56 -> 0 | Y31: =X$31*(1-'Annexe G Evolution Portefeuill'!$E21)+X$88*'Annexe B Plan commercial'!$D18*Hypothèses!$D$56 -> 0 | Z31: =Y$31*(1-'Annexe G Evolution Portefeuill'!$E21)+Y$88*'Annexe B Plan commercial'!$D18*Hypothèses!$D$56 -> 0 | AA31: =Z$31*(1-'Annexe G Evolution Portefeuill'!$E21)+Z$88*'Annexe B Plan commercial'!$D18*Hypothèses!$D$56 -> 0 | AB31: =AA$31*(1-'Annexe G Evolution Portefeuill'!$E21)+AA$88*'Annexe B Plan commercial'!$D18*Hypothèses!$D$56 -> 0 | AC31: =AB$31*(1-'Annexe G Evolution Portefeuill'!$E21)+AB$88*'Annexe B Plan commercial'!$D18*Hypothèses!$D$56 -> 0 | ... AG31: =AF$31*(1-'Annexe G Evolution Portefeuill'!$E21)+AF$88*'Annexe B Plan commercial'!$D18*Hypothèses!$D$56 -> 0 | AH31: =AG$31*(1-'Annexe G Evolution Portefeuill'!$F21)+AG$88*'Annexe B Plan commercial'!$E18*Hypothèses!$E$56 -> 0 | AI31: =AH$31*(1-'Annexe G Evolution Portefeuill'!$F21)+AH$88*'Annexe B Plan commercial'!$E18*Hypothèses!$E$56 -> 0 | AJ31: =AI$31*(1-'Annexe G Evolution Portefeuill'!$F21)+AI$88*'Annexe B Plan commercial'!$E18*Hypothèses!$E$56 -> 0 | AK31: =AJ$31*(1-'Annexe G Evolution Portefeuill'!$F21)+AJ$88*'Annexe B Plan commercial'!$E18*Hypothèses!$E$56 -> 0 | AL31: =AK$31*(1-'Annexe G Evolution Portefeuill'!$F21)+AK$88*'Annexe B Plan commercial'!$E18*Hypothèses!$E$56 -> 0 | AM31: =AL$31*(1-'Annexe G Evolution Portefeuill'!$F21)+AL$88*'Annexe B Plan commercial'!$E18*Hypothèses!$E$56 -> 0 | AN31: =AM$31*(1-'Annexe G Evolution Portefeuill'!$F21)+AM$88*'Annexe B Plan commercial'!$E18*Hypothèses!$E$56 -> 0 | AO31: =AN$31*(1-'Annexe G Evolution Portefeuill'!$F21)+AN$88*'Annexe B Plan commercial'!$E18*Hypothèses!$E$56 -> 0 | ... AS31: =AR$31*(1-'Annexe G Evolution Portefeuill'!$F21)+AR$88*'Annexe B Plan commercial'!$E18*Hypothèses!$E$56 -> 0 | AT31: =AS$31*(1-'Annexe G Evolution Portefeuill'!$G21)+AS$88*'Annexe B Plan commercial'!$F18*Hypothèses!$F$56 -> 0 | AU31: =AT$31*(1-'Annexe G Evolution Portefeuill'!$G21)+AT$88*'Annexe B Plan commercial'!$F18*Hypothèses!$F$56 -> 0 | AV31: =AU$31*(1-'Annexe G Evolution Portefeuill'!$G21)+AU$88*'Annexe B Plan commercial'!$F18*Hypothèses!$F$56 -> 0 | AW31: =AV$31*(1-'Annexe G Evolution Portefeuill'!$G21)+AV$88*'Annexe B Plan commercial'!$F18*Hypothèses!$F$56 -> 0 | AX31: =AW$31*(1-'Annexe G Evolution Portefeuill'!$G21)+AW$88*'Annexe B Plan commercial'!$F18*Hypothèses!$F$56 -> 0 | AY31: =AX$31*(1-'Annexe G Evolution Portefeuill'!$G21)+AX$88*'Annexe B Plan commercial'!$F18*Hypothèses!$F$56 -> 0 | AZ31: =AY$31*(1-'Annexe G Evolution Portefeuill'!$G21)+AY$88*'Annexe B Plan commercial'!$F18*Hypothèses!$F$56 -> 0 | BA31: =AZ$31*(1-'Annexe G Evolution Portefeuill'!$G21)+AZ$88*'Annexe B Plan commercial'!$F18*Hypothèses!$F$56 -> 0 | ... BE31: =BD$31*(1-'Annexe G Evolution Portefeuill'!$G21)+BD$88*'Annexe B Plan commercial'!$F18*Hypothèses!$F$56 -> 0 | BF31: =BE$31*(1-'Annexe G Evolution Portefeuill'!$H21)+BE$88*'Annexe B Plan commercial'!$G18*Hypothèses!$G$56 -> 0 | BG31: =BF$31*(1-'Annexe G Evolution Portefeuill'!$H21)+BF$88*'Annexe B Plan commercial'!$G18*Hypothèses!$G$56 -> 0 | BH31: =BG$31*(1-'Annexe G Evolution Portefeuill'!$H21)+BG$88*'Annexe B Plan commercial'!$G18*Hypothèses!$G$56 -> 0 | BI31: =BH$31*(1-'Annexe G Evolution Portefeuill'!$H21)+BH$88*'Annexe B Plan commercial'!$G18*Hypothèses!$G$56 -> 0 | BJ31: =BI$31*(1-'Annexe G Evolution Portefeuill'!$H21)+BI$88*'Annexe B Plan commercial'!$G18*Hypothèses!$G$56 -> 0 | BK31: =BJ$31*(1-'Annexe G Evolution Portefeuill'!$H21)+BJ$88*'Annexe B Plan commercial'!$G18*Hypothèses!$G$56 -> 0 | BL31: =BK$31*(1-'Annexe G Evolution Portefeuill'!$H21)+BK$88*'Annexe B Plan commercial'!$G18*Hypothèses!$G$56 -> 0 | BM31: =BL$31*(1-'Annexe G Evolution Portefeuill'!$H21)+BL$88*'Annexe B Plan commercial'!$G18*Hypothèses!$G$56 -> 0 | ... BQ31: =BP$31*(1-'Annexe G Evolution Portefeuill'!$H21)+BP$88*'Annexe B Plan commercial'!$G18*Hypothèses!$G$56 -> 0 | BR31: =BQ$31*(1-'Annexe G Evolution Portefeuill'!$I21)+BQ$88*'Annexe B Plan commercial'!$H18*Hypothèses!$H$56 -> 0 | BS31: =BR$31*(1-'Annexe G Evolution Portefeuill'!$I21)+BR$88*'Annexe B Plan commercial'!$H18*Hypothèses!$H$56 -> 0 | BT31: =BS$31*(1-'Annexe G Evolution Portefeuill'!$I21)+BS$88*'Annexe B Plan commercial'!$H18*Hypothèses!$H$56 -> 0 | BU31: =BT$31*(1-'Annexe G Evolution Portefeuill'!$I21)+BT$88*'Annexe B Plan commercial'!$H18*Hypothèses!$H$56 -> 1.05 | BV31: =BU$31*(1-'Annexe G Evolution Portefeuill'!$I21)+BU$88*'Annexe B Plan commercial'!$H18*Hypothèses!$H$56 -> 2.0874 | BW31: =BV$31*(1-'Annexe G Evolution Portefeuill'!$I21)+BV$88*'Annexe B Plan commercial'!$H18*Hypothèses!$H$56 -> 3.1123512 | BX31: =BW$31*(1-'Annexe G Evolution Portefeuill'!$I21)+BW$88*'Annexe B Plan commercial'!$H18*Hypothèses!$H$56 -> 5.175003 | BY31: =BX$31*(1-'Annexe G Evolution Portefeuill'!$I21)+BX$88*'Annexe B Plan commercial'!$H18*Hypothèses!$H$56 -> 22.626829 | ... CC31: =CB$31*(1-'Annexe G Evolution Portefeuill'!$I21)+CB$88*'Annexe B Plan commercial'!$H18*Hypothèses!$H$56 -> 90.364895
A32: dt BE | C32: 0 | D32: =C$32*(1-'Annexe G Evolution Portefeuill'!$C21)+C$87*'Annexe B Plan commercial'!$B24*Hypothèses!$B$57 -> 0 | E32: =D$32*(1-'Annexe G Evolution Portefeuill'!$C21)+D$87*'Annexe B Plan commercial'!$B24*Hypothèses!$B$57 -> 0 | F32: =E$32*(1-'Annexe G Evolution Portefeuill'!$C21)+E$87*'Annexe B Plan commercial'!$B24*Hypothèses!$B$57 -> 0 | G32: =F$32*(1-'Annexe G Evolution Portefeuill'!$C21)+F$87*'Annexe B Plan commercial'!$B24*Hypothèses!$B$57 -> 0 | H32: =G$32*(1-'Annexe G Evolution Portefeuill'!$C21)+G$87*'Annexe B Plan commercial'!$B24*Hypothèses!$B$57 -> 0 | I32: =H$32*(1-'Annexe G Evolution Portefeuill'!$C21)+H$87*'Annexe B Plan commercial'!$B24*Hypothèses!$B$57 -> 0 | J32: =I$32*(1-'Annexe G Evolution Portefeuill'!$D21)+I$89*'Annexe B Plan commercial'!$C24*Hypothèses!$C$57 -> 0 | K32: =J$32*(1-'Annexe G Evolution Portefeuill'!$D21)+J$89*'Annexe B Plan commercial'!$C24*Hypothèses!$C$57 -> 0 | L32: =K$32*(1-'Annexe G Evolution Portefeuill'!$D21)+K$89*'Annexe B Plan commercial'!$C24*Hypothèses!$C$57 -> 0 | M32: =L$32*(1-'Annexe G Evolution Portefeuill'!$D21)+L$89*'Annexe B Plan commercial'!$C24*Hypothèses!$C$57 -> 0 | N32: =M$32*(1-'Annexe G Evolution Portefeuill'!$D21)+M$89*'Annexe B Plan commercial'!$C24*Hypothèses!$C$57 -> 0 | O32: =N$32*(1-'Annexe G Evolution Portefeuill'!$D21)+N$89*'Annexe B Plan commercial'!$C24*Hypothèses!$C$57 -> 0 | P32: =O$32*(1-'Annexe G Evolution Portefeuill'!$D21)+O$89*'Annexe B Plan commercial'!$C24*Hypothèses!$C$57 -> 0 | Q32: =P$32*(1-'Annexe G Evolution Portefeuill'!$D21)+P$89*'Annexe B Plan commercial'!$C24*Hypothèses!$C$57 -> 0 | ... U32: =T$32*(1-'Annexe G Evolution Portefeuill'!$D21)+T$89*'Annexe B Plan commercial'!$C24*Hypothèses!$C$57 -> 0 | V32: =U$32*(1-'Annexe G Evolution Portefeuill'!$E21)+U$89*'Annexe B Plan commercial'!$D24*Hypothèses!$D$57 -> 0 | W32: =V$32*(1-'Annexe G Evolution Portefeuill'!$E21)+V$89*'Annexe B Plan commercial'!$D24*Hypothèses!$D$57 -> 0 | X32: =W$32*(1-'Annexe G Evolution Portefeuill'!$E21)+W$89*'Annexe B Plan commercial'!$D24*Hypothèses!$D$57 -> 0 | Y32: =X$32*(1-'Annexe G Evolution Portefeuill'!$E21)+X$89*'Annexe B Plan commercial'!$D24*Hypothèses!$D$57 -> 0 | Z32: =Y$32*(1-'Annexe G Evolution Portefeuill'!$E21)+Y$89*'Annexe B Plan commercial'!$D24*Hypothèses!$D$57 -> 0 | AA32: =Z$32*(1-'Annexe G Evolution Portefeuill'!$E21)+Z$89*'Annexe B Plan commercial'!$D24*Hypothèses!$D$57 -> 0 | AB32: =AA$32*(1-'Annexe G Evolution Portefeuill'!$E21)+AA$89*'Annexe B Plan commercial'!$D24*Hypothèses!$D$57 -> 0 | AC32: =AB$32*(1-'Annexe G Evolution Portefeuill'!$E21)+AB$89*'Annexe B Plan commercial'!$D24*Hypothèses!$D$57 -> 0 | ... AG32: =AF$32*(1-'Annexe G Evolution Portefeuill'!$E21)+AF$89*'Annexe B Plan commercial'!$D24*Hypothèses!$D$57 -> 0 | AH32: =AG$32*(1-'Annexe G Evolution Portefeuill'!$F21)+AG$89*'Annexe B Plan commercial'!$E24*Hypothèses!$E$57 -> 0 | AI32: =AH$32*(1-'Annexe G Evolution Portefeuill'!$F21)+AH$89*'Annexe B Plan commercial'!$E24*Hypothèses!$E$57 -> 0 | AJ32: =AI$32*(1-'Annexe G Evolution Portefeuill'!$F21)+AI$89*'Annexe B Plan commercial'!$E24*Hypothèses!$E$57 -> 0 | AK32: =AJ$32*(1-'Annexe G Evolution Portefeuill'!$F21)+AJ$89*'Annexe B Plan commercial'!$E24*Hypothèses!$E$57 -> 0 | AL32: =AK$32*(1-'Annexe G Evolution Portefeuill'!$F21)+AK$89*'Annexe B Plan commercial'!$E24*Hypothèses!$E$57 -> 0 | AM32: =AL$32*(1-'Annexe G Evolution Portefeuill'!$F21)+AL$89*'Annexe B Plan commercial'!$E24*Hypothèses!$E$57 -> 0 | AN32: =AM$32*(1-'Annexe G Evolution Portefeuill'!$F21)+AM$89*'Annexe B Plan commercial'!$E24*Hypothèses!$E$57 -> 0 | AO32: =AN$32*(1-'Annexe G Evolution Portefeuill'!$F21)+AN$89*'Annexe B Plan commercial'!$E24*Hypothèses!$E$57 -> 0 | ... AS32: =AR$32*(1-'Annexe G Evolution Portefeuill'!$F21)+AR$89*'Annexe B Plan commercial'!$E24*Hypothèses!$E$57 -> 0 | AT32: =AS$32*(1-'Annexe G Evolution Portefeuill'!$G21)+AS$89*'Annexe B Plan commercial'!$F24*Hypothèses!$F$57 -> 0 | AU32: =AT$32*(1-'Annexe G Evolution Portefeuill'!$G21)+AT$89*'Annexe B Plan commercial'!$F24*Hypothèses!$F$57 -> 0 | AV32: =AU$32*(1-'Annexe G Evolution Portefeuill'!$G21)+AU$89*'Annexe B Plan commercial'!$F24*Hypothèses!$F$57 -> 0 | AW32: =AV$32*(1-'Annexe G Evolution Portefeuill'!$G21)+AV$89*'Annexe B Plan commercial'!$F24*Hypothèses!$F$57 -> 0 | AX32: =AW$32*(1-'Annexe G Evolution Portefeuill'!$G21)+AW$89*'Annexe B Plan commercial'!$F24*Hypothèses!$F$57 -> 0 | AY32: =AX$32*(1-'Annexe G Evolution Portefeuill'!$G21)+AX$89*'Annexe B Plan commercial'!$F24*Hypothèses!$F$57 -> 0 | AZ32: =AY$32*(1-'Annexe G Evolution Portefeuill'!$G21)+AY$89*'Annexe B Plan commercial'!$F24*Hypothèses!$F$57 -> 0 | BA32: =AZ$32*(1-'Annexe G Evolution Portefeuill'!$G21)+AZ$89*'Annexe B Plan commercial'!$F24*Hypothèses!$F$57 -> 0 | ... BE32: =BD$32*(1-'Annexe G Evolution Portefeuill'!$G21)+BD$89*'Annexe B Plan commercial'!$F24*Hypothèses!$F$57 -> 0 | BF32: =BE$32*(1-'Annexe G Evolution Portefeuill'!$H21)+BE$89*'Annexe B Plan commercial'!$G24*Hypothèses!$G$57 -> 0 | BG32: =BF$32*(1-'Annexe G Evolution Portefeuill'!$H21)+BF$89*'Annexe B Plan commercial'!$G24*Hypothèses!$G$57 -> 0 | BH32: =BG$32*(1-'Annexe G Evolution Portefeuill'!$H21)+BG$89*'Annexe B Plan commercial'!$G24*Hypothèses!$G$57 -> 0 | BI32: =BH$32*(1-'Annexe G Evolution Portefeuill'!$H21)+BH$89*'Annexe B Plan commercial'!$G24*Hypothèses!$G$57 -> 0 | BJ32: =BI$32*(1-'Annexe G Evolution Portefeuill'!$H21)+BI$89*'Annexe B Plan commercial'!$G24*Hypothèses!$G$57 -> 0 | BK32: =BJ$32*(1-'Annexe G Evolution Portefeuill'!$H21)+BJ$89*'Annexe B Plan commercial'!$G24*Hypothèses!$G$57 -> 0 | BL32: =BK$32*(1-'Annexe G Evolution Portefeuill'!$H21)+BK$89*'Annexe B Plan commercial'!$G24*Hypothèses!$G$57 -> 0 | BM32: =BL$32*(1-'Annexe G Evolution Portefeuill'!$H21)+BL$89*'Annexe B Plan commercial'!$G24*Hypothèses!$G$57 -> 0 | ... BQ32: =BP$32*(1-'Annexe G Evolution Portefeuill'!$H21)+BP$89*'Annexe B Plan commercial'!$G24*Hypothèses!$G$57 -> 0 | BR32: =BQ$32*(1-'Annexe G Evolution Portefeuill'!$I21)+BQ$89*'Annexe B Plan commercial'!$H24*Hypothèses!$H$57 -> 0 | BS32: =BR$32*(1-'Annexe G Evolution Portefeuill'!$I21)+BR$89*'Annexe B Plan commercial'!$H24*Hypothèses!$H$57 -> 0 | BT32: =BS$32*(1-'Annexe G Evolution Portefeuill'!$I21)+BS$89*'Annexe B Plan commercial'!$H24*Hypothèses!$H$57 -> 0 | BU32: =BT$32*(1-'Annexe G Evolution Portefeuill'!$I21)+BT$89*'Annexe B Plan commercial'!$H24*Hypothèses!$H$57 -> 0 | BV32: =BU$32*(1-'Annexe G Evolution Portefeuill'!$I21)+BU$89*'Annexe B Plan commercial'!$H24*Hypothèses!$H$57 -> 0 | BW32: =BV$32*(1-'Annexe G Evolution Portefeuill'!$I21)+BV$89*'Annexe B Plan commercial'!$H24*Hypothèses!$H$57 -> 0 | BX32: =BW$32*(1-'Annexe G Evolution Portefeuill'!$I21)+BW$89*'Annexe B Plan commercial'!$H24*Hypothèses!$H$57 -> 0 | BY32: =BX$32*(1-'Annexe G Evolution Portefeuill'!$I21)+BX$89*'Annexe B Plan commercial'!$H24*Hypothèses!$H$57 -> 0 | ... CC32: =CB$32*(1-'Annexe G Evolution Portefeuill'!$I21)+CB$89*'Annexe B Plan commercial'!$H24*Hypothèses!$H$57 -> 0
A33: dt DE | C33: 0 | D33: =C$33*(1-'Annexe G Evolution Portefeuill'!$C21)+C$87*'Annexe B Plan commercial'!$B30*Hypothèses!$B$58 -> 0 | E33: =D$33*(1-'Annexe G Evolution Portefeuill'!$C21)+D$87*'Annexe B Plan commercial'!$B30*Hypothèses!$B$58 -> 0 | F33: =E$33*(1-'Annexe G Evolution Portefeuill'!$C21)+E$87*'Annexe B Plan commercial'!$B30*Hypothèses!$B$58 -> 0 | G33: =F$33*(1-'Annexe G Evolution Portefeuill'!$C21)+F$87*'Annexe B Plan commercial'!$B30*Hypothèses!$B$58 -> 0 | H33: =G$33*(1-'Annexe G Evolution Portefeuill'!$C21)+G$87*'Annexe B Plan commercial'!$B30*Hypothèses!$B$58 -> 0 | I33: =H$33*(1-'Annexe G Evolution Portefeuill'!$C21)+H$87*'Annexe B Plan commercial'!$B30*Hypothèses!$B$58 -> 0 | J33: =I$33*(1-'Annexe G Evolution Portefeuill'!$D21)+I$90*'Annexe B Plan commercial'!$C30*Hypothèses!$C$58 -> 0 | K33: =J$33*(1-'Annexe G Evolution Portefeuill'!$D21)+J$90*'Annexe B Plan commercial'!$C30*Hypothèses!$C$58 -> 0 | L33: =K$33*(1-'Annexe G Evolution Portefeuill'!$D21)+K$90*'Annexe B Plan commercial'!$C30*Hypothèses!$C$58 -> 0 | M33: =L$33*(1-'Annexe G Evolution Portefeuill'!$D21)+L$90*'Annexe B Plan commercial'!$C30*Hypothèses!$C$58 -> 0 | N33: =M$33*(1-'Annexe G Evolution Portefeuill'!$D21)+M$90*'Annexe B Plan commercial'!$C30*Hypothèses!$C$58 -> 0 | O33: =N$33*(1-'Annexe G Evolution Portefeuill'!$D21)+N$90*'Annexe B Plan commercial'!$C30*Hypothèses!$C$58 -> 0 | P33: =O$33*(1-'Annexe G Evolution Portefeuill'!$D21)+O$90*'Annexe B Plan commercial'!$C30*Hypothèses!$C$58 -> 0 | Q33: =P$33*(1-'Annexe G Evolution Portefeuill'!$D21)+P$90*'Annexe B Plan commercial'!$C30*Hypothèses!$C$58 -> 0 | ... U33: =T$33*(1-'Annexe G Evolution Portefeuill'!$D21)+T$90*'Annexe B Plan commercial'!$C30*Hypothèses!$C$58 -> 0 | V33: =U$33*(1-'Annexe G Evolution Portefeuill'!$E21)+U$90*'Annexe B Plan commercial'!$D30*Hypothèses!$D$58 -> 0 | W33: =V$33*(1-'Annexe G Evolution Portefeuill'!$E21)+V$90*'Annexe B Plan commercial'!$D30*Hypothèses!$D$58 -> 0 | X33: =W$33*(1-'Annexe G Evolution Portefeuill'!$E21)+W$90*'Annexe B Plan commercial'!$D30*Hypothèses!$D$58 -> 0 | Y33: =X$33*(1-'Annexe G Evolution Portefeuill'!$E21)+X$90*'Annexe B Plan commercial'!$D30*Hypothèses!$D$58 -> 0 | Z33: =Y$33*(1-'Annexe G Evolution Portefeuill'!$E21)+Y$90*'Annexe B Plan commercial'!$D30*Hypothèses!$D$58 -> 0 | AA33: =Z$33*(1-'Annexe G Evolution Portefeuill'!$E21)+Z$90*'Annexe B Plan commercial'!$D30*Hypothèses!$D$58 -> 0 | AB33: =AA$33*(1-'Annexe G Evolution Portefeuill'!$E21)+AA$90*'Annexe B Plan commercial'!$D30*Hypothèses!$D$58 -> 0 | AC33: =AB$33*(1-'Annexe G Evolution Portefeuill'!$E21)+AB$90*'Annexe B Plan commercial'!$D30*Hypothèses!$D$58 -> 0 | ... AG33: =AF$33*(1-'Annexe G Evolution Portefeuill'!$E21)+AF$90*'Annexe B Plan commercial'!$D30*Hypothèses!$D$58 -> 0 | AH33: =AG$33*(1-'Annexe G Evolution Portefeuill'!$F21)+AG$90*'Annexe B Plan commercial'!$E30*Hypothèses!$E$58 -> 0 | AI33: =AH$33*(1-'Annexe G Evolution Portefeuill'!$F21)+AH$90*'Annexe B Plan commercial'!$E30*Hypothèses!$E$58 -> 0 | AJ33: =AI$33*(1-'Annexe G Evolution Portefeuill'!$F21)+AI$90*'Annexe B Plan commercial'!$E30*Hypothèses!$E$58 -> 0 | AK33: =AJ$33*(1-'Annexe G Evolution Portefeuill'!$F21)+AJ$90*'Annexe B Plan commercial'!$E30*Hypothèses!$E$58 -> 0 | AL33: =AK$33*(1-'Annexe G Evolution Portefeuill'!$F21)+AK$90*'Annexe B Plan commercial'!$E30*Hypothèses!$E$58 -> 0 | AM33: =AL$33*(1-'Annexe G Evolution Portefeuill'!$F21)+AL$90*'Annexe B Plan commercial'!$E30*Hypothèses!$E$58 -> 0 | AN33: =AM$33*(1-'Annexe G Evolution Portefeuill'!$F21)+AM$90*'Annexe B Plan commercial'!$E30*Hypothèses!$E$58 -> 0 | AO33: =AN$33*(1-'Annexe G Evolution Portefeuill'!$F21)+AN$90*'Annexe B Plan commercial'!$E30*Hypothèses!$E$58 -> 0 | ... AS33: =AR$33*(1-'Annexe G Evolution Portefeuill'!$F21)+AR$90*'Annexe B Plan commercial'!$E30*Hypothèses!$E$58 -> 0 | AT33: =AS$33*(1-'Annexe G Evolution Portefeuill'!$G21)+AS$90*'Annexe B Plan commercial'!$F30*Hypothèses!$F$58 -> 0 | AU33: =AT$33*(1-'Annexe G Evolution Portefeuill'!$G21)+AT$90*'Annexe B Plan commercial'!$F30*Hypothèses!$F$58 -> 0 | AV33: =AU$33*(1-'Annexe G Evolution Portefeuill'!$G21)+AU$90*'Annexe B Plan commercial'!$F30*Hypothèses!$F$58 -> 0 | AW33: =AV$33*(1-'Annexe G Evolution Portefeuill'!$G21)+AV$90*'Annexe B Plan commercial'!$F30*Hypothèses!$F$58 -> 0 | AX33: =AW$33*(1-'Annexe G Evolution Portefeuill'!$G21)+AW$90*'Annexe B Plan commercial'!$F30*Hypothèses!$F$58 -> 0 | AY33: =AX$33*(1-'Annexe G Evolution Portefeuill'!$G21)+AX$90*'Annexe B Plan commercial'!$F30*Hypothèses!$F$58 -> 0 | AZ33: =AY$33*(1-'Annexe G Evolution Portefeuill'!$G21)+AY$90*'Annexe B Plan commercial'!$F30*Hypothèses!$F$58 -> 0 | BA33: =AZ$33*(1-'Annexe G Evolution Portefeuill'!$G21)+AZ$90*'Annexe B Plan commercial'!$F30*Hypothèses!$F$58 -> 0 | ... BE33: =BD$33*(1-'Annexe G Evolution Portefeuill'!$G21)+BD$90*'Annexe B Plan commercial'!$F30*Hypothèses!$F$58 -> 0 | BF33: =BE$33*(1-'Annexe G Evolution Portefeuill'!$H21)+BE$90*'Annexe B Plan commercial'!$G30*Hypothèses!$G$58 -> 0 | BG33: =BF$33*(1-'Annexe G Evolution Portefeuill'!$H21)+BF$90*'Annexe B Plan commercial'!$G30*Hypothèses!$G$58 -> 0 | BH33: =BG$33*(1-'Annexe G Evolution Portefeuill'!$H21)+BG$90*'Annexe B Plan commercial'!$G30*Hypothèses!$G$58 -> 0 | BI33: =BH$33*(1-'Annexe G Evolution Portefeuill'!$H21)+BH$90*'Annexe B Plan commercial'!$G30*Hypothèses!$G$58 -> 0 | BJ33: =BI$33*(1-'Annexe G Evolution Portefeuill'!$H21)+BI$90*'Annexe B Plan commercial'!$G30*Hypothèses!$G$58 -> 0 | BK33: =BJ$33*(1-'Annexe G Evolution Portefeuill'!$H21)+BJ$90*'Annexe B Plan commercial'!$G30*Hypothèses!$G$58 -> 0 | BL33: =BK$33*(1-'Annexe G Evolution Portefeuill'!$H21)+BK$90*'Annexe B Plan commercial'!$G30*Hypothèses!$G$58 -> 0 | BM33: =BL$33*(1-'Annexe G Evolution Portefeuill'!$H21)+BL$90*'Annexe B Plan commercial'!$G30*Hypothèses!$G$58 -> 0 | ... BQ33: =BP$33*(1-'Annexe G Evolution Portefeuill'!$H21)+BP$90*'Annexe B Plan commercial'!$G30*Hypothèses!$G$58 -> 0 | BR33: =BQ$33*(1-'Annexe G Evolution Portefeuill'!$I22)+BQ$90*'Annexe B Plan commercial'!$H30*Hypothèses!$H$58 -> 0 | BS33: =BR$33*(1-'Annexe G Evolution Portefeuill'!$I22)+BR$90*'Annexe B Plan commercial'!$H30*Hypothèses!$H$58 -> 0 | BT33: =BS$33*(1-'Annexe G Evolution Portefeuill'!$I22)+BS$90*'Annexe B Plan commercial'!$H30*Hypothèses!$H$58 -> 0 | BU33: =BT$33*(1-'Annexe G Evolution Portefeuill'!$I22)+BT$90*'Annexe B Plan commercial'!$H30*Hypothèses!$H$58 -> 0 | BV33: =BU$33*(1-'Annexe G Evolution Portefeuill'!$I22)+BU$90*'Annexe B Plan commercial'!$H30*Hypothèses!$H$58 -> 0 | BW33: =BV$33*(1-'Annexe G Evolution Portefeuill'!$I22)+BV$90*'Annexe B Plan commercial'!$H30*Hypothèses!$H$58 -> 0 | BX33: =BW$33*(1-'Annexe G Evolution Portefeuill'!$I22)+BW$90*'Annexe B Plan commercial'!$H30*Hypothèses!$H$58 -> 0 | BY33: =BX$33*(1-'Annexe G Evolution Portefeuill'!$I22)+BX$90*'Annexe B Plan commercial'!$H30*Hypothèses!$H$58 -> 0 | ... CC33: =CB$33*(1-'Annexe G Evolution Portefeuill'!$I22)+CB$90*'Annexe B Plan commercial'!$H30*Hypothèses!$H$58 -> 0
A35: Optiwize Pro - Essentiel | C35: =C36+C37+C38 -> 30.1 | D35: =D36+D37+D38 -> 30.372092 | E35: =E36+E37+E38 -> 30.6333 | F35: =F36+F37+F38 -> 30.88406 | G35: =G36+G37+G38 -> 31.12479 | H35: =H36+H37+H38 -> 31.35589 | I35: =I36+I37+I38 -> 31.577746 | J35: =J36+J37+J38 -> 31.631344 | ... CC35: =CC36+CC37+CC38 -> 116.34734
A36: dt FR | C36: =43*0.7 -> 30.1 | D36: =C36*(1-'Annexe G Evolution Portefeuill'!$C22)+C$86*'Annexe B Plan commercial'!$B7*Hypothèses!$B$54 -> 30.372092 | E36: =D36*(1-'Annexe G Evolution Portefeuill'!$C22)+D$86*'Annexe B Plan commercial'!$B7*Hypothèses!$B$54 -> 30.6333 | F36: =E36*(1-'Annexe G Evolution Portefeuill'!$C22)+E$86*'Annexe B Plan commercial'!$B7*Hypothèses!$B$54 -> 30.88406 | G36: =F36*(1-'Annexe G Evolution Portefeuill'!$C22)+F$86*'Annexe B Plan commercial'!$B7*Hypothèses!$B$54 -> 31.12479 | H36: =G36*(1-'Annexe G Evolution Portefeuill'!$C22)+G$86*'Annexe B Plan commercial'!$B7*Hypothèses!$B$54 -> 31.35589 | I36: =H36*(1-'Annexe G Evolution Portefeuill'!$C22)+H$86*'Annexe B Plan commercial'!$B7*Hypothèses!$B$54 -> 31.577746 | J36: =I36*(1-'Annexe G Evolution Portefeuill'!$D22)+I$86*'Annexe B Plan commercial'!$C7*Hypothèses!$C$54 -> 31.631344 | K36: =J36*(1-'Annexe G Evolution Portefeuill'!$D22)+J$86*'Annexe B Plan commercial'!$C7*Hypothèses!$C$54 -> 31.77661 | L36: =K36*(1-'Annexe G Evolution Portefeuill'!$D22)+K$86*'Annexe B Plan commercial'!$C7*Hypothèses!$C$54 -> 31.391647 | M36: =L36*(1-'Annexe G Evolution Portefeuill'!$D22)+L$86*'Annexe B Plan commercial'!$C7*Hypothèses!$C$54 -> 31.545542 | N36: =M36*(1-'Annexe G Evolution Portefeuill'!$D22)+M$86*'Annexe B Plan commercial'!$C7*Hypothèses!$C$54 -> 31.693897 | O36: =N36*(1-'Annexe G Evolution Portefeuill'!$D22)+N$86*'Annexe B Plan commercial'!$C7*Hypothèses!$C$54 -> 31.836911 | P36: =O36*(1-'Annexe G Evolution Portefeuill'!$D22)+O$86*'Annexe B Plan commercial'!$C7*Hypothèses!$C$54 -> 31.974777 | Q36: =P36*(1-'Annexe G Evolution Portefeuill'!$D22)+P$86*'Annexe B Plan commercial'!$C7*Hypothèses!$C$54 -> 32.341674 | ... U36: =T36*(1-'Annexe G Evolution Portefeuill'!$D22)+T$86*'Annexe B Plan commercial'!$C7*Hypothèses!$C$54 -> 33.68185 | V36: =U36*(1-'Annexe G Evolution Portefeuill'!$E22)+U$86*'Annexe B Plan commercial'!$D7*Hypothèses!$D$54 -> 33.751058 | W36: =V36*(1-'Annexe G Evolution Portefeuill'!$E22)+V$86*'Annexe B Plan commercial'!$D7*Hypothèses!$D$54 -> 33.817913 | X36: =W36*(1-'Annexe G Evolution Portefeuill'!$E22)+W$86*'Annexe B Plan commercial'!$D7*Hypothèses!$D$54 -> 33.882496 | Y36: =X36*(1-'Annexe G Evolution Portefeuill'!$E22)+X$86*'Annexe B Plan commercial'!$D7*Hypothèses!$D$54 -> 33.944882 | Z36: =Y36*(1-'Annexe G Evolution Portefeuill'!$E22)+Y$86*'Annexe B Plan commercial'!$D7*Hypothèses!$D$54 -> 34.005147 | AA36: =Z36*(1-'Annexe G Evolution Portefeuill'!$E22)+Z$86*'Annexe B Plan commercial'!$D7*Hypothèses!$D$54 -> 34.063364 | AB36: =AA36*(1-'Annexe G Evolution Portefeuill'!$E22)+AA$86*'Annexe B Plan commercial'!$D7*Hypothèses!$D$54 -> 34.119601 | AC36: =AB36*(1-'Annexe G Evolution Portefeuill'!$E22)+AB$86*'Annexe B Plan commercial'!$D7*Hypothèses!$D$54 -> 34.267523 | ... AG36: =AF36*(1-'Annexe G Evolution Portefeuill'!$E22)+AF$86*'Annexe B Plan commercial'!$D7*Hypothèses!$D$54 -> 34.810601 | AH36: =AG36*(1-'Annexe G Evolution Portefeuill'!$F22)+AG$86*'Annexe B Plan commercial'!$E7*Hypothèses!$E$54 -> 34.712464 | AI36: =AH36*(1-'Annexe G Evolution Portefeuill'!$F22)+AH$86*'Annexe B Plan commercial'!$E7*Hypothèses!$E$54 -> 34.61737 | AJ36: =AI36*(1-'Annexe G Evolution Portefeuill'!$F22)+AI$86*'Annexe B Plan commercial'!$E7*Hypothèses!$E$54 -> 34.525223 | AK36: =AJ36*(1-'Annexe G Evolution Portefeuill'!$F22)+AJ$86*'Annexe B Plan commercial'!$E7*Hypothèses!$E$54 -> 34.435933 | AL36: =AK36*(1-'Annexe G Evolution Portefeuill'!$F22)+AK$86*'Annexe B Plan commercial'!$E7*Hypothèses!$E$54 -> 34.349411 | AM36: =AL36*(1-'Annexe G Evolution Portefeuill'!$F22)+AL$86*'Annexe B Plan commercial'!$E7*Hypothèses!$E$54 -> 34.265571 | AN36: =AM36*(1-'Annexe G Evolution Portefeuill'!$F22)+AM$86*'Annexe B Plan commercial'!$E7*Hypothèses!$E$54 -> 34.18433 | AO36: =AN36*(1-'Annexe G Evolution Portefeuill'!$F22)+AN$86*'Annexe B Plan commercial'!$E7*Hypothèses!$E$54 -> 34.105608 | ... AS36: =AR36*(1-'Annexe G Evolution Portefeuill'!$F22)+AR$86*'Annexe B Plan commercial'!$E7*Hypothèses!$E$54 -> 33.814377 | AT36: =AS36*(1-'Annexe G Evolution Portefeuill'!$G22)+AS$86*'Annexe B Plan commercial'!$F7*Hypothèses!$F$54 -> 33.45394 | AU36: =AT36*(1-'Annexe G Evolution Portefeuill'!$G22)+AT$86*'Annexe B Plan commercial'!$F7*Hypothèses!$F$54 -> 33.104317 | AV36: =AU36*(1-'Annexe G Evolution Portefeuill'!$G22)+AU$86*'Annexe B Plan commercial'!$F7*Hypothèses!$F$54 -> 32.765182 | AW36: =AV36*(1-'Annexe G Evolution Portefeuill'!$G22)+AV$86*'Annexe B Plan commercial'!$F7*Hypothèses!$F$54 -> 32.436221 | AX36: =AW36*(1-'Annexe G Evolution Portefeuill'!$G22)+AW$86*'Annexe B Plan commercial'!$F7*Hypothèses!$F$54 -> 32.117129 | AY36: =AX36*(1-'Annexe G Evolution Portefeuill'!$G22)+AX$86*'Annexe B Plan commercial'!$F7*Hypothèses!$F$54 -> 31.807609 | AZ36: =AY36*(1-'Annexe G Evolution Portefeuill'!$G22)+AY$86*'Annexe B Plan commercial'!$F7*Hypothèses!$F$54 -> 31.507376 | BA36: =AZ36*(1-'Annexe G Evolution Portefeuill'!$G22)+AZ$86*'Annexe B Plan commercial'!$F7*Hypothèses!$F$54 -> 31.333146 | ... BE36: =BD36*(1-'Annexe G Evolution Portefeuill'!$G22)+BD$86*'Annexe B Plan commercial'!$F7*Hypothèses!$F$54 -> 30.686953 | BF36: =BE36*(1-'Annexe G Evolution Portefeuill'!$H22)+BE$86*'Annexe B Plan commercial'!$G7*Hypothèses!$G$54 -> 30.660084 | BG36: =BF36*(1-'Annexe G Evolution Portefeuill'!$H22)+BF$86*'Annexe B Plan commercial'!$G7*Hypothèses!$G$54 -> 30.633913 | BH36: =BG36*(1-'Annexe G Evolution Portefeuill'!$H22)+BG$86*'Annexe B Plan commercial'!$G7*Hypothèses!$G$54 -> 30.818423 | BI36: =BH36*(1-'Annexe G Evolution Portefeuill'!$H22)+BH$86*'Annexe B Plan commercial'!$G7*Hypothèses!$G$54 -> 30.998136 | BJ36: =BI36*(1-'Annexe G Evolution Portefeuill'!$H22)+BI$86*'Annexe B Plan commercial'!$G7*Hypothèses!$G$54 -> 31.593176 | BK36: =BJ36*(1-'Annexe G Evolution Portefeuill'!$H22)+BJ$86*'Annexe B Plan commercial'!$G7*Hypothèses!$G$54 -> 32.592746 | BL36: =BK36*(1-'Annexe G Evolution Portefeuill'!$H22)+BK$86*'Annexe B Plan commercial'!$G7*Hypothèses!$G$54 -> 33.566326 | BM36: =BL36*(1-'Annexe G Evolution Portefeuill'!$H22)+BL$86*'Annexe B Plan commercial'!$G7*Hypothèses!$G$54 -> 34.583602 | ... BQ36: =BP36*(1-'Annexe G Evolution Portefeuill'!$H22)+BP$86*'Annexe B Plan commercial'!$G7*Hypothèses!$G$54 -> 38.395 | BR36: =BQ36*(1-'Annexe G Evolution Portefeuill'!$I22)+BQ$86*'Annexe B Plan commercial'!$H7*Hypothèses!$H$54 -> 39.44031 | BS36: =BR36*(1-'Annexe G Evolution Portefeuill'!$I22)+BR$86*'Annexe B Plan commercial'!$H7*Hypothèses!$H$54 -> 40.462623 | BT36: =BS36*(1-'Annexe G Evolution Portefeuill'!$I22)+BS$86*'Annexe B Plan commercial'!$H7*Hypothèses!$H$54 -> 41.462445 | BU36: =BT36*(1-'Annexe G Evolution Portefeuill'!$I22)+BT$86*'Annexe B Plan commercial'!$H7*Hypothèses!$H$54 -> 42.440272 | BV36: =BU36*(1-'Annexe G Evolution Portefeuill'!$I22)+BU$86*'Annexe B Plan commercial'!$H7*Hypothèses!$H$54 -> 43.396586 | BW36: =BV36*(1-'Annexe G Evolution Portefeuill'!$I22)+BV$86*'Annexe B Plan commercial'!$H7*Hypothèses!$H$54 -> 44.331861 | BX36: =BW36*(1-'Annexe G Evolution Portefeuill'!$I22)+BW$86*'Annexe B Plan commercial'!$H7*Hypothèses!$H$54 -> 45.24656 | BY36: =BX36*(1-'Annexe G Evolution Portefeuill'!$I22)+BX$86*'Annexe B Plan commercial'!$H7*Hypothèses!$H$54 -> 48.013092 | ... CC36: =CB36*(1-'Annexe G Evolution Portefeuill'!$I22)+CB$86*'Annexe B Plan commercial'!$H7*Hypothèses!$H$54 -> 59.296511
A37: dt ES | C37: 0 | D37: =C37*(1-'Annexe G Evolution Portefeuill'!$C22)+C$87*'Annexe B Plan commercial'!$B13*Hypothèses!$B$55 -> 0 | E37: =D37*(1-'Annexe G Evolution Portefeuill'!$C22)+D$87*'Annexe B Plan commercial'!$B13*Hypothèses!$B$55 -> 0 | F37: =E37*(1-'Annexe G Evolution Portefeuill'!$C22)+E$87*'Annexe B Plan commercial'!$B13*Hypothèses!$B$55 -> 0 | G37: =F37*(1-'Annexe G Evolution Portefeuill'!$C22)+F$87*'Annexe B Plan commercial'!$B13*Hypothèses!$B$55 -> 0 | H37: =G37*(1-'Annexe G Evolution Portefeuill'!$C22)+G$87*'Annexe B Plan commercial'!$B13*Hypothèses!$B$55 -> 0 | I37: =H37*(1-'Annexe G Evolution Portefeuill'!$C22)+H$87*'Annexe B Plan commercial'!$B13*Hypothèses!$B$55 -> 0 | J37: =I37*(1-'Annexe G Evolution Portefeuill'!$D22)+I$87*'Annexe B Plan commercial'!$C13*Hypothèses!$C$55 -> 0 | K37: =J37*(1-'Annexe G Evolution Portefeuill'!$D22)+J$87*'Annexe B Plan commercial'!$C13*Hypothèses!$C$55 -> 0 | L37: =K37*(1-'Annexe G Evolution Portefeuill'!$D22)+K$87*'Annexe B Plan commercial'!$C13*Hypothèses!$C$55 -> 0 | M37: =L37*(1-'Annexe G Evolution Portefeuill'!$D22)+L$87*'Annexe B Plan commercial'!$C13*Hypothèses!$C$55 -> 0 | N37: =M37*(1-'Annexe G Evolution Portefeuill'!$D22)+M$87*'Annexe B Plan commercial'!$C13*Hypothèses!$C$55 -> 0 | O37: =N37*(1-'Annexe G Evolution Portefeuill'!$D22)+N$87*'Annexe B Plan commercial'!$C13*Hypothèses!$C$55 -> 0 | P37: =O37*(1-'Annexe G Evolution Portefeuill'!$D22)+O$87*'Annexe B Plan commercial'!$C13*Hypothèses!$C$55 -> 0 | Q37: =P37*(1-'Annexe G Evolution Portefeuill'!$D22)+P$87*'Annexe B Plan commercial'!$C13*Hypothèses!$C$55 -> 0 | ... U37: =T37*(1-'Annexe G Evolution Portefeuill'!$D22)+T$87*'Annexe B Plan commercial'!$C13*Hypothèses!$C$55 -> 0 | V37: =U37*(1-'Annexe G Evolution Portefeuill'!$E22)+U$87*'Annexe B Plan commercial'!$D13*Hypothèses!$D$55 -> 0 | W37: =V37*(1-'Annexe G Evolution Portefeuill'!$E22)+V$87*'Annexe B Plan commercial'!$D13*Hypothèses!$D$55 -> 0 | X37: =W37*(1-'Annexe G Evolution Portefeuill'!$E22)+W$87*'Annexe B Plan commercial'!$D13*Hypothèses!$D$55 -> 0 | Y37: =X37*(1-'Annexe G Evolution Portefeuill'!$E22)+X$87*'Annexe B Plan commercial'!$D13*Hypothèses!$D$55 -> 0 | Z37: =Y37*(1-'Annexe G Evolution Portefeuill'!$E22)+Y$87*'Annexe B Plan commercial'!$D13*Hypothèses!$D$55 -> 0 | AA37: =Z37*(1-'Annexe G Evolution Portefeuill'!$E22)+Z$87*'Annexe B Plan commercial'!$D13*Hypothèses!$D$55 -> 0 | AB37: =AA37*(1-'Annexe G Evolution Portefeuill'!$E22)+AA$87*'Annexe B Plan commercial'!$D13*Hypothèses!$D$55 -> 0 | AC37: =AB37*(1-'Annexe G Evolution Portefeuill'!$E22)+AB$87*'Annexe B Plan commercial'!$D13*Hypothèses!$D$55 -> 0 | ... AG37: =AF37*(1-'Annexe G Evolution Portefeuill'!$E22)+AF$87*'Annexe B Plan commercial'!$D13*Hypothèses!$D$55 -> 0 | AH37: =AG37*(1-'Annexe G Evolution Portefeuill'!$F22)+AG$87*'Annexe B Plan commercial'!$E13*Hypothèses!$E$55 -> 0 | AI37: =AH37*(1-'Annexe G Evolution Portefeuill'!$F22)+AH$87*'Annexe B Plan commercial'!$E13*Hypothèses!$E$55 -> 0 | AJ37: =AI37*(1-'Annexe G Evolution Portefeuill'!$F22)+AI$87*'Annexe B Plan commercial'!$E13*Hypothèses!$E$55 -> 0 | AK37: =AJ37*(1-'Annexe G Evolution Portefeuill'!$F22)+AJ$87*'Annexe B Plan commercial'!$E13*Hypothèses!$E$55 -> 0 | AL37: =AK37*(1-'Annexe G Evolution Portefeuill'!$F22)+AK$87*'Annexe B Plan commercial'!$E13*Hypothèses!$E$55 -> 0 | AM37: =AL37*(1-'Annexe G Evolution Portefeuill'!$F22)+AL$87*'Annexe B Plan commercial'!$E13*Hypothèses!$E$55 -> 0 | AN37: =AM37*(1-'Annexe G Evolution Portefeuill'!$F22)+AM$87*'Annexe B Plan commercial'!$E13*Hypothèses!$E$55 -> 0 | AO37: =AN37*(1-'Annexe G Evolution Portefeuill'!$F22)+AN$87*'Annexe B Plan commercial'!$E13*Hypothèses!$E$55 -> 0 | ... AS37: =AR37*(1-'Annexe G Evolution Portefeuill'!$F22)+AR$87*'Annexe B Plan commercial'!$E13*Hypothèses!$E$55 -> 0 | AT37: =AS37*(1-'Annexe G Evolution Portefeuill'!$G22)+AS$87*'Annexe B Plan commercial'!$F13*Hypothèses!$F$55 -> 0 | AU37: =AT37*(1-'Annexe G Evolution Portefeuill'!$G22)+AT$87*'Annexe B Plan commercial'!$F13*Hypothèses!$F$55 -> 0 | AV37: =AU37*(1-'Annexe G Evolution Portefeuill'!$G22)+AU$87*'Annexe B Plan commercial'!$F13*Hypothèses!$F$55 -> 0 | AW37: =AV37*(1-'Annexe G Evolution Portefeuill'!$G22)+AV$87*'Annexe B Plan commercial'!$F13*Hypothèses!$F$55 -> 0 | AX37: =AW37*(1-'Annexe G Evolution Portefeuill'!$G22)+AW$87*'Annexe B Plan commercial'!$F13*Hypothèses!$F$55 -> 0 | AY37: =AX37*(1-'Annexe G Evolution Portefeuill'!$G22)+AX$87*'Annexe B Plan commercial'!$F13*Hypothèses!$F$55 -> 0 | AZ37: =AY37*(1-'Annexe G Evolution Portefeuill'!$G22)+AY$87*'Annexe B Plan commercial'!$F13*Hypothèses!$F$55 -> 0 | BA37: =AZ37*(1-'Annexe G Evolution Portefeuill'!$G22)+AZ$87*'Annexe B Plan commercial'!$F13*Hypothèses!$F$55 -> 0 | ... BE37: =BD37*(1-'Annexe G Evolution Portefeuill'!$G22)+BD$87*'Annexe B Plan commercial'!$F13*Hypothèses!$F$55 -> 0 | BF37: =BE37*(1-'Annexe G Evolution Portefeuill'!$H22)+BE$87*'Annexe B Plan commercial'!$G13*Hypothèses!$G$55 -> 0 | BG37: =BF37*(1-'Annexe G Evolution Portefeuill'!$H22)+BF$87*'Annexe B Plan commercial'!$G13*Hypothèses!$G$55 -> 0 | BH37: =BG37*(1-'Annexe G Evolution Portefeuill'!$H22)+BG$87*'Annexe B Plan commercial'!$G13*Hypothèses!$G$55 -> 0.21 | BI37: =BH37*(1-'Annexe G Evolution Portefeuill'!$H22)+BH$87*'Annexe B Plan commercial'!$G13*Hypothèses!$G$55 -> 0.41454 | BJ37: =BI37*(1-'Annexe G Evolution Portefeuill'!$H22)+BI$87*'Annexe B Plan commercial'!$G13*Hypothèses!$G$55 -> 0.61376196 | BK37: =BJ37*(1-'Annexe G Evolution Portefeuill'!$H22)+BJ$87*'Annexe B Plan commercial'!$G13*Hypothèses!$G$55 -> 0.80780415 | BL37: =BK37*(1-'Annexe G Evolution Portefeuill'!$H22)+BK$87*'Annexe B Plan commercial'!$G13*Hypothèses!$G$55 -> 0.99680124 | BM37: =BL37*(1-'Annexe G Evolution Portefeuill'!$H22)+BL$87*'Annexe B Plan commercial'!$G13*Hypothèses!$G$55 -> 3.0361269 | ... BQ37: =BP37*(1-'Annexe G Evolution Portefeuill'!$H22)+BP$87*'Annexe B Plan commercial'!$G13*Hypothèses!$G$55 -> 10.676812 | BR37: =BQ37*(1-'Annexe G Evolution Portefeuill'!$I22)+BQ$87*'Annexe B Plan commercial'!$H13*Hypothèses!$H$55 -> 12.507165 | BS37: =BR37*(1-'Annexe G Evolution Portefeuill'!$I22)+BR$87*'Annexe B Plan commercial'!$H13*Hypothèses!$H$55 -> 14.50725 | BT37: =BS37*(1-'Annexe G Evolution Portefeuill'!$I22)+BS$87*'Annexe B Plan commercial'!$H13*Hypothèses!$H$55 -> 16.463333 | BU37: =BT37*(1-'Annexe G Evolution Portefeuill'!$I22)+BT$87*'Annexe B Plan commercial'!$H13*Hypothèses!$H$55 -> 18.376382 | BV37: =BU37*(1-'Annexe G Evolution Portefeuill'!$I22)+BU$87*'Annexe B Plan commercial'!$H13*Hypothèses!$H$55 -> 20.247344 | BW37: =BV37*(1-'Annexe G Evolution Portefeuill'!$I22)+BV$87*'Annexe B Plan commercial'!$H13*Hypothèses!$H$55 -> 22.077145 | BX37: =BW37*(1-'Annexe G Evolution Portefeuill'!$I22)+BW$87*'Annexe B Plan commercial'!$H13*Hypothèses!$H$55 -> 24.28669 | BY37: =BX37*(1-'Annexe G Evolution Portefeuill'!$I22)+BX$87*'Annexe B Plan commercial'!$H13*Hypothèses!$H$55 -> 27.266606 | ... CC37: =CB37*(1-'Annexe G Evolution Portefeuill'!$I22)+CB$87*'Annexe B Plan commercial'!$H13*Hypothèses!$H$55 -> 39.375714
A38: dt CH | C38: 0 | D38: =C$38*(1-'Annexe G Evolution Portefeuill'!$C$22)+C$88*'Annexe B Plan commercial'!$B$19*Hypothèses!$B$56 -> 0 | E38: =D$38*(1-'Annexe G Evolution Portefeuill'!$C$22)+D$88*'Annexe B Plan commercial'!$B$19*Hypothèses!$B$56 -> 0 | F38: =E$38*(1-'Annexe G Evolution Portefeuill'!$C$22)+E$88*'Annexe B Plan commercial'!$B$19*Hypothèses!$B$56 -> 0 | G38: =F$38*(1-'Annexe G Evolution Portefeuill'!$C$22)+F$88*'Annexe B Plan commercial'!$B$19*Hypothèses!$B$56 -> 0 | H38: =G$38*(1-'Annexe G Evolution Portefeuill'!$C$22)+G$88*'Annexe B Plan commercial'!$B$19*Hypothèses!$B$56 -> 0 | I38: =H$38*(1-'Annexe G Evolution Portefeuill'!$C$22)+H$88*'Annexe B Plan commercial'!$B$19*Hypothèses!$B$56 -> 0 | J38: =I$38*(1-'Annexe G Evolution Portefeuill'!$D$22)+I$88*'Annexe B Plan commercial'!$C$19*Hypothèses!$C$56 -> 0 | K38: =J$38*(1-'Annexe G Evolution Portefeuill'!$D$22)+J$88*'Annexe B Plan commercial'!$C$19*Hypothèses!$C$56 -> 0 | L38: =K$38*(1-'Annexe G Evolution Portefeuill'!$D$22)+K$88*'Annexe B Plan commercial'!$C$19*Hypothèses!$C$56 -> 0 | M38: =L$38*(1-'Annexe G Evolution Portefeuill'!$D$22)+L$88*'Annexe B Plan commercial'!$C$19*Hypothèses!$C$56 -> 0 | N38: =M$38*(1-'Annexe G Evolution Portefeuill'!$D$22)+M$88*'Annexe B Plan commercial'!$C$19*Hypothèses!$C$56 -> 0 | O38: =N$38*(1-'Annexe G Evolution Portefeuill'!$D$22)+N$88*'Annexe B Plan commercial'!$C$19*Hypothèses!$C$56 -> 0 | P38: =O$38*(1-'Annexe G Evolution Portefeuill'!$D$22)+O$88*'Annexe B Plan commercial'!$C$19*Hypothèses!$C$56 -> 0 | Q38: =P$38*(1-'Annexe G Evolution Portefeuill'!$D$22)+P$88*'Annexe B Plan commercial'!$C$19*Hypothèses!$C$56 -> 0 | ... U38: =T$38*(1-'Annexe G Evolution Portefeuill'!$D$22)+T$88*'Annexe B Plan commercial'!$C$19*Hypothèses!$C$56 -> 0 | V38: =U$38*(1-'Annexe G Evolution Portefeuill'!$E$22)+U$88*'Annexe B Plan commercial'!$D$19*Hypothèses!$D$56 -> 0 | W38: =V$38*(1-'Annexe G Evolution Portefeuill'!$E$22)+V$88*'Annexe B Plan commercial'!$D$19*Hypothèses!$D$56 -> 0 | X38: =W$38*(1-'Annexe G Evolution Portefeuill'!$E$22)+W$88*'Annexe B Plan commercial'!$D$19*Hypothèses!$D$56 -> 0 | Y38: =X$38*(1-'Annexe G Evolution Portefeuill'!$E$22)+X$88*'Annexe B Plan commercial'!$D$19*Hypothèses!$D$56 -> 0 | Z38: =Y$38*(1-'Annexe G Evolution Portefeuill'!$E$22)+Y$88*'Annexe B Plan commercial'!$D$19*Hypothèses!$D$56 -> 0 | AA38: =Z$38*(1-'Annexe G Evolution Portefeuill'!$E$22)+Z$88*'Annexe B Plan commercial'!$D$19*Hypothèses!$D$56 -> 0 | AB38: =AA$38*(1-'Annexe G Evolution Portefeuill'!$E$22)+AA$88*'Annexe B Plan commercial'!$D$19*Hypothèses!$D$56 -> 0 | AC38: =AB$38*(1-'Annexe G Evolution Portefeuill'!$E$22)+AB$88*'Annexe B Plan commercial'!$D$19*Hypothèses!$D$56 -> 0 | ... AG38: =AF$38*(1-'Annexe G Evolution Portefeuill'!$E$22)+AF$88*'Annexe B Plan commercial'!$D$19*Hypothèses!$D$56 -> 0 | AH38: =AG$38*(1-'Annexe G Evolution Portefeuill'!$F$22)+AG$88*'Annexe B Plan commercial'!$E$19*Hypothèses!$E$56 -> 0 | AI38: =AH$38*(1-'Annexe G Evolution Portefeuill'!$F$22)+AH$88*'Annexe B Plan commercial'!$E$19*Hypothèses!$E$56 -> 0 | AJ38: =AI$38*(1-'Annexe G Evolution Portefeuill'!$F$22)+AI$88*'Annexe B Plan commercial'!$E$19*Hypothèses!$E$56 -> 0 | AK38: =AJ$38*(1-'Annexe G Evolution Portefeuill'!$F$22)+AJ$88*'Annexe B Plan commercial'!$E$19*Hypothèses!$E$56 -> 0 | AL38: =AK$38*(1-'Annexe G Evolution Portefeuill'!$F$22)+AK$88*'Annexe B Plan commercial'!$E$19*Hypothèses!$E$56 -> 0 | AM38: =AL$38*(1-'Annexe G Evolution Portefeuill'!$F$22)+AL$88*'Annexe B Plan commercial'!$E$19*Hypothèses!$E$56 -> 0 | AN38: =AM$38*(1-'Annexe G Evolution Portefeuill'!$F$22)+AM$88*'Annexe B Plan commercial'!$E$19*Hypothèses!$E$56 -> 0 | AO38: =AN$38*(1-'Annexe G Evolution Portefeuill'!$F$22)+AN$88*'Annexe B Plan commercial'!$E$19*Hypothèses!$E$56 -> 0 | ... AS38: =AR$38*(1-'Annexe G Evolution Portefeuill'!$F$22)+AR$88*'Annexe B Plan commercial'!$E$19*Hypothèses!$E$56 -> 0 | AT38: =AS$38*(1-'Annexe G Evolution Portefeuill'!$G$22)+AS$88*'Annexe B Plan commercial'!$F$19*Hypothèses!$F56 -> 0 | AU38: =AT$38*(1-'Annexe G Evolution Portefeuill'!$G$22)+AT$88*'Annexe B Plan commercial'!$F$19*Hypothèses!$F56 -> 0 | AV38: =AU$38*(1-'Annexe G Evolution Portefeuill'!$G$22)+AU$88*'Annexe B Plan commercial'!$F$19*Hypothèses!$F56 -> 0 | AW38: =AV$38*(1-'Annexe G Evolution Portefeuill'!$G$22)+AV$88*'Annexe B Plan commercial'!$F$19*Hypothèses!$F56 -> 0 | AX38: =AW$38*(1-'Annexe G Evolution Portefeuill'!$G$22)+AW$88*'Annexe B Plan commercial'!$F$19*Hypothèses!$F56 -> 0 | AY38: =AX$38*(1-'Annexe G Evolution Portefeuill'!$G$22)+AX$88*'Annexe B Plan commercial'!$F$19*Hypothèses!$F56 -> 0 | AZ38: =AY$38*(1-'Annexe G Evolution Portefeuill'!$G$22)+AY$88*'Annexe B Plan commercial'!$F$19*Hypothèses!$F56 -> 0 | BA38: =AZ$38*(1-'Annexe G Evolution Portefeuill'!$G$22)+AZ$88*'Annexe B Plan commercial'!$F$19*Hypothèses!$F56 -> 0 | ... BE38: =BD$38*(1-'Annexe G Evolution Portefeuill'!$G$22)+BD$88*'Annexe B Plan commercial'!$F$19*Hypothèses!$F56 -> 0 | BF38: =BE$38*(1-'Annexe G Evolution Portefeuill'!$H$22)+BE$88*'Annexe B Plan commercial'!$G$19*Hypothèses!$G$56 -> 0 | BG38: =BF$38*(1-'Annexe G Evolution Portefeuill'!$H$22)+BF$88*'Annexe B Plan commercial'!$G$19*Hypothèses!$G$56 -> 0 | BH38: =BG$38*(1-'Annexe G Evolution Portefeuill'!$H$22)+BG$88*'Annexe B Plan commercial'!$G$19*Hypothèses!$G$56 -> 0 | BI38: =BH$38*(1-'Annexe G Evolution Portefeuill'!$H$22)+BH$88*'Annexe B Plan commercial'!$G$19*Hypothèses!$G$56 -> 0 | BJ38: =BI$38*(1-'Annexe G Evolution Portefeuill'!$H$22)+BI$88*'Annexe B Plan commercial'!$G$19*Hypothèses!$G$56 -> 0 | BK38: =BJ$38*(1-'Annexe G Evolution Portefeuill'!$H$22)+BJ$88*'Annexe B Plan commercial'!$G$19*Hypothèses!$G$56 -> 0 | BL38: =BK$38*(1-'Annexe G Evolution Portefeuill'!$H$22)+BK$88*'Annexe B Plan commercial'!$G$19*Hypothèses!$G$56 -> 0 | BM38: =BL$38*(1-'Annexe G Evolution Portefeuill'!$H$22)+BL$88*'Annexe B Plan commercial'!$G$19*Hypothèses!$G$56 -> 0 | ... BQ38: =BP$38*(1-'Annexe G Evolution Portefeuill'!$H$22)+BP$88*'Annexe B Plan commercial'!$G$19*Hypothèses!$G$56 -> 0 | BR38: =BQ$38*(1-'Annexe G Evolution Portefeuill'!$I$22)+BQ$88*'Annexe B Plan commercial'!$H$19*Hypothèses!$H$56 -> 0 | BS38: =BR$38*(1-'Annexe G Evolution Portefeuill'!$I$22)+BR$88*'Annexe B Plan commercial'!$H$19*Hypothèses!$H$56 -> 0 | BT38: =BS$38*(1-'Annexe G Evolution Portefeuill'!$I$22)+BS$88*'Annexe B Plan commercial'!$H$19*Hypothèses!$H$56 -> 0 | BU38: =BT$38*(1-'Annexe G Evolution Portefeuill'!$I$22)+BT$88*'Annexe B Plan commercial'!$H$19*Hypothèses!$H$56 -> 0.21 | BV38: =BU$38*(1-'Annexe G Evolution Portefeuill'!$I$22)+BU$88*'Annexe B Plan commercial'!$H$19*Hypothèses!$H$56 -> 0.41538 | BW38: =BV$38*(1-'Annexe G Evolution Portefeuill'!$I$22)+BV$88*'Annexe B Plan commercial'!$H$19*Hypothèses!$H$56 -> 0.61624164 | BX38: =BW$38*(1-'Annexe G Evolution Portefeuill'!$I$22)+BW$88*'Annexe B Plan commercial'!$H$19*Hypothèses!$H$56 -> 1.0226843 | BY38: =BX$38*(1-'Annexe G Evolution Portefeuill'!$I$22)+BX$88*'Annexe B Plan commercial'!$H$19*Hypothèses!$H$56 -> 4.5029705 | ... CC38: =CB$38*(1-'Annexe G Evolution Portefeuill'!$I$22)+CB$88*'Annexe B Plan commercial'!$H$19*Hypothèses!$H$56 -> 17.675112
A39: dt BE | C39: 0 | D39: =C$39*(1-'Annexe G Evolution Portefeuill'!$C$22)+C$89*'Annexe B Plan commercial'!$B$25*Hypothèses!$B$57 -> 0 | E39: =D$39*(1-'Annexe G Evolution Portefeuill'!$C$22)+D$89*'Annexe B Plan commercial'!$B$25*Hypothèses!$B$57 -> 0 | F39: =E$39*(1-'Annexe G Evolution Portefeuill'!$C$22)+E$89*'Annexe B Plan commercial'!$B$25*Hypothèses!$B$57 -> 0 | G39: =F$39*(1-'Annexe G Evolution Portefeuill'!$C$22)+F$89*'Annexe B Plan commercial'!$B$25*Hypothèses!$B$57 -> 0 | H39: =G$39*(1-'Annexe G Evolution Portefeuill'!$C$22)+G$89*'Annexe B Plan commercial'!$B$25*Hypothèses!$B$57 -> 0 | I39: =H$39*(1-'Annexe G Evolution Portefeuill'!$C$22)+H$89*'Annexe B Plan commercial'!$B$25*Hypothèses!$B$57 -> 0 | J39: =I$39*(1-'Annexe G Evolution Portefeuill'!$D$22)+I$89*'Annexe B Plan commercial'!$C$25*Hypothèses!$C$57 -> 0 | K39: =J$39*(1-'Annexe G Evolution Portefeuill'!$D$22)+J$89*'Annexe B Plan commercial'!$C$25*Hypothèses!$C$57 -> 0 | L39: =K$39*(1-'Annexe G Evolution Portefeuill'!$D$22)+K$89*'Annexe B Plan commercial'!$C$25*Hypothèses!$C$57 -> 0 | M39: =L$39*(1-'Annexe G Evolution Portefeuill'!$D$22)+L$89*'Annexe B Plan commercial'!$C$25*Hypothèses!$C$57 -> 0 | N39: =M$39*(1-'Annexe G Evolution Portefeuill'!$D$22)+M$89*'Annexe B Plan commercial'!$C$25*Hypothèses!$C$57 -> 0 | O39: =N$39*(1-'Annexe G Evolution Portefeuill'!$D$22)+N$89*'Annexe B Plan commercial'!$C$25*Hypothèses!$C$57 -> 0 | P39: =O$39*(1-'Annexe G Evolution Portefeuill'!$D$22)+O$89*'Annexe B Plan commercial'!$C$25*Hypothèses!$C$57 -> 0 | Q39: =P$39*(1-'Annexe G Evolution Portefeuill'!$D$22)+P$89*'Annexe B Plan commercial'!$C$25*Hypothèses!$C$57 -> 0 | ... U39: =T$39*(1-'Annexe G Evolution Portefeuill'!$D$22)+T$89*'Annexe B Plan commercial'!$C$25*Hypothèses!$C$57 -> 0 | V39: =U$39*(1-'Annexe G Evolution Portefeuill'!$E$22)+U$89*'Annexe B Plan commercial'!$D$25*Hypothèses!$D$57 -> 0 | W39: =V$39*(1-'Annexe G Evolution Portefeuill'!$E$22)+V$89*'Annexe B Plan commercial'!$D$25*Hypothèses!$D$57 -> 0 | X39: =W$39*(1-'Annexe G Evolution Portefeuill'!$E$22)+W$89*'Annexe B Plan commercial'!$D$25*Hypothèses!$D$57 -> 0 | Y39: =X$39*(1-'Annexe G Evolution Portefeuill'!$E$22)+X$89*'Annexe B Plan commercial'!$D$25*Hypothèses!$D$57 -> 0 | Z39: =Y$39*(1-'Annexe G Evolution Portefeuill'!$E$22)+Y$89*'Annexe B Plan commercial'!$D$25*Hypothèses!$D$57 -> 0 | AA39: =Z$39*(1-'Annexe G Evolution Portefeuill'!$E$22)+Z$89*'Annexe B Plan commercial'!$D$25*Hypothèses!$D$57 -> 0 | AB39: =AA$39*(1-'Annexe G Evolution Portefeuill'!$E$22)+AA$89*'Annexe B Plan commercial'!$D$25*Hypothèses!$D$57 -> 0 | AC39: =AB$39*(1-'Annexe G Evolution Portefeuill'!$E$22)+AB$89*'Annexe B Plan commercial'!$D$25*Hypothèses!$D$57 -> 0 | ... AG39: =AF$39*(1-'Annexe G Evolution Portefeuill'!$E$22)+AF$89*'Annexe B Plan commercial'!$D$25*Hypothèses!$D$57 -> 0 | AH39: =AG$39*(1-'Annexe G Evolution Portefeuill'!$F$22)+AG$89*'Annexe B Plan commercial'!$E$25*Hypothèses!$E$57 -> 0 | AI39: =AH$39*(1-'Annexe G Evolution Portefeuill'!$F$22)+AH$89*'Annexe B Plan commercial'!$E$25*Hypothèses!$E$57 -> 0 | AJ39: =AI$39*(1-'Annexe G Evolution Portefeuill'!$F$22)+AI$89*'Annexe B Plan commercial'!$E$25*Hypothèses!$E$57 -> 0 | AK39: =AJ$39*(1-'Annexe G Evolution Portefeuill'!$F$22)+AJ$89*'Annexe B Plan commercial'!$E$25*Hypothèses!$E$57 -> 0 | AL39: =AK$39*(1-'Annexe G Evolution Portefeuill'!$F$22)+AK$89*'Annexe B Plan commercial'!$E$25*Hypothèses!$E$57 -> 0 | AM39: =AL$39*(1-'Annexe G Evolution Portefeuill'!$F$22)+AL$89*'Annexe B Plan commercial'!$E$25*Hypothèses!$E$57 -> 0 | AN39: =AM$39*(1-'Annexe G Evolution Portefeuill'!$F$22)+AM$89*'Annexe B Plan commercial'!$E$25*Hypothèses!$E$57 -> 0 | AO39: =AN$39*(1-'Annexe G Evolution Portefeuill'!$F$22)+AN$89*'Annexe B Plan commercial'!$E$25*Hypothèses!$E$57 -> 0 | ... AS39: =AR$39*(1-'Annexe G Evolution Portefeuill'!$F$22)+AR$89*'Annexe B Plan commercial'!$E$25*Hypothèses!$E$57 -> 0 | AT39: =AS$39*(1-'Annexe G Evolution Portefeuill'!$G$22)+AS$89*'Annexe B Plan commercial'!$F$25*Hypothèses!$F57 -> 0 | AU39: =AT$39*(1-'Annexe G Evolution Portefeuill'!$G$22)+AT$89*'Annexe B Plan commercial'!$F$25*Hypothèses!$F57 -> 0 | AV39: =AU$39*(1-'Annexe G Evolution Portefeuill'!$G$22)+AU$89*'Annexe B Plan commercial'!$F$25*Hypothèses!$F57 -> 0 | AW39: =AV$39*(1-'Annexe G Evolution Portefeuill'!$G$22)+AV$89*'Annexe B Plan commercial'!$F$25*Hypothèses!$F57 -> 0 | AX39: =AW$39*(1-'Annexe G Evolution Portefeuill'!$G$22)+AW$89*'Annexe B Plan commercial'!$F$25*Hypothèses!$F57 -> 0 | AY39: =AX$39*(1-'Annexe G Evolution Portefeuill'!$G$22)+AX$89*'Annexe B Plan commercial'!$F$25*Hypothèses!$F57 -> 0 | AZ39: =AY$39*(1-'Annexe G Evolution Portefeuill'!$G$22)+AY$89*'Annexe B Plan commercial'!$F$25*Hypothèses!$F57 -> 0 | BA39: =AZ$39*(1-'Annexe G Evolution Portefeuill'!$G$22)+AZ$89*'Annexe B Plan commercial'!$F$25*Hypothèses!$F57 -> 0 | ... BE39: =BD$39*(1-'Annexe G Evolution Portefeuill'!$G$22)+BD$89*'Annexe B Plan commercial'!$F$25*Hypothèses!$F57 -> 0 | BF39: =BE$39*(1-'Annexe G Evolution Portefeuill'!$H$22)+BE$89*'Annexe B Plan commercial'!$G$25*Hypothèses!$G$57 -> 0 | BG39: =BF$39*(1-'Annexe G Evolution Portefeuill'!$H$22)+BF$89*'Annexe B Plan commercial'!$G$25*Hypothèses!$G$57 -> 0 | BH39: =BG$39*(1-'Annexe G Evolution Portefeuill'!$H$22)+BG$89*'Annexe B Plan commercial'!$G$25*Hypothèses!$G$57 -> 0 | BI39: =BH$39*(1-'Annexe G Evolution Portefeuill'!$H$22)+BH$89*'Annexe B Plan commercial'!$G$25*Hypothèses!$G$57 -> 0 | BJ39: =BI$39*(1-'Annexe G Evolution Portefeuill'!$H$22)+BI$89*'Annexe B Plan commercial'!$G$25*Hypothèses!$G$57 -> 0 | BK39: =BJ$39*(1-'Annexe G Evolution Portefeuill'!$H$22)+BJ$89*'Annexe B Plan commercial'!$G$25*Hypothèses!$G$57 -> 0 | BL39: =BK$39*(1-'Annexe G Evolution Portefeuill'!$H$22)+BK$89*'Annexe B Plan commercial'!$G$25*Hypothèses!$G$57 -> 0 | BM39: =BL$39*(1-'Annexe G Evolution Portefeuill'!$H$22)+BL$89*'Annexe B Plan commercial'!$G$25*Hypothèses!$G$57 -> 0 | ... BQ39: =BP$39*(1-'Annexe G Evolution Portefeuill'!$H$22)+BP$89*'Annexe B Plan commercial'!$G$25*Hypothèses!$G$57 -> 0 | BR39: =BQ$39*(1-'Annexe G Evolution Portefeuill'!$I$22)+BQ$89*'Annexe B Plan commercial'!$H$25*Hypothèses!$H$57 -> 0 | BS39: =BR$39*(1-'Annexe G Evolution Portefeuill'!$I$22)+BR$89*'Annexe B Plan commercial'!$H$25*Hypothèses!$H$57 -> 0 | BT39: =BS$39*(1-'Annexe G Evolution Portefeuill'!$I$22)+BS$89*'Annexe B Plan commercial'!$H$25*Hypothèses!$H$57 -> 0 | BU39: =BT$39*(1-'Annexe G Evolution Portefeuill'!$I$22)+BT$89*'Annexe B Plan commercial'!$H$25*Hypothèses!$H$57 -> 0 | BV39: =BU$39*(1-'Annexe G Evolution Portefeuill'!$I$22)+BU$89*'Annexe B Plan commercial'!$H$25*Hypothèses!$H$57 -> 0 | BW39: =BV$39*(1-'Annexe G Evolution Portefeuill'!$I$22)+BV$89*'Annexe B Plan commercial'!$H$25*Hypothèses!$H$57 -> 0 | BX39: =BW$39*(1-'Annexe G Evolution Portefeuill'!$I$22)+BW$89*'Annexe B Plan commercial'!$H$25*Hypothèses!$H$57 -> 0 | BY39: =BX$39*(1-'Annexe G Evolution Portefeuill'!$I$22)+BX$89*'Annexe B Plan commercial'!$H$25*Hypothèses!$H$57 -> 0 | ... CC39: =CB$39*(1-'Annexe G Evolution Portefeuill'!$I$22)+CB$89*'Annexe B Plan commercial'!$H$25*Hypothèses!$H$57 -> 0
A40: dt DE | C40: 0 | D40: =C$40*(1-'Annexe G Evolution Portefeuill'!$C$22)+C$90*'Annexe B Plan commercial'!$B$31*Hypothèses!$B$58 -> 0 | E40: =D$40*(1-'Annexe G Evolution Portefeuill'!$C$22)+D$90*'Annexe B Plan commercial'!$B$31*Hypothèses!$B$58 -> 0 | F40: =E$40*(1-'Annexe G Evolution Portefeuill'!$C$22)+E$90*'Annexe B Plan commercial'!$B$31*Hypothèses!$B$58 -> 0 | G40: =F$40*(1-'Annexe G Evolution Portefeuill'!$C$22)+F$90*'Annexe B Plan commercial'!$B$31*Hypothèses!$B$58 -> 0 | H40: =G$40*(1-'Annexe G Evolution Portefeuill'!$C$22)+G$90*'Annexe B Plan commercial'!$B$31*Hypothèses!$B$58 -> 0 | I40: =H$40*(1-'Annexe G Evolution Portefeuill'!$C$22)+H$90*'Annexe B Plan commercial'!$B$31*Hypothèses!$B$58 -> 0 | J40: =I$40*(1-'Annexe G Evolution Portefeuill'!$D$22)+I$90*'Annexe B Plan commercial'!$C$31*Hypothèses!$C$58 -> 0 | K40: =J$40*(1-'Annexe G Evolution Portefeuill'!$D$22)+J$90*'Annexe B Plan commercial'!$C$31*Hypothèses!$C$58 -> 0 | L40: =K$40*(1-'Annexe G Evolution Portefeuill'!$D$22)+K$90*'Annexe B Plan commercial'!$C$31*Hypothèses!$C$58 -> 0 | M40: =L$40*(1-'Annexe G Evolution Portefeuill'!$D$22)+L$90*'Annexe B Plan commercial'!$C$31*Hypothèses!$C$58 -> 0 | N40: =M$40*(1-'Annexe G Evolution Portefeuill'!$D$22)+M$90*'Annexe B Plan commercial'!$C$31*Hypothèses!$C$58 -> 0 | O40: =N$40*(1-'Annexe G Evolution Portefeuill'!$D$22)+N$90*'Annexe B Plan commercial'!$C$31*Hypothèses!$C$58 -> 0 | P40: =O$40*(1-'Annexe G Evolution Portefeuill'!$D$22)+O$90*'Annexe B Plan commercial'!$C$31*Hypothèses!$C$58 -> 0 | Q40: =P$40*(1-'Annexe G Evolution Portefeuill'!$D$22)+P$90*'Annexe B Plan commercial'!$C$31*Hypothèses!$C$58 -> 0 | ... U40: =T$40*(1-'Annexe G Evolution Portefeuill'!$D$22)+T$90*'Annexe B Plan commercial'!$C$31*Hypothèses!$C$58 -> 0 | V40: =U$40*(1-'Annexe G Evolution Portefeuill'!$E$22)+U$90*'Annexe B Plan commercial'!$D$31*Hypothèses!$D$58 -> 0 | W40: =V$40*(1-'Annexe G Evolution Portefeuill'!$E$22)+V$90*'Annexe B Plan commercial'!$D$31*Hypothèses!$D$58 -> 0 | X40: =W$40*(1-'Annexe G Evolution Portefeuill'!$E$22)+W$90*'Annexe B Plan commercial'!$D$31*Hypothèses!$D$58 -> 0 | Y40: =X$40*(1-'Annexe G Evolution Portefeuill'!$E$22)+X$90*'Annexe B Plan commercial'!$D$31*Hypothèses!$D$58 -> 0 | Z40: =Y$40*(1-'Annexe G Evolution Portefeuill'!$E$22)+Y$90*'Annexe B Plan commercial'!$D$31*Hypothèses!$D$58 -> 0 | AA40: =Z$40*(1-'Annexe G Evolution Portefeuill'!$E$22)+Z$90*'Annexe B Plan commercial'!$D$31*Hypothèses!$D$58 -> 0 | AB40: =AA$40*(1-'Annexe G Evolution Portefeuill'!$E$22)+AA$90*'Annexe B Plan commercial'!$D$31*Hypothèses!$D$58 -> 0 | AC40: =AB$40*(1-'Annexe G Evolution Portefeuill'!$E$22)+AB$90*'Annexe B Plan commercial'!$D$31*Hypothèses!$D$58 -> 0 | ... AG40: =AF$40*(1-'Annexe G Evolution Portefeuill'!$E$22)+AF$90*'Annexe B Plan commercial'!$D$31*Hypothèses!$D$58 -> 0 | AH40: =AG$40*(1-'Annexe G Evolution Portefeuill'!$F$22)+AG$90*'Annexe B Plan commercial'!$E$31*Hypothèses!$E$58 -> 0 | AI40: =AH$40*(1-'Annexe G Evolution Portefeuill'!$F$22)+AH$90*'Annexe B Plan commercial'!$E$31*Hypothèses!$E$58 -> 0 | AJ40: =AI$40*(1-'Annexe G Evolution Portefeuill'!$F$22)+AI$90*'Annexe B Plan commercial'!$E$31*Hypothèses!$E$58 -> 0 | AK40: =AJ$40*(1-'Annexe G Evolution Portefeuill'!$F$22)+AJ$90*'Annexe B Plan commercial'!$E$31*Hypothèses!$E$58 -> 0 | AL40: =AK$40*(1-'Annexe G Evolution Portefeuill'!$F$22)+AK$90*'Annexe B Plan commercial'!$E$31*Hypothèses!$E$58 -> 0 | AM40: =AL$40*(1-'Annexe G Evolution Portefeuill'!$F$22)+AL$90*'Annexe B Plan commercial'!$E$31*Hypothèses!$E$58 -> 0 | AN40: =AM$40*(1-'Annexe G Evolution Portefeuill'!$F$22)+AM$90*'Annexe B Plan commercial'!$E$31*Hypothèses!$E$58 -> 0 | AO40: =AN$40*(1-'Annexe G Evolution Portefeuill'!$F$22)+AN$90*'Annexe B Plan commercial'!$E$31*Hypothèses!$E$58 -> 0 | ... AS40: =AR$40*(1-'Annexe G Evolution Portefeuill'!$F$22)+AR$90*'Annexe B Plan commercial'!$E$31*Hypothèses!$E$58 -> 0 | AT40: =AS$40*(1-'Annexe G Evolution Portefeuill'!$G$22)+AS$90*'Annexe B Plan commercial'!$F$31*Hypothèses!$F58 -> 0 | AU40: =AT$40*(1-'Annexe G Evolution Portefeuill'!$G$22)+AT$90*'Annexe B Plan commercial'!$F$31*Hypothèses!$F58 -> 0 | AV40: =AU$40*(1-'Annexe G Evolution Portefeuill'!$G$22)+AU$90*'Annexe B Plan commercial'!$F$31*Hypothèses!$F58 -> 0 | AW40: =AV$40*(1-'Annexe G Evolution Portefeuill'!$G$22)+AV$90*'Annexe B Plan commercial'!$F$31*Hypothèses!$F58 -> 0 | AX40: =AW$40*(1-'Annexe G Evolution Portefeuill'!$G$22)+AW$90*'Annexe B Plan commercial'!$F$31*Hypothèses!$F58 -> 0 | AY40: =AX$40*(1-'Annexe G Evolution Portefeuill'!$G$22)+AX$90*'Annexe B Plan commercial'!$F$31*Hypothèses!$F58 -> 0 | AZ40: =AY$40*(1-'Annexe G Evolution Portefeuill'!$G$22)+AY$90*'Annexe B Plan commercial'!$F$31*Hypothèses!$F58 -> 0 | BA40: =AZ$40*(1-'Annexe G Evolution Portefeuill'!$G$22)+AZ$90*'Annexe B Plan commercial'!$F$31*Hypothèses!$F58 -> 0 | ... BE40: =BD$40*(1-'Annexe G Evolution Portefeuill'!$G$22)+BD$90*'Annexe B Plan commercial'!$F$31*Hypothèses!$F58 -> 0 | BF40: =BE$40*(1-'Annexe G Evolution Portefeuill'!$H$22)+BE$90*'Annexe B Plan commercial'!$G$31*Hypothèses!$G$58 -> 0 | BG40: =BF$40*(1-'Annexe G Evolution Portefeuill'!$H$22)+BF$90*'Annexe B Plan commercial'!$G$31*Hypothèses!$G$58 -> 0 | BH40: =BG$40*(1-'Annexe G Evolution Portefeuill'!$H$22)+BG$90*'Annexe B Plan commercial'!$G$31*Hypothèses!$G$58 -> 0 | BI40: =BH$40*(1-'Annexe G Evolution Portefeuill'!$H$22)+BH$90*'Annexe B Plan commercial'!$G$31*Hypothèses!$G$58 -> 0 | BJ40: =BI$40*(1-'Annexe G Evolution Portefeuill'!$H$22)+BI$90*'Annexe B Plan commercial'!$G$31*Hypothèses!$G$58 -> 0 | BK40: =BJ$40*(1-'Annexe G Evolution Portefeuill'!$H$22)+BJ$90*'Annexe B Plan commercial'!$G$31*Hypothèses!$G$58 -> 0 | BL40: =BK$40*(1-'Annexe G Evolution Portefeuill'!$H$22)+BK$90*'Annexe B Plan commercial'!$G$31*Hypothèses!$G$58 -> 0 | BM40: =BL$40*(1-'Annexe G Evolution Portefeuill'!$H$22)+BL$90*'Annexe B Plan commercial'!$G$31*Hypothèses!$G$58 -> 0 | ... BQ40: =BP$40*(1-'Annexe G Evolution Portefeuill'!$H$22)+BP$90*'Annexe B Plan commercial'!$G$31*Hypothèses!$G$58 -> 0 | BR40: =BQ$40*(1-'Annexe G Evolution Portefeuill'!$I$22)+BQ$90*'Annexe B Plan commercial'!$H$31*Hypothèses!$H$58 -> 0 | BS40: =BR$40*(1-'Annexe G Evolution Portefeuill'!$I$22)+BR$90*'Annexe B Plan commercial'!$H$31*Hypothèses!$H$58 -> 0 | BT40: =BS$40*(1-'Annexe G Evolution Portefeuill'!$I$22)+BS$90*'Annexe B Plan commercial'!$H$31*Hypothèses!$H$58 -> 0 | BU40: =BT$40*(1-'Annexe G Evolution Portefeuill'!$I$22)+BT$90*'Annexe B Plan commercial'!$H$31*Hypothèses!$H$58 -> 0 | BV40: =BU$40*(1-'Annexe G Evolution Portefeuill'!$I$22)+BU$90*'Annexe B Plan commercial'!$H$31*Hypothèses!$H$58 -> 0 | BW40: =BV$40*(1-'Annexe G Evolution Portefeuill'!$I$22)+BV$90*'Annexe B Plan commercial'!$H$31*Hypothèses!$H$58 -> 0 | BX40: =BW$40*(1-'Annexe G Evolution Portefeuill'!$I$22)+BW$90*'Annexe B Plan commercial'!$H$31*Hypothèses!$H$58 -> 0 | BY40: =BX$40*(1-'Annexe G Evolution Portefeuill'!$I$22)+BX$90*'Annexe B Plan commercial'!$H$31*Hypothèses!$H$58 -> 0 | ... CC40: =CB$40*(1-'Annexe G Evolution Portefeuill'!$I$22)+CB$90*'Annexe B Plan commercial'!$H$31*Hypothèses!$H$58 -> 0
A42: Upsell Leads v1 | C42: =SUM(C43:C47) -> 8.3475 | D42: =SUM(D43:D47) -> 8.992034 | E42: =SUM(E43:E47) -> 9.6519196 | F42: =SUM(F43:F47) -> 10.326695 | G42: =SUM(G43:G47) -> 11.015915 | H42: =SUM(H43:H47) -> 11.719144 | I42: =SUM(I43:I47) -> 12.435964 | J42: =SUM(J43:J47) -> 14.257353 | ... CC42: =SUM(CC43:CC47) -> 850.35095
A43: dt FR | C43: =(C22+C29+C36)*(Hypothèses!$B$71+(Hypothèses!$C$71-Hypothèses!$B$71)*MONTH(C$2)/12) -> 8.3475 | D43: =(D22+D29+D36)*(Hypothèses!$B$71+(Hypothèses!$C$71-Hypothèses!$B$71)*MONTH(D$2)/12) -> 8.992034 | E43: =(E22+E29+E36)*(Hypothèses!$B$71+(Hypothèses!$C$71-Hypothèses!$B$71)*MONTH(E$2)/12) -> 9.6519196 | F43: =(F22+F29+F36)*(Hypothèses!$B$71+(Hypothèses!$C$71-Hypothèses!$B$71)*MONTH(F$2)/12) -> 10.326695 | G43: =(G22+G29+G36)*(Hypothèses!$B$71+(Hypothèses!$C$71-Hypothèses!$B$71)*MONTH(G$2)/12) -> 11.015915 | H43: =(H22+H29+H36)*(Hypothèses!$B$71+(Hypothèses!$C$71-Hypothèses!$B$71)*MONTH(H$2)/12) -> 11.719144 | I43: =(I22+I29+I36)*(Hypothèses!$B$71+(Hypothèses!$C$71-Hypothèses!$B$71)*MONTH(I$2)/12) -> 12.435964 | J43: =(J22+J29+J36)*(Hypothèses!$C$71+(Hypothèses!$D$71-Hypothèses!$C$71)*MONTH(J$2)/12) -> 14.257353 | K43: =(K22+K29+K36)*(Hypothèses!$C$71+(Hypothèses!$D$71-Hypothèses!$C$71)*MONTH(K$2)/12) -> 16.180579 | L43: =(L22+L29+L36)*(Hypothèses!$C$71+(Hypothèses!$D$71-Hypothèses!$C$71)*MONTH(L$2)/12) -> 17.877233 | M43: =(M22+M29+M36)*(Hypothèses!$C$71+(Hypothèses!$D$71-Hypothèses!$C$71)*MONTH(M$2)/12) -> 19.90336 | N43: =(N22+N29+N36)*(Hypothèses!$C$71+(Hypothèses!$D$71-Hypothèses!$C$71)*MONTH(N$2)/12) -> 21.989716 | O43: =(O22+O29+O36)*(Hypothèses!$C$71+(Hypothèses!$D$71-Hypothèses!$C$71)*MONTH(O$2)/12) -> 24.134908 | P43: =(P22+P29+P36)*(Hypothèses!$C$71+(Hypothèses!$D$71-Hypothèses!$C$71)*MONTH(P$2)/12) -> 26.33758 | Q43: =(Q22+Q29+Q36)*(Hypothèses!$C$71+(Hypothèses!$D$71-Hypothèses!$C$71)*MONTH(Q$2)/12) -> 28.783602 | ... U43: =(U22+U29+U36)*(Hypothèses!$C$71+(Hypothèses!$D$71-Hypothèses!$C$71)*MONTH(U$2)/12) -> 39.292764 | V43: =(V22+V29+V36)*(Hypothèses!$D$71+(Hypothèses!$E$71-Hypothèses!$D$71)*MONTH(V$2)/12) -> 42.85409 | W43: =(W22+W29+W36)*(Hypothèses!$D$71+(Hypothèses!$E$71-Hypothèses!$D$71)*MONTH(W$2)/12) -> 46.521626 | X43: =(X22+X29+X36)*(Hypothèses!$D$71+(Hypothèses!$E$71-Hypothèses!$D$71)*MONTH(X$2)/12) -> 50.293513 | Y43: =(Y22+Y29+Y36)*(Hypothèses!$D$71+(Hypothèses!$E$71-Hypothèses!$D$71)*MONTH(Y$2)/12) -> 54.167925 | Z43: =(Z22+Z29+Z36)*(Hypothèses!$D$71+(Hypothèses!$E$71-Hypothèses!$D$71)*MONTH(Z$2)/12) -> 58.143072 | AA43: =(AA22+AA29+AA36)*(Hypothèses!$D$71+(Hypothèses!$E$71-Hypothèses!$D$71)*MONTH(AA$2)/12) -> 62.217196 | AB43: =(AB22+AB29+AB36)*(Hypothèses!$D$71+(Hypothèses!$E$71-Hypothèses!$D$71)*MONTH(AB$2)/12) -> 66.388573 | AC43: =(AC22+AC29+AC36)*(Hypothèses!$D$71+(Hypothèses!$E$71-Hypothèses!$D$71)*MONTH(AC$2)/12) -> 70.834907 | ... AG43: =(AG22+AG29+AG36)*(Hypothèses!$D$71+(Hypothèses!$E$71-Hypothèses!$D$71)*MONTH(AG$2)/12) -> 89.665936 | AH43: =(AH22+AH29+AH36)*(Hypothèses!$E$71+(Hypothèses!$F$71-Hypothèses!$E$71)*MONTH(AH$2)/12) -> 93.949294 | AI43: =(AI22+AI29+AI36)*(Hypothèses!$E$71+(Hypothèses!$F$71-Hypothèses!$E$71)*MONTH(AI$2)/12) -> 98.313842 | AJ43: =(AJ22+AJ29+AJ36)*(Hypothèses!$E$71+(Hypothèses!$F$71-Hypothèses!$E$71)*MONTH(AJ$2)/12) -> 102.75848 | AK43: =(AK22+AK29+AK36)*(Hypothèses!$E$71+(Hypothèses!$F$71-Hypothèses!$E$71)*MONTH(AK$2)/12) -> 107.28214 | AL43: =(AL22+AL29+AL36)*(Hypothèses!$E$71+(Hypothèses!$F$71-Hypothèses!$E$71)*MONTH(AL$2)/12) -> 111.88374 | AM43: =(AM22+AM29+AM36)*(Hypothèses!$E$71+(Hypothèses!$F$71-Hypothèses!$E$71)*MONTH(AM$2)/12) -> 116.56223 | AN43: =(AN22+AN29+AN36)*(Hypothèses!$E$71+(Hypothèses!$F$71-Hypothèses!$E$71)*MONTH(AN$2)/12) -> 121.31657 | AO43: =(AO22+AO29+AO36)*(Hypothèses!$E$71+(Hypothèses!$F$71-Hypothèses!$E$71)*MONTH(AO$2)/12) -> 126.14574 | ... AS43: =(AS22+AS29+AS36)*(Hypothèses!$E$71+(Hypothèses!$F$71-Hypothèses!$E$71)*MONTH(AS$2)/12) -> 146.19058 | AT43: =(AT22+AT29+AT36)*(Hypothèses!$F$71+(Hypothèses!$G$71-Hypothèses!$F$71)*MONTH(AT$2)/12) -> 149.41109 | AU43: =(AU22+AU29+AU36)*(Hypothèses!$F$71+(Hypothèses!$G$71-Hypothèses!$F$71)*MONTH(AU$2)/12) -> 152.64851 | AV43: =(AV22+AV29+AV36)*(Hypothèses!$F$71+(Hypothèses!$G$71-Hypothèses!$F$71)*MONTH(AV$2)/12) -> 155.90255 | AW43: =(AW22+AW29+AW36)*(Hypothèses!$F$71+(Hypothèses!$G$71-Hypothèses!$F$71)*MONTH(AW$2)/12) -> 159.17294 | AX43: =(AX22+AX29+AX36)*(Hypothèses!$F$71+(Hypothèses!$G$71-Hypothèses!$F$71)*MONTH(AX$2)/12) -> 162.4594 | AY43: =(AY22+AY29+AY36)*(Hypothèses!$F$71+(Hypothèses!$G$71-Hypothèses!$F$71)*MONTH(AY$2)/12) -> 165.76167 | AZ43: =(AZ22+AZ29+AZ36)*(Hypothèses!$F$71+(Hypothèses!$G$71-Hypothèses!$F$71)*MONTH(AZ$2)/12) -> 169.07948 | BA43: =(BA22+BA29+BA36)*(Hypothèses!$F$71+(Hypothèses!$G$71-Hypothèses!$F$71)*MONTH(BA$2)/12) -> 173.15355 | ... BE43: =(BE22+BE29+BE36)*(Hypothèses!$F$71+(Hypothèses!$G$71-Hypothèses!$F$71)*MONTH(BE$2)/12) -> 189.6127 | BF43: =(BF22+BF29+BF36)*(Hypothèses!$G$71+(Hypothèses!$H$71-Hypothèses!$G$71)*MONTH(BF$2)/12) -> 192.70452 | BG43: =(BG22+BG29+BG36)*(Hypothèses!$G$71+(Hypothèses!$H$71-Hypothèses!$G$71)*MONTH(BG$2)/12) -> 195.7738 | BH43: =(BH22+BH29+BH36)*(Hypothèses!$G$71+(Hypothèses!$H$71-Hypothèses!$G$71)*MONTH(BH$2)/12) -> 200.18572 | BI43: =(BI22+BI29+BI36)*(Hypothèses!$G$71+(Hypothèses!$H$71-Hypothèses!$G$71)*MONTH(BI$2)/12) -> 204.56208 | BJ43: =(BJ22+BJ29+BJ36)*(Hypothèses!$G$71+(Hypothèses!$H$71-Hypothèses!$G$71)*MONTH(BJ$2)/12) -> 211.63326 | BK43: =(BK22+BK29+BK36)*(Hypothèses!$G$71+(Hypothèses!$H$71-Hypothèses!$G$71)*MONTH(BK$2)/12) -> 221.37286 | BL43: =(BL22+BL29+BL36)*(Hypothèses!$G$71+(Hypothèses!$H$71-Hypothèses!$G$71)*MONTH(BL$2)/12) -> 231.02483 | BM43: =(BM22+BM29+BM36)*(Hypothèses!$G$71+(Hypothèses!$H$71-Hypothèses!$G$71)*MONTH(BM$2)/12) -> 241.03882 | ... BQ43: =(BQ22+BQ29+BQ36)*(Hypothèses!$G$71+(Hypothèses!$H$71-Hypothèses!$G$71)*MONTH(BQ$2)/12) -> 280.20671 | BR43: =(BR22+BR29+BR36)*(Hypothèses!$H$71) -> 289.75108 | BS43: =(BS22+BS29+BS36)*(Hypothèses!$H$71) -> 299.20847 | BT43: =(BT22+BT29+BT36)*(Hypothèses!$H$71) -> 308.5799 | BU43: =(BU22+BU29+BU36)*(Hypothèses!$H$71) -> 317.86637 | BV43: =(BV22+BV29+BV36)*(Hypothèses!$H$71) -> 327.06887 | BW43: =(BW22+BW29+BW36)*(Hypothèses!$H$71) -> 336.18838 | BX43: =(BX22+BX29+BX36)*(Hypothèses!$H$71) -> 345.22587 | BY43: =(BY22+BY29+BY36)*(Hypothèses!$H$71) -> 366.35001 | ... CC43: =(CC22+CC29+CC36)*(Hypothèses!$H$71) -> 454.25088
A44: dt ES | C44: =(C23+C30+C37)*(Hypothèses!$B$71+(Hypothèses!$C$71-Hypothèses!$B$71)*MONTH(C$2)/12) -> 0 | D44: =(D23+D30+D37)*(Hypothèses!$B$71+(Hypothèses!$C$71-Hypothèses!$B$71)*MONTH(D$2)/12) -> 0 | E44: =(E23+E30+E37)*(Hypothèses!$B$71+(Hypothèses!$C$71-Hypothèses!$B$71)*MONTH(E$2)/12) -> 0 | F44: =(F23+F30+F37)*(Hypothèses!$B$71+(Hypothèses!$C$71-Hypothèses!$B$71)*MONTH(F$2)/12) -> 0 | G44: =(G23+G30+G37)*(Hypothèses!$B$71+(Hypothèses!$C$71-Hypothèses!$B$71)*MONTH(G$2)/12) -> 0 | H44: =(H23+H30+H37)*(Hypothèses!$B$71+(Hypothèses!$C$71-Hypothèses!$B$71)*MONTH(H$2)/12) -> 0 | I44: =(I23+I30+I37)*(Hypothèses!$B$71+(Hypothèses!$C$71-Hypothèses!$B$71)*MONTH(I$2)/12) -> 0 | J44: =(J23+J30+J37)*(Hypothèses!$C$71+(Hypothèses!$D$71-Hypothèses!$C$71)*MONTH(J$2)/12) -> 0 | K44: =(K23+K30+K37)*(Hypothèses!$C$71+(Hypothèses!$D$71-Hypothèses!$C$71)*MONTH(K$2)/12) -> 0 | L44: =(L23+L30+L37)*(Hypothèses!$C$71+(Hypothèses!$D$71-Hypothèses!$C$71)*MONTH(L$2)/12) -> 0 | M44: =(M23+M30+M37)*(Hypothèses!$C$71+(Hypothèses!$D$71-Hypothèses!$C$71)*MONTH(M$2)/12) -> 0 | N44: =(N23+N30+N37)*(Hypothèses!$C$71+(Hypothèses!$D$71-Hypothèses!$C$71)*MONTH(N$2)/12) -> 0 | O44: =(O23+O30+O37)*(Hypothèses!$C$71+(Hypothèses!$D$71-Hypothèses!$C$71)*MONTH(O$2)/12) -> 0 | P44: =(P23+P30+P37)*(Hypothèses!$C$71+(Hypothèses!$D$71-Hypothèses!$C$71)*MONTH(P$2)/12) -> 0 | Q44: =(Q23+Q30+Q37)*(Hypothèses!$C$71+(Hypothèses!$D$71-Hypothèses!$C$71)*MONTH(Q$2)/12) -> 0 | ... U44: =(U23+U30+U37)*(Hypothèses!$C$71+(Hypothèses!$D$71-Hypothèses!$C$71)*MONTH(U$2)/12) -> 0 | V44: =(V23+V30+V37)*(Hypothèses!$D$71+(Hypothèses!$E$71-Hypothèses!$D$71)*MONTH(V$2)/12) -> 0 | W44: =(W23+W30+W37)*(Hypothèses!$D$71+(Hypothèses!$E$71-Hypothèses!$D$71)*MONTH(W$2)/12) -> 0 | X44: =(X23+X30+X37)*(Hypothèses!$D$71+(Hypothèses!$E$71-Hypothèses!$D$71)*MONTH(X$2)/12) -> 0 | Y44: =(Y23+Y30+Y37)*(Hypothèses!$D$71+(Hypothèses!$E$71-Hypothèses!$D$71)*MONTH(Y$2)/12) -> 0 | Z44: =(Z23+Z30+Z37)*(Hypothèses!$D$71+(Hypothèses!$E$71-Hypothèses!$D$71)*MONTH(Z$2)/12) -> 0 | AA44: =(AA23+AA30+AA37)*(Hypothèses!$D$71+(Hypothèses!$E$71-Hypothèses!$D$71)*MONTH(AA$2)/12) -> 0 | AB44: =(AB23+AB30+AB37)*(Hypothèses!$D$71+(Hypothèses!$E$71-Hypothèses!$D$71)*MONTH(AB$2)/12) -> 0 | AC44: =(AC23+AC30+AC37)*(Hypothèses!$D$71+(Hypothèses!$E$71-Hypothèses!$D$71)*MONTH(AC$2)/12) -> 0 | ... AG44: =(AG23+AG30+AG37)*(Hypothèses!$D$71+(Hypothèses!$E$71-Hypothèses!$D$71)*MONTH(AG$2)/12) -> 0 | AH44: =(AH23+AH30+AH37)*(Hypothèses!$E$71+(Hypothèses!$F$71-Hypothèses!$E$71)*MONTH(AH$2)/12) -> 0 | AI44: =(AI23+AI30+AI37)*(Hypothèses!$E$71+(Hypothèses!$F$71-Hypothèses!$E$71)*MONTH(AI$2)/12) -> 0 | AJ44: =(AJ23+AJ30+AJ37)*(Hypothèses!$E$71+(Hypothèses!$F$71-Hypothèses!$E$71)*MONTH(AJ$2)/12) -> 0 | AK44: =(AK23+AK30+AK37)*(Hypothèses!$E$71+(Hypothèses!$F$71-Hypothèses!$E$71)*MONTH(AK$2)/12) -> 0 | AL44: =(AL23+AL30+AL37)*(Hypothèses!$E$71+(Hypothèses!$F$71-Hypothèses!$E$71)*MONTH(AL$2)/12) -> 0 | AM44: =(AM23+AM30+AM37)*(Hypothèses!$E$71+(Hypothèses!$F$71-Hypothèses!$E$71)*MONTH(AM$2)/12) -> 0 | AN44: =(AN23+AN30+AN37)*(Hypothèses!$E$71+(Hypothèses!$F$71-Hypothèses!$E$71)*MONTH(AN$2)/12) -> 0 | AO44: =(AO23+AO30+AO37)*(Hypothèses!$E$71+(Hypothèses!$F$71-Hypothèses!$E$71)*MONTH(AO$2)/12) -> 0 | ... AS44: =(AS23+AS30+AS37)*(Hypothèses!$E$71+(Hypothèses!$F$71-Hypothèses!$E$71)*MONTH(AS$2)/12) -> 0 | AT44: =(AT23+AT30+AT37)*(Hypothèses!$F$71+(Hypothèses!$G$71-Hypothèses!$F$71)*MONTH(AT$2)/12) -> 0 | AU44: =(AU23+AU30+AU37)*(Hypothèses!$F$71+(Hypothèses!$G$71-Hypothèses!$F$71)*MONTH(AU$2)/12) -> 0 | AV44: =(AV23+AV30+AV37)*(Hypothèses!$F$71+(Hypothèses!$G$71-Hypothèses!$F$71)*MONTH(AV$2)/12) -> 0 | AW44: =(AW23+AW30+AW37)*(Hypothèses!$F$71+(Hypothèses!$G$71-Hypothèses!$F$71)*MONTH(AW$2)/12) -> 0 | AX44: =(AX23+AX30+AX37)*(Hypothèses!$F$71+(Hypothèses!$G$71-Hypothèses!$F$71)*MONTH(AX$2)/12) -> 0 | AY44: =(AY23+AY30+AY37)*(Hypothèses!$F$71+(Hypothèses!$G$71-Hypothèses!$F$71)*MONTH(AY$2)/12) -> 0 | AZ44: =(AZ23+AZ30+AZ37)*(Hypothèses!$F$71+(Hypothèses!$G$71-Hypothèses!$F$71)*MONTH(AZ$2)/12) -> 0 | BA44: =(BA23+BA30+BA37)*(Hypothèses!$F$71+(Hypothèses!$G$71-Hypothèses!$F$71)*MONTH(BA$2)/12) -> 0 | ... BE44: =(BE23+BE30+BE37)*(Hypothèses!$F$71+(Hypothèses!$G$71-Hypothèses!$F$71)*MONTH(BE$2)/12) -> 0 | BF44: =(BF23+BF30+BF37)*(Hypothèses!$G$71+(Hypothèses!$H$71-Hypothèses!$G$71)*MONTH(BF$2)/12) -> 0 | BG44: =(BG23+BG30+BG37)*(Hypothèses!$G$71+(Hypothèses!$H$71-Hypothèses!$G$71)*MONTH(BG$2)/12) -> 0 | BH44: =(BH23+BH30+BH37)*(Hypothèses!$G$71+(Hypothèses!$H$71-Hypothèses!$G$71)*MONTH(BH$2)/12) -> 1.365 | BI44: =(BI23+BI30+BI37)*(Hypothèses!$G$71+(Hypothèses!$H$71-Hypothèses!$G$71)*MONTH(BI$2)/12) -> 2.7162135 | BJ44: =(BJ23+BJ30+BJ37)*(Hypothèses!$G$71+(Hypothèses!$H$71-Hypothèses!$G$71)*MONTH(BJ$2)/12) -> 4.053829 | BK44: =(BK23+BK30+BK37)*(Hypothèses!$G$71+(Hypothèses!$H$71-Hypothèses!$G$71)*MONTH(BK$2)/12) -> 5.3780317 | BL44: =(BL23+BL30+BL37)*(Hypothèses!$G$71+(Hypothèses!$H$71-Hypothèses!$G$71)*MONTH(BL$2)/12) -> 6.6890033 | BM44: =(BM23+BM30+BM37)*(Hypothèses!$G$71+(Hypothèses!$H$71-Hypothèses!$G$71)*MONTH(BM$2)/12) -> 20.045998 | ... BQ44: =(BQ23+BQ30+BQ37)*(Hypothèses!$G$71+(Hypothèses!$H$71-Hypothèses!$G$71)*MONTH(BQ$2)/12) -> 72.145455 | BR44: =(BR23+BR30+BR37)*(Hypothèses!$H$71) -> 84.838905 | BS44: =(BS23+BS30+BS37)*(Hypothèses!$H$71) -> 98.769701 | BT44: =(BT23+BT30+BT37)*(Hypothèses!$H$71) -> 112.56053 | BU44: =(BU23+BU30+BU37)*(Hypothèses!$H$71) -> 126.21316 | BV44: =(BV23+BV30+BV37)*(Hypothèses!$H$71) -> 139.72932 | BW44: =(BW23+BW30+BW37)*(Hypothèses!$H$71) -> 153.11074 | BX44: =(BX23+BX30+BX37)*(Hypothèses!$H$71) -> 169.08909 | BY44: =(BY23+BY30+BY37)*(Hypothèses!$H$71) -> 190.23156 | ... CC44: =(CC23+CC30+CC37)*(Hypothèses!$H$71) -> 278.14444
A45: dt CH | C45: =(C24+C31+C38)*(Hypothèses!$B$71+(Hypothèses!$C$71-Hypothèses!$B$71)*MONTH(C$2)/12) -> 0 | D45: =(D24+D31+D38)*(Hypothèses!$B$71+(Hypothèses!$C$71-Hypothèses!$B$71)*MONTH(D$2)/12) -> 0 | E45: =(E24+E31+E38)*(Hypothèses!$B$71+(Hypothèses!$C$71-Hypothèses!$B$71)*MONTH(E$2)/12) -> 0 | F45: =(F24+F31+F38)*(Hypothèses!$B$71+(Hypothèses!$C$71-Hypothèses!$B$71)*MONTH(F$2)/12) -> 0 | G45: =(G24+G31+G38)*(Hypothèses!$B$71+(Hypothèses!$C$71-Hypothèses!$B$71)*MONTH(G$2)/12) -> 0 | H45: =(H24+H31+H38)*(Hypothèses!$B$71+(Hypothèses!$C$71-Hypothèses!$B$71)*MONTH(H$2)/12) -> 0 | I45: =(I24+I31+I38)*(Hypothèses!$B$71+(Hypothèses!$C$71-Hypothèses!$B$71)*MONTH(I$2)/12) -> 0 | J45: =(J24+J31+J38)*(Hypothèses!$C$71+(Hypothèses!$D$71-Hypothèses!$C$71)*MONTH(J$2)/12) -> 0 | K45: =(K24+K31+K38)*(Hypothèses!$C$71+(Hypothèses!$D$71-Hypothèses!$C$71)*MONTH(K$2)/12) -> 0 | L45: =(L24+L31+L38)*(Hypothèses!$C$71+(Hypothèses!$D$71-Hypothèses!$C$71)*MONTH(L$2)/12) -> 0 | M45: =(M24+M31+M38)*(Hypothèses!$C$71+(Hypothèses!$D$71-Hypothèses!$C$71)*MONTH(M$2)/12) -> 0 | N45: =(N24+N31+N38)*(Hypothèses!$C$71+(Hypothèses!$D$71-Hypothèses!$C$71)*MONTH(N$2)/12) -> 0 | O45: =(O24+O31+O38)*(Hypothèses!$C$71+(Hypothèses!$D$71-Hypothèses!$C$71)*MONTH(O$2)/12) -> 0 | P45: =(P24+P31+P38)*(Hypothèses!$C$71+(Hypothèses!$D$71-Hypothèses!$C$71)*MONTH(P$2)/12) -> 0 | Q45: =(Q24+Q31+Q38)*(Hypothèses!$C$71+(Hypothèses!$D$71-Hypothèses!$C$71)*MONTH(Q$2)/12) -> 0 | ... U45: =(U24+U31+U38)*(Hypothèses!$C$71+(Hypothèses!$D$71-Hypothèses!$C$71)*MONTH(U$2)/12) -> 0 | V45: =(V24+V31+V38)*(Hypothèses!$D$71+(Hypothèses!$E$71-Hypothèses!$D$71)*MONTH(V$2)/12) -> 0 | W45: =(W24+W31+W38)*(Hypothèses!$D$71+(Hypothèses!$E$71-Hypothèses!$D$71)*MONTH(W$2)/12) -> 0 | X45: =(X24+X31+X38)*(Hypothèses!$D$71+(Hypothèses!$E$71-Hypothèses!$D$71)*MONTH(X$2)/12) -> 0 | Y45: =(Y24+Y31+Y38)*(Hypothèses!$D$71+(Hypothèses!$E$71-Hypothèses!$D$71)*MONTH(Y$2)/12) -> 0 | Z45: =(Z24+Z31+Z38)*(Hypothèses!$D$71+(Hypothèses!$E$71-Hypothèses!$D$71)*MONTH(Z$2)/12) -> 0 | AA45: =(AA24+AA31+AA38)*(Hypothèses!$D$71+(Hypothèses!$E$71-Hypothèses!$D$71)*MONTH(AA$2)/12) -> 0 | AB45: =(AB24+AB31+AB38)*(Hypothèses!$D$71+(Hypothèses!$E$71-Hypothèses!$D$71)*MONTH(AB$2)/12) -> 0 | AC45: =(AC24+AC31+AC38)*(Hypothèses!$D$71+(Hypothèses!$E$71-Hypothèses!$D$71)*MONTH(AC$2)/12) -> 0 | ... AG45: =(AG24+AG31+AG38)*(Hypothèses!$D$71+(Hypothèses!$E$71-Hypothèses!$D$71)*MONTH(AG$2)/12) -> 0 | AH45: =(AH24+AH31+AH38)*(Hypothèses!$E$71+(Hypothèses!$F$71-Hypothèses!$E$71)*MONTH(AH$2)/12) -> 0 | AI45: =(AI24+AI31+AI38)*(Hypothèses!$E$71+(Hypothèses!$F$71-Hypothèses!$E$71)*MONTH(AI$2)/12) -> 0 | AJ45: =(AJ24+AJ31+AJ38)*(Hypothèses!$E$71+(Hypothèses!$F$71-Hypothèses!$E$71)*MONTH(AJ$2)/12) -> 0 | AK45: =(AK24+AK31+AK38)*(Hypothèses!$E$71+(Hypothèses!$F$71-Hypothèses!$E$71)*MONTH(AK$2)/12) -> 0 | AL45: =(AL24+AL31+AL38)*(Hypothèses!$E$71+(Hypothèses!$F$71-Hypothèses!$E$71)*MONTH(AL$2)/12) -> 0 | AM45: =(AM24+AM31+AM38)*(Hypothèses!$E$71+(Hypothèses!$F$71-Hypothèses!$E$71)*MONTH(AM$2)/12) -> 0 | AN45: =(AN24+AN31+AN38)*(Hypothèses!$E$71+(Hypothèses!$F$71-Hypothèses!$E$71)*MONTH(AN$2)/12) -> 0 | AO45: =(AO24+AO31+AO38)*(Hypothèses!$E$71+(Hypothèses!$F$71-Hypothèses!$E$71)*MONTH(AO$2)/12) -> 0 | ... AS45: =(AS24+AS31+AS38)*(Hypothèses!$E$71+(Hypothèses!$F$71-Hypothèses!$E$71)*MONTH(AS$2)/12) -> 0 | AT45: =(AT24+AT31+AT38)*(Hypothèses!$F$71+(Hypothèses!$G$71-Hypothèses!$F$71)*MONTH(AT$2)/12) -> 0 | AU45: =(AU24+AU31+AU38)*(Hypothèses!$F$71+(Hypothèses!$G$71-Hypothèses!$F$71)*MONTH(AU$2)/12) -> 0 | AV45: =(AV24+AV31+AV38)*(Hypothèses!$F$71+(Hypothèses!$G$71-Hypothèses!$F$71)*MONTH(AV$2)/12) -> 0 | AW45: =(AW24+AW31+AW38)*(Hypothèses!$F$71+(Hypothèses!$G$71-Hypothèses!$F$71)*MONTH(AW$2)/12) -> 0 | AX45: =(AX24+AX31+AX38)*(Hypothèses!$F$71+(Hypothèses!$G$71-Hypothèses!$F$71)*MONTH(AX$2)/12) -> 0 | AY45: =(AY24+AY31+AY38)*(Hypothèses!$F$71+(Hypothèses!$G$71-Hypothèses!$F$71)*MONTH(AY$2)/12) -> 0 | AZ45: =(AZ24+AZ31+AZ38)*(Hypothèses!$F$71+(Hypothèses!$G$71-Hypothèses!$F$71)*MONTH(AZ$2)/12) -> 0 | BA45: =(BA24+BA31+BA38)*(Hypothèses!$F$71+(Hypothèses!$G$71-Hypothèses!$F$71)*MONTH(BA$2)/12) -> 0 | ... BE45: =(BE24+BE31+BE38)*(Hypothèses!$F$71+(Hypothèses!$G$71-Hypothèses!$F$71)*MONTH(BE$2)/12) -> 0 | BF45: =(BF24+BF31+BF38)*(Hypothèses!$G$71+(Hypothèses!$H$71-Hypothèses!$G$71)*MONTH(BF$2)/12) -> 0 | BG45: =(BG24+BG31+BG38)*(Hypothèses!$G$71+(Hypothèses!$H$71-Hypothèses!$G$71)*MONTH(BG$2)/12) -> 0 | BH45: =(BH24+BH31+BH38)*(Hypothèses!$G$71+(Hypothèses!$H$71-Hypothèses!$G$71)*MONTH(BH$2)/12) -> 0 | BI45: =(BI24+BI31+BI38)*(Hypothèses!$G$71+(Hypothèses!$H$71-Hypothèses!$G$71)*MONTH(BI$2)/12) -> 0 | BJ45: =(BJ24+BJ31+BJ38)*(Hypothèses!$G$71+(Hypothèses!$H$71-Hypothèses!$G$71)*MONTH(BJ$2)/12) -> 0 | BK45: =(BK24+BK31+BK38)*(Hypothèses!$G$71+(Hypothèses!$H$71-Hypothèses!$G$71)*MONTH(BK$2)/12) -> 0 | BL45: =(BL24+BL31+BL38)*(Hypothèses!$G$71+(Hypothèses!$H$71-Hypothèses!$G$71)*MONTH(BL$2)/12) -> 0 | BM45: =(BM24+BM31+BM38)*(Hypothèses!$G$71+(Hypothèses!$H$71-Hypothèses!$G$71)*MONTH(BM$2)/12) -> 0 | ... BQ45: =(BQ24+BQ31+BQ38)*(Hypothèses!$G$71+(Hypothèses!$H$71-Hypothèses!$G$71)*MONTH(BQ$2)/12) -> 0 | BR45: =(BR24+BR31+BR38)*(Hypothèses!$H$71) -> 0 | BS45: =(BS24+BS31+BS38)*(Hypothèses!$H$71) -> 0 | BT45: =(BT24+BT31+BT38)*(Hypothèses!$H$71) -> 0 | BU45: =(BU24+BU31+BU38)*(Hypothèses!$H$71) -> 1.365 | BV45: =(BV24+BV31+BV38)*(Hypothèses!$H$71) -> 2.716077 | BW45: =(BW24+BW31+BW38)*(Hypothèses!$H$71) -> 4.053409 | BX45: =(BX24+BX31+BX38)*(Hypothèses!$H$71) -> 6.7421713 | BY45: =(BY24+BY31+BY38)*(Hypothèses!$H$71) -> 29.441718 | ... CC45: =(CC24+CC31+CC38)*(Hypothèses!$H$71) -> 117.95563
A46: dt BE | C46: =(C25+C32+C39)*(Hypothèses!$B$71+(Hypothèses!$C$71-Hypothèses!$B$71)*MONTH(C$2)/12) -> 0 | D46: =(D25+D32+D39)*(Hypothèses!$B$71+(Hypothèses!$C$71-Hypothèses!$B$71)*MONTH(D$2)/12) -> 0 | E46: =(E25+E32+E39)*(Hypothèses!$B$71+(Hypothèses!$C$71-Hypothèses!$B$71)*MONTH(E$2)/12) -> 0 | F46: =(F25+F32+F39)*(Hypothèses!$B$71+(Hypothèses!$C$71-Hypothèses!$B$71)*MONTH(F$2)/12) -> 0 | G46: =(G25+G32+G39)*(Hypothèses!$B$71+(Hypothèses!$C$71-Hypothèses!$B$71)*MONTH(G$2)/12) -> 0 | H46: =(H25+H32+H39)*(Hypothèses!$B$71+(Hypothèses!$C$71-Hypothèses!$B$71)*MONTH(H$2)/12) -> 0 | I46: =(I25+I32+I39)*(Hypothèses!$B$71+(Hypothèses!$C$71-Hypothèses!$B$71)*MONTH(I$2)/12) -> 0 | J46: =(J25+J32+J39)*(Hypothèses!$C$71+(Hypothèses!$D$71-Hypothèses!$C$71)*MONTH(J$2)/12) -> 0 | K46: =(K25+K32+K39)*(Hypothèses!$C$71+(Hypothèses!$D$71-Hypothèses!$C$71)*MONTH(K$2)/12) -> 0 | L46: =(L25+L32+L39)*(Hypothèses!$C$71+(Hypothèses!$D$71-Hypothèses!$C$71)*MONTH(L$2)/12) -> 0 | M46: =(M25+M32+M39)*(Hypothèses!$C$71+(Hypothèses!$D$71-Hypothèses!$C$71)*MONTH(M$2)/12) -> 0 | N46: =(N25+N32+N39)*(Hypothèses!$C$71+(Hypothèses!$D$71-Hypothèses!$C$71)*MONTH(N$2)/12) -> 0 | O46: =(O25+O32+O39)*(Hypothèses!$C$71+(Hypothèses!$D$71-Hypothèses!$C$71)*MONTH(O$2)/12) -> 0 | P46: =(P25+P32+P39)*(Hypothèses!$C$71+(Hypothèses!$D$71-Hypothèses!$C$71)*MONTH(P$2)/12) -> 0 | Q46: =(Q25+Q32+Q39)*(Hypothèses!$C$71+(Hypothèses!$D$71-Hypothèses!$C$71)*MONTH(Q$2)/12) -> 0 | ... U46: =(U25+U32+U39)*(Hypothèses!$C$71+(Hypothèses!$D$71-Hypothèses!$C$71)*MONTH(U$2)/12) -> 0 | V46: =(V25+V32+V39)*(Hypothèses!$D$71+(Hypothèses!$E$71-Hypothèses!$D$71)*MONTH(V$2)/12) -> 0 | W46: =(W25+W32+W39)*(Hypothèses!$D$71+(Hypothèses!$E$71-Hypothèses!$D$71)*MONTH(W$2)/12) -> 0 | X46: =(X25+X32+X39)*(Hypothèses!$D$71+(Hypothèses!$E$71-Hypothèses!$D$71)*MONTH(X$2)/12) -> 0 | Y46: =(Y25+Y32+Y39)*(Hypothèses!$D$71+(Hypothèses!$E$71-Hypothèses!$D$71)*MONTH(Y$2)/12) -> 0 | Z46: =(Z25+Z32+Z39)*(Hypothèses!$D$71+(Hypothèses!$E$71-Hypothèses!$D$71)*MONTH(Z$2)/12) -> 0 | AA46: =(AA25+AA32+AA39)*(Hypothèses!$D$71+(Hypothèses!$E$71-Hypothèses!$D$71)*MONTH(AA$2)/12) -> 0 | AB46: =(AB25+AB32+AB39)*(Hypothèses!$D$71+(Hypothèses!$E$71-Hypothèses!$D$71)*MONTH(AB$2)/12) -> 0 | AC46: =(AC25+AC32+AC39)*(Hypothèses!$D$71+(Hypothèses!$E$71-Hypothèses!$D$71)*MONTH(AC$2)/12) -> 0 | ... AG46: =(AG25+AG32+AG39)*(Hypothèses!$D$71+(Hypothèses!$E$71-Hypothèses!$D$71)*MONTH(AG$2)/12) -> 0 | AH46: =(AH25+AH32+AH39)*(Hypothèses!$E$71+(Hypothèses!$F$71-Hypothèses!$E$71)*MONTH(AH$2)/12) -> 0 | AI46: =(AI25+AI32+AI39)*(Hypothèses!$E$71+(Hypothèses!$F$71-Hypothèses!$E$71)*MONTH(AI$2)/12) -> 0 | AJ46: =(AJ25+AJ32+AJ39)*(Hypothèses!$E$71+(Hypothèses!$F$71-Hypothèses!$E$71)*MONTH(AJ$2)/12) -> 0 | AK46: =(AK25+AK32+AK39)*(Hypothèses!$E$71+(Hypothèses!$F$71-Hypothèses!$E$71)*MONTH(AK$2)/12) -> 0 | AL46: =(AL25+AL32+AL39)*(Hypothèses!$E$71+(Hypothèses!$F$71-Hypothèses!$E$71)*MONTH(AL$2)/12) -> 0 | AM46: =(AM25+AM32+AM39)*(Hypothèses!$E$71+(Hypothèses!$F$71-Hypothèses!$E$71)*MONTH(AM$2)/12) -> 0 | AN46: =(AN25+AN32+AN39)*(Hypothèses!$E$71+(Hypothèses!$F$71-Hypothèses!$E$71)*MONTH(AN$2)/12) -> 0 | AO46: =(AO25+AO32+AO39)*(Hypothèses!$E$71+(Hypothèses!$F$71-Hypothèses!$E$71)*MONTH(AO$2)/12) -> 0 | ... AS46: =(AS25+AS32+AS39)*(Hypothèses!$E$71+(Hypothèses!$F$71-Hypothèses!$E$71)*MONTH(AS$2)/12) -> 0 | AT46: =(AT25+AT32+AT39)*(Hypothèses!$F$71+(Hypothèses!$G$71-Hypothèses!$F$71)*MONTH(AT$2)/12) -> 0 | AU46: =(AU25+AU32+AU39)*(Hypothèses!$F$71+(Hypothèses!$G$71-Hypothèses!$F$71)*MONTH(AU$2)/12) -> 0 | AV46: =(AV25+AV32+AV39)*(Hypothèses!$F$71+(Hypothèses!$G$71-Hypothèses!$F$71)*MONTH(AV$2)/12) -> 0 | AW46: =(AW25+AW32+AW39)*(Hypothèses!$F$71+(Hypothèses!$G$71-Hypothèses!$F$71)*MONTH(AW$2)/12) -> 0 | AX46: =(AX25+AX32+AX39)*(Hypothèses!$F$71+(Hypothèses!$G$71-Hypothèses!$F$71)*MONTH(AX$2)/12) -> 0 | AY46: =(AY25+AY32+AY39)*(Hypothèses!$F$71+(Hypothèses!$G$71-Hypothèses!$F$71)*MONTH(AY$2)/12) -> 0 | AZ46: =(AZ25+AZ32+AZ39)*(Hypothèses!$F$71+(Hypothèses!$G$71-Hypothèses!$F$71)*MONTH(AZ$2)/12) -> 0 | BA46: =(BA25+BA32+BA39)*(Hypothèses!$F$71+(Hypothèses!$G$71-Hypothèses!$F$71)*MONTH(BA$2)/12) -> 0 | ... BE46: =(BE25+BE32+BE39)*(Hypothèses!$F$71+(Hypothèses!$G$71-Hypothèses!$F$71)*MONTH(BE$2)/12) -> 0 | BF46: =(BF25+BF32+BF39)*(Hypothèses!$G$71+(Hypothèses!$H$71-Hypothèses!$G$71)*MONTH(BF$2)/12) -> 0 | BG46: =(BG25+BG32+BG39)*(Hypothèses!$G$71+(Hypothèses!$H$71-Hypothèses!$G$71)*MONTH(BG$2)/12) -> 0 | BH46: =(BH25+BH32+BH39)*(Hypothèses!$G$71+(Hypothèses!$H$71-Hypothèses!$G$71)*MONTH(BH$2)/12) -> 0 | BI46: =(BI25+BI32+BI39)*(Hypothèses!$G$71+(Hypothèses!$H$71-Hypothèses!$G$71)*MONTH(BI$2)/12) -> 0 | BJ46: =(BJ25+BJ32+BJ39)*(Hypothèses!$G$71+(Hypothèses!$H$71-Hypothèses!$G$71)*MONTH(BJ$2)/12) -> 0 | BK46: =(BK25+BK32+BK39)*(Hypothèses!$G$71+(Hypothèses!$H$71-Hypothèses!$G$71)*MONTH(BK$2)/12) -> 0 | BL46: =(BL25+BL32+BL39)*(Hypothèses!$G$71+(Hypothèses!$H$71-Hypothèses!$G$71)*MONTH(BL$2)/12) -> 0 | BM46: =(BM25+BM32+BM39)*(Hypothèses!$G$71+(Hypothèses!$H$71-Hypothèses!$G$71)*MONTH(BM$2)/12) -> 0 | ... BQ46: =(BQ25+BQ32+BQ39)*(Hypothèses!$G$71+(Hypothèses!$H$71-Hypothèses!$G$71)*MONTH(BQ$2)/12) -> 0 | BR46: =(BR25+BR32+BR39)*(Hypothèses!$H$71) -> 0 | BS46: =(BS25+BS32+BS39)*(Hypothèses!$H$71) -> 0 | BT46: =(BT25+BT32+BT39)*(Hypothèses!$H$71) -> 0 | BU46: =(BU25+BU32+BU39)*(Hypothèses!$H$71) -> 0 | BV46: =(BV25+BV32+BV39)*(Hypothèses!$H$71) -> 0 | BW46: =(BW25+BW32+BW39)*(Hypothèses!$H$71) -> 0 | BX46: =(BX25+BX32+BX39)*(Hypothèses!$H$71) -> 0 | BY46: =(BY25+BY32+BY39)*(Hypothèses!$H$71) -> 0 | ... CC46: =(CC25+CC32+CC39)*(Hypothèses!$H$71) -> 0
A47: dt DE | C47: =(C26+C33+C40)*(Hypothèses!$B$71+(Hypothèses!$C$71-Hypothèses!$B$71)*MONTH(C$2)/12) -> 0 | D47: =(D26+D33+D40)*(Hypothèses!$B$71+(Hypothèses!$C$71-Hypothèses!$B$71)*MONTH(D$2)/12) -> 0 | E47: =(E26+E33+E40)*(Hypothèses!$B$71+(Hypothèses!$C$71-Hypothèses!$B$71)*MONTH(E$2)/12) -> 0 | F47: =(F26+F33+F40)*(Hypothèses!$B$71+(Hypothèses!$C$71-Hypothèses!$B$71)*MONTH(F$2)/12) -> 0 | G47: =(G26+G33+G40)*(Hypothèses!$B$71+(Hypothèses!$C$71-Hypothèses!$B$71)*MONTH(G$2)/12) -> 0 | H47: =(H26+H33+H40)*(Hypothèses!$B$71+(Hypothèses!$C$71-Hypothèses!$B$71)*MONTH(H$2)/12) -> 0 | I47: =(I26+I33+I40)*(Hypothèses!$B$71+(Hypothèses!$C$71-Hypothèses!$B$71)*MONTH(I$2)/12) -> 0 | J47: =(J26+J33+J40)*(Hypothèses!$C$71+(Hypothèses!$D$71-Hypothèses!$C$71)*MONTH(J$2)/12) -> 0 | K47: =(K26+K33+K40)*(Hypothèses!$C$71+(Hypothèses!$D$71-Hypothèses!$C$71)*MONTH(K$2)/12) -> 0 | L47: =(L26+L33+L40)*(Hypothèses!$C$71+(Hypothèses!$D$71-Hypothèses!$C$71)*MONTH(L$2)/12) -> 0 | M47: =(M26+M33+M40)*(Hypothèses!$C$71+(Hypothèses!$D$71-Hypothèses!$C$71)*MONTH(M$2)/12) -> 0 | N47: =(N26+N33+N40)*(Hypothèses!$C$71+(Hypothèses!$D$71-Hypothèses!$C$71)*MONTH(N$2)/12) -> 0 | O47: =(O26+O33+O40)*(Hypothèses!$C$71+(Hypothèses!$D$71-Hypothèses!$C$71)*MONTH(O$2)/12) -> 0 | P47: =(P26+P33+P40)*(Hypothèses!$C$71+(Hypothèses!$D$71-Hypothèses!$C$71)*MONTH(P$2)/12) -> 0 | Q47: =(Q26+Q33+Q40)*(Hypothèses!$C$71+(Hypothèses!$D$71-Hypothèses!$C$71)*MONTH(Q$2)/12) -> 0 | ... U47: =(U26+U33+U40)*(Hypothèses!$C$71+(Hypothèses!$D$71-Hypothèses!$C$71)*MONTH(U$2)/12) -> 0 | V47: =(V26+V33+V40)*(Hypothèses!$D$71+(Hypothèses!$E$71-Hypothèses!$D$71)*MONTH(V$2)/12) -> 0 | W47: =(W26+W33+W40)*(Hypothèses!$D$71+(Hypothèses!$E$71-Hypothèses!$D$71)*MONTH(W$2)/12) -> 0 | X47: =(X26+X33+X40)*(Hypothèses!$D$71+(Hypothèses!$E$71-Hypothèses!$D$71)*MONTH(X$2)/12) -> 0 | Y47: =(Y26+Y33+Y40)*(Hypothèses!$D$71+(Hypothèses!$E$71-Hypothèses!$D$71)*MONTH(Y$2)/12) -> 0 | Z47: =(Z26+Z33+Z40)*(Hypothèses!$D$71+(Hypothèses!$E$71-Hypothèses!$D$71)*MONTH(Z$2)/12) -> 0 | AA47: =(AA26+AA33+AA40)*(Hypothèses!$D$71+(Hypothèses!$E$71-Hypothèses!$D$71)*MONTH(AA$2)/12) -> 0 | AB47: =(AB26+AB33+AB40)*(Hypothèses!$D$71+(Hypothèses!$E$71-Hypothèses!$D$71)*MONTH(AB$2)/12) -> 0 | AC47: =(AC26+AC33+AC40)*(Hypothèses!$D$71+(Hypothèses!$E$71-Hypothèses!$D$71)*MONTH(AC$2)/12) -> 0 | ... AG47: =(AG26+AG33+AG40)*(Hypothèses!$D$71+(Hypothèses!$E$71-Hypothèses!$D$71)*MONTH(AG$2)/12) -> 0 | AH47: =(AH26+AH33+AH40)*(Hypothèses!$E$71+(Hypothèses!$F$71-Hypothèses!$E$71)*MONTH(AH$2)/12) -> 0 | AI47: =(AI26+AI33+AI40)*(Hypothèses!$E$71+(Hypothèses!$F$71-Hypothèses!$E$71)*MONTH(AI$2)/12) -> 0 | AJ47: =(AJ26+AJ33+AJ40)*(Hypothèses!$E$71+(Hypothèses!$F$71-Hypothèses!$E$71)*MONTH(AJ$2)/12) -> 0 | AK47: =(AK26+AK33+AK40)*(Hypothèses!$E$71+(Hypothèses!$F$71-Hypothèses!$E$71)*MONTH(AK$2)/12) -> 0 | AL47: =(AL26+AL33+AL40)*(Hypothèses!$E$71+(Hypothèses!$F$71-Hypothèses!$E$71)*MONTH(AL$2)/12) -> 0 | AM47: =(AM26+AM33+AM40)*(Hypothèses!$E$71+(Hypothèses!$F$71-Hypothèses!$E$71)*MONTH(AM$2)/12) -> 0 | AN47: =(AN26+AN33+AN40)*(Hypothèses!$E$71+(Hypothèses!$F$71-Hypothèses!$E$71)*MONTH(AN$2)/12) -> 0 | AO47: =(AO26+AO33+AO40)*(Hypothèses!$E$71+(Hypothèses!$F$71-Hypothèses!$E$71)*MONTH(AO$2)/12) -> 0 | ... AS47: =(AS26+AS33+AS40)*(Hypothèses!$E$71+(Hypothèses!$F$71-Hypothèses!$E$71)*MONTH(AS$2)/12) -> 0 | AT47: =(AT26+AT33+AT40)*(Hypothèses!$F$71+(Hypothèses!$G$71-Hypothèses!$F$71)*MONTH(AT$2)/12) -> 0 | AU47: =(AU26+AU33+AU40)*(Hypothèses!$F$71+(Hypothèses!$G$71-Hypothèses!$F$71)*MONTH(AU$2)/12) -> 0 | AV47: =(AV26+AV33+AV40)*(Hypothèses!$F$71+(Hypothèses!$G$71-Hypothèses!$F$71)*MONTH(AV$2)/12) -> 0 | AW47: =(AW26+AW33+AW40)*(Hypothèses!$F$71+(Hypothèses!$G$71-Hypothèses!$F$71)*MONTH(AW$2)/12) -> 0 | AX47: =(AX26+AX33+AX40)*(Hypothèses!$F$71+(Hypothèses!$G$71-Hypothèses!$F$71)*MONTH(AX$2)/12) -> 0 | AY47: =(AY26+AY33+AY40)*(Hypothèses!$F$71+(Hypothèses!$G$71-Hypothèses!$F$71)*MONTH(AY$2)/12) -> 0 | AZ47: =(AZ26+AZ33+AZ40)*(Hypothèses!$F$71+(Hypothèses!$G$71-Hypothèses!$F$71)*MONTH(AZ$2)/12) -> 0 | BA47: =(BA26+BA33+BA40)*(Hypothèses!$F$71+(Hypothèses!$G$71-Hypothèses!$F$71)*MONTH(BA$2)/12) -> 0 | ... BE47: =(BE26+BE33+BE40)*(Hypothèses!$F$71+(Hypothèses!$G$71-Hypothèses!$F$71)*MONTH(BE$2)/12) -> 0 | BF47: =(BF26+BF33+BF40)*(Hypothèses!$G$71+(Hypothèses!$H$71-Hypothèses!$G$71)*MONTH(BF$2)/12) -> 0 | BG47: =(BG26+BG33+BG40)*(Hypothèses!$G$71+(Hypothèses!$H$71-Hypothèses!$G$71)*MONTH(BG$2)/12) -> 0 | BH47: =(BH26+BH33+BH40)*(Hypothèses!$G$71+(Hypothèses!$H$71-Hypothèses!$G$71)*MONTH(BH$2)/12) -> 0 | BI47: =(BI26+BI33+BI40)*(Hypothèses!$G$71+(Hypothèses!$H$71-Hypothèses!$G$71)*MONTH(BI$2)/12) -> 0 | BJ47: =(BJ26+BJ33+BJ40)*(Hypothèses!$G$71+(Hypothèses!$H$71-Hypothèses!$G$71)*MONTH(BJ$2)/12) -> 0 | BK47: =(BK26+BK33+BK40)*(Hypothèses!$G$71+(Hypothèses!$H$71-Hypothèses!$G$71)*MONTH(BK$2)/12) -> 0 | BL47: =(BL26+BL33+BL40)*(Hypothèses!$G$71+(Hypothèses!$H$71-Hypothèses!$G$71)*MONTH(BL$2)/12) -> 0 | BM47: =(BM26+BM33+BM40)*(Hypothèses!$G$71+(Hypothèses!$H$71-Hypothèses!$G$71)*MONTH(BM$2)/12) -> 0 | ... BQ47: =(BQ26+BQ33+BQ40)*(Hypothèses!$G$71+(Hypothèses!$H$71-Hypothèses!$G$71)*MONTH(BQ$2)/12) -> 0 | BR47: =(BR26+BR33+BR40)*(Hypothèses!$H$71) -> 0 | BS47: =(BS26+BS33+BS40)*(Hypothèses!$H$71) -> 0 | BT47: =(BT26+BT33+BT40)*(Hypothèses!$H$71) -> 0 | BU47: =(BU26+BU33+BU40)*(Hypothèses!$H$71) -> 0 | BV47: =(BV26+BV33+BV40)*(Hypothèses!$H$71) -> 0 | BW47: =(BW26+BW33+BW40)*(Hypothèses!$H$71) -> 0 | BX47: =(BX26+BX33+BX40)*(Hypothèses!$H$71) -> 0 | BY47: =(BY26+BY33+BY40)*(Hypothèses!$H$71) -> 0 | ... CC47: =(CC26+CC33+CC40)*(Hypothèses!$H$71) -> 0
A49: Autre Upsell
A51: Bureau d'études | C51: =C52+C59+C66 -> 47.7 | D51: =D52+D59+D66 -> 48.67868 | E51: =E52+E59+E66 -> 49.638444 | F51: =F52+F59+F66 -> 50.579733 | G51: =G52+G59+G66 -> 51.502977 | H51: =H52+H59+H66 -> 52.408594 | I51: =I52+I59+I66 -> 53.296989 | J51: =J52+J59+J66 -> 54.313725 | ... CC51: =CC52+CC59+CC66 -> 820.32424
A52: Optiwize Pro - Premium | C52: =C53+C54+C55 -> 15 | D52: =D53+D54+D55 -> 15.29895 | E52: =E53+E54+E55 -> 15.59491 | F52: =F53+F54+F55 -> 15.88791 | G52: =G53+G54+G55 -> 16.177981 | H52: =H53+H54+H55 -> 16.465151 | I52: =I53+I54+I55 -> 16.749449 | J52: =J53+J54+J55 -> 17.125623 | ... CC52: =CC53+CC54+CC55 -> 360.21052
